Workbook

Sheet All_Weather
B1: DBC | C1: COMT | D1: GLD | E1: IEF | F1: TLT | G1: VTI | H1: SPMO | I1: SHY | J1: TIP | K1: Cash GBP/CHF | L1: DBC | M1: COMT | N1: GLD | O1: IEF | P1: TLT | Q1: VTI | R1: SPMO | S1: SHY | T1: TIP | U1: GBP_USD | V1: CHF_USD | W1: Total Stock | X1: Tot Cash $ | Y1: Rem. Cash
A2: 43802 | B2: 20 | D2: 2 | E2: 5 | F2: 8 | G2: 10 | K2: 4000 | L2: 15.28 | N2: 139.3 | O2: 112.09 | P2: 141.5 | Q2: 159 | U2: 1.30038 | W2: =SUMPRODUCT(B2:G2,L2:Q2) -> 3866.65 | X2: =K2*U2 -> 5201.52 | Y2: =X2-W2 -> 1334.87
A3: 43471 | B3: 18 | D3: 2 | E3: 6 | F3: 9 | G3: 10 | K3: 2200 | L3: 16.245 | N3: 147.365 | O3: 111.415 | P3: 138.748 | Q3: 164.2 | U3: 1.31572 | W3: =SUMPRODUCT(B3:G3,L3:Q3) -> 4146.362 | X3: =K3*U3+Y2 -> 4229.454 | Y3: =X3-W3 -> 83.092
A4: 43865 | B4: 0 | D4: 2 | E4: 6 | F4: 9 | G4: 11 | K4: 4000 | N4: 146.115 | O4: 113.055 | P4: 143.325 | Q4: 167.6 | U4: 1.3012 | W4: =SUMPRODUCT(B4:G4,L4:Q4) -> 4104.085 | X4: =K4*U4+Y3 -> 5287.892 | Y4: =X4-W4 -> 1183.807
A5: 43895 | B5: 0 | D5: 2 | E5: 6 | F5: 9 | G5: 11 | K5: 4000 | N5: 157.165 | O5: 119.17 | P5: 157.675 | Q5: 152.97 | U5: 1.2945 | W5: =SUMPRODUCT(B5:G5,L5:Q5) -> 4131.095 | X5: =K5*U5+Y4 -> 6361.807 | Y5: =X5-W5 -> 2230.712
A6: 43920 | B6: =26*3 -> 78 | D6: 2 | E6: 5 | F6: 7 | G6: 12 | K6: 6000 | L6: =(11.325*73+11.335*5)/78 -> 11.325641 | N6: 151.865 | O6: 121.255 | P6: 166.31 | Q6: 130.67 | U6: 1.24027 | W6: =SUMPRODUCT(B6:G6,L6:Q6) -> 4525.615 | X6: =K6*U6+Y5 -> 9672.332 | Y6: =X6-W6 -> 5146.717
A7: 43920 | G7: 30 | Q7: 130.67 | U7: 1.24027 | W7: =SUMPRODUCT(B7:G7,L7:Q7) -> 3920.1 | X7: =K7*U7+Y6 -> 5146.717 | Y7: =X7-W7 -> 1226.617
A8: 43952 | B8: 28 | D8: 2 | E8: 5 | F8: 7 | G8: 11 | K8: 4000 | L8: 10.765 | N8: 159.63 | O8: 121.755 | P8: 167.44 | Q8: 142.35318 | U8: 1.25275 | W8: =SUMPRODUCT(B8:G8,L8:Q8) -> 3967.42 | X8: =K8*U8+Y7 -> 6237.617 | Y8: =X8-W8 -> 2270.197
A9: 43983 | B9: 25 | D9: 2 | E9: 5 | F9: 7 | G9: 10 | K9: 4000 | L9: 11.725 | N9: 162.96 | O9: 121.615 | P9: 162.095 | Q9: 153.575 | U9: 1.2394 | W9: =SUMPRODUCT(B9:G9,L9:Q9) -> 3897.535 | X9: =K9*U9+Y8 -> 7227.797 | Y9: =X9-W9 -> 3330.262
A10: 44014 | B10: 50 | D10: 3 | E10: 8 | F10: 12 | G10: 0 | K10: 1000 | L10: 12.485 | N10: 167.035 | O10: 121.685 | P10: 163.42 | Q10: 159.5 | U10: 1.24615 | W10: =SUMPRODUCT(B10:G10,L10:Q10) -> 4059.875 | X10: =K10*U10+Y9 -> 4576.412 | Y10: =X10-W10 -> 516.537
A11: 44074 | B11: 45 | D11: 2 | E11: 9 | F11: 11 | G11: 1 | K11: 2800 | L11: 12.89 | N11: 185.16 | O11: 122.75 | P11: 170.6 | Q11: 164.02 | U11: 1.31225 | W11: =SUMPRODUCT(B11:G11,L11:Q11) -> 4095.74 | X11: =K11*U11+Y10 -> 4190.837 | Y11: =X11-W11 -> 95.097
A12: 44081 | B12: 16 | D12: 2 | E12: 6 | F12: 9 | G12: 8 | K12: 4000 | L12: 12.785 | N12: 179.47 | O12: 121.755 | P12: =(1315.16+164.39)/9 -> 164.39444 | Q12: 170 | U12: 1.3167 | W12: =SUMPRODUCT(B12:G12,L12:Q12) -> 4133.58 | X12: =K12*U12+Y11 -> 5361.897 | Y12: =X12-W12 -> 1228.317
A13: 44110 | B13: 18 | D13: 1 | E13: 4 | F13: 11 | G13: 6 | K13: 3000 | L13: 13.145 | N13: 177.78 | O13: 121.265 | P13: 160.83 | Q13: =(171.8*5+171.83*1)/6 -> 171.805 | U13: 1.29065 | W13: =SUMPRODUCT(B13:G13,L13:Q13) -> 3699.41 | X13: =K13*U13+Y12 -> 5100.267 | Y13: =X13-W13 -> 1400.857
A14: 44141 | B14: 29 | D14: 2 | E14: 6 | F14: 8 | G14: 8 | K14: 3000 | L14: 13.105 | N14: 183.345 | O14: 120.535 | P14: 159.68 | Q14: =(179.355+179.43)/2 -> 179.3925 | U14: 1.3157 | W14: =SUMPRODUCT(B14:G14,L14:Q14) -> 4182.525 | X14: =K14*U14+Y13 -> 5347.957 | Y14: =X14-W14 -> 1165.432
A15: 44169 | B15: 6 | D15: 3 | E15: 7 | F15: 14 | G15: 3 | K15: 3000 | L15: 14.09 | N15: 172.26 | O15: 119.34 | P15: 155.34 | Q15: 190.97 | U15: 1.3489 | W15: =SUMPRODUCT(B15:G15,L15:Q15) -> 4184.37 | X15: =K15*U15+Y14 -> 5212.132 | Y15: =X15-W15 -> 1027.762
A16: 44200 | B16: 10 | D16: 1 | E16: 6 | F16: 7 | G16: 10 | K16: 4000 | L16: 14.685 | N16: 182.14 | O16: 120.02 | P16: 157.835 | Q16: 191.47 | U16: 1.35515 | W16: =SUMPRODUCT(B16:G16,L16:Q16) -> 4068.655 | X16: =K16*U16+Y15 -> 6448.362 | Y16: =X16-W16 -> 2379.707
A17: 44228 | D17: 4 | F17: 18 | K17: 10000 | L17: 16.77 | N17: =(160.72+160.775*3)/4 -> 160.76125 | O17: 115.17 | P17: 139.925 | Q17: 201.41 | U17: 1.39622 | W17: =SUMPRODUCT(B17:G17,L17:Q17) -> 3161.695 | X17: =K17*U17+Y16 -> 16341.907 | Y17: =X17-W17 -> 13180.212
A18: 44348 | B18: -54 | G18: -8 | L18: 18.905 | N18: 178.16 | O18: 114.29 | P18: 138.15 | Q18: 218.44 | W18: =SUMPRODUCT(B18:G18,L18:Q18) -> -2768.39 | X18: =K18*U18+Y17 -> 13180.212 | Y18: =X18-W18 -> 15948.602
A19: 44378 | E19: 11 | F19: 12 | O19: 114.285 | P19: 138.095 | W19: =SUMPRODUCT(B19:G19,L19:Q19) -> 2914.275 | Y19: =X19-W19 -> -2914.275
A20: 44397 | K20: 1000 | U20: 1.35915 | Y20: =X20-W20 -> 0
A21: 44432 | B21: 14 | D21: 2 | L21: 18.925 | N21: 169.015 | O21: 117.29 | P21: 149.56 | Q21: 231.03 | W21: =SUMPRODUCT(B21:G21,L21:Q21) -> 602.98 | Y21: =X21-W21 -> -602.98
A22: 44439 | K22: 3000 | U22: 1.3751 | X22: =K22*U22+Y21+K22*V22 -> 3522.32 | Y22: =X22-W22 -> 3522.32
A23: 44447 | K23: 3000 | U23: 1.3754 | X23: =K23*U23+Y22+K23*V23 -> 7648.52 | Y23: =X23-W23 -> 7648.52
A24: 44459 | K24: 2000 | U24: 1.3662 | X24: =K24*U24+Y23+K24*V24 -> 10380.92 | Y24: =X24-W24 -> 10380.92
A25: 44474 | B25: 0 | D25: 2 | E25: 8 | F25: 6 | G25: 9 | K25: 2000 | L25: 21.01 | N25: 163.76 | O25: 115.025 | P25: 143.655 | Q25: 224.62 | U25: 1.36275 | W25: =SUMPRODUCT(B25:G25,L25:Q25) -> 4131.23 | X25: =K25*U25+Y24+K25*V25 -> 13106.42 | Y25: =X25-W25 -> 8975.19
A26: 44474 | K26: 8900 | V26: 1.07695 | X26: =K26*U26+Y25+K26*V26 -> 18560.045 | Y26: =X26-W26 -> 18560.045
A27: 44491 | K27: 10000 | U27: 1.3782 | X27: =K27*U27+Y26+K27*V27 -> 32342.045 | Y27: =X27-W27 -> 32342.045
A28: 44491 | K28: 1100 | V28: 1.09235 | X28: =K28*U28+Y27+K28*V28 -> 33543.63 | Y28: =X28-W28 -> 33543.63
A29: 44498 | K29: 10000 | V29: 1.0961 | X29: =K29*U29+Y28+K29*V29 -> 44504.63 | Y29: =X29-W29 -> 44504.63
A30: 44503 | K30: 20000 | V30: =(1.09585+1.09485)/2 -> 1.09535 | X30: =K30*U30+Y29+K30*V30 -> 66411.63 | Y30: =X30-W30 -> 66411.63
A31: 44512 | D31: 1 | E31: 9 | F31: 11 | L31: 21.35 | N31: 174.185 | O31: 114.615 | P31: 147.335 | Q31: 241.4 | W31: =SUMPRODUCT(B31:G31,L31:Q31) -> 2826.405 | Y31: =X31-W31 -> -2826.405
A32: 44524 | K32: 3000 | V32: 1.0704 | X32: =K32*U32+Y31+K32*V32 -> 384.795 | Y32: =X32-W32 -> 384.795
A33: 44533 | E33: -3 | F33: -10 | O33: 116.34 | P33: 153.925 | W33: =SUMPRODUCT(B33:G33,L33:Q33) -> -1888.27 | X33: =K33*U33+Y32+K33*V33 -> 384.795 | Y33: =X33-W33 -> 2273.065
A34: 44533 | B34: 22 | D34: 1 | G34: 5 | L34: 19.54 | N34: 166.34 | Q34: 231.05 | W34: =SUMPRODUCT(B34:G34,L34:Q34) -> 1751.47 | Y34: =X34-W34 -> -1751.47
A35: 44594 | K35: 7000 | V35: 1.08855 | X35: =K35*U35+Y34+K35*V35-1.89 -> 5866.49 | Y35: =X35-W35 -> 5866.49
A36: 44615 | K36: 10000 | V36: 1.08925 | X36: =K36*U36+Y35+K36*V36-1.89 -> 16757.1 | Y36: =X36-W36 -> 16757.1
A37: 44690 | B37: -5 | L37: 26.99 | W37: =SUMPRODUCT(B37:G37,L37:Q37) -> -134.95 | Y37: =X37-W37 -> 134.95
A38: 44868 | V38: 0.987 | X38: =K38*U38+Y37+K38*V38-1.89 -> 133.06 | Y38: =X38-W38 -> 133.06
A39: 44911 | B39: -320 | L39: 24.26 | W39: =SUMPRODUCT(B39:G39,L39:Q39) -> -7763.2 | Y39: =X39-W39 -> 7763.2
A40: 44978 | C40: 197 | F40: 23 | M40: 27.47 | P40: 100.545 | W40: =SUMPRODUCT(B40:G40,L40:Q40) -> 7724.125 | Y40: =X40-W40 -> -7724.125
A41: 44986 | F41: 11 | G41: 6 | P41: 100.255 | Q41: 199 | W41: =SUMPRODUCT(B41:G41,L41:Q41) -> 2296.805 | Y41: =X41-W41 -> -2296.805
A42: 44986 | G42: -6 | Q42: 198.75 | W42: =SUMPRODUCT(B42:G42,L42:Q42) -> -1192.5 | Y42: =X42-W42 -> 1192.5
A43: 45009 | G43: 3 | Q43: 197 | W43: =SUMPRODUCT(B43:G43,L43:Q43) -> 591 | Y43: =X43-W43 -> -591
A44: 45044 | G44: 5 | Q44: 206 | W44: =SUMPRODUCT(B44:G44,L44:Q44) -> 1030 | Y44: =X44-W44 -> -1030
A45: 45138 | F45: 20 | G45: -9 | P45: 99.84 | Q45: 227.98 | W45: =SUMPRODUCT(B45:G45,L45:Q45) -> -55.02 | Y45: =X45-W45 -> 55.02
A46: 45516 | C46: 15 | E46: 12 | F46: 21 | G46: -13 | M46: 26.57 | O46: 96.93 | P46: 96.7 | Q46: 262.41 | W46: =SUMPRODUCT(B46:G46,L46:Q46) -> 181.08 | Y46: =X46-W46 -> -181.08
A47: 45804 | C47: 92 | D47: 11 | E47: -72 | F47: -132 | G47: -14 | I47: 70 | J47: 53 | M47: 25.04 | N47: 304.29 | O47: 94.21 | P47: 85.89 | Q47: 290.79 | S47: 82.53 | T47: 108.91 | W47: =SUMPRODUCT(B47:J47,L47:T47) -> -4991.46 | Y47: =X47-W47 -> 4991.46
A48: 45922 | G48: -60 | H48: 160 | Q48: 329.64 | R48: 122.08 | W48: =SUMPRODUCT(B48:J48,L48:T48) -> -245.6 | Y48: =X48-W48 -> 245.6
A50: Dividends | C50: 8 | E50: 1 | F50: 3
A52: Total Qty | B52: =SUM(B2:B51) -> 0 | C52: =SUM(C2:C51) -> 312 | D52: =SUM(D2:D51) -> 49 | E52: =SUM(E2:E51) -> 50 | F52: =SUM(F2:F51) -> 111 | G52: =SUM(G2:G51) -> 59 | H52: =SUM(H2:H51) -> 160 | I52: =SUM(I2:I51) -> 70 | J52: =SUM(J2:J51) -> 53 | K52: Total | N52: Portfolio return | P52: =(($K$53/SUM($W$2:W48))^(1/(DATEDIF(A2,A48,"M")+1)))^12-1 -> 0.052264903
A53: Total Amt | B53: =IFERROR(__xludf.DUMMYFUNCTION("B52*GOOGLEFINANCE(B1, ""price"")"),0.0) -> 0 | C53: =IFERROR(__xludf.DUMMYFUNCTION("C52*GOOGLEFINANCE(C1, ""price"")"),8417.76) -> 8417.76 | D53: =IFERROR(__xludf.DUMMYFUNCTION("D52*GOOGLEFINANCE(D1, ""price"")"),19006.12) -> 19006.12 | E53: =IFERROR(__xludf.DUMMYFUNCTION("E52*GOOGLEFINANCE(E1, ""price"")"),4875.0) -> 4875 | F53: =IFERROR(__xludf.DUMMYFUNCTION("F52*GOOGLEFINANCE(F1, ""price"")"),10013.31) -> 10013.31 | G53: =IFERROR(__xludf.DUMMYFUNCTION("G52*GOOGLEFINANCE(G1, ""price"")"),19842.29) -> 19842.29 | H53: =IFERROR(__xludf.DUMMYFUNCTION("H52*GOOGLEFINANCE(H1, ""price"")"),19219.2) -> 19219.2 | I53: =IFERROR(__xludf.DUMMYFUNCTION("I52*GOOGLEFINANCE(I1, ""price"")"),5815.599999999999) -> 5815.6 | J53: =IFERROR(__xludf.DUMMYFUNCTION("J52*GOOGLEFINANCE(J1, ""price"")"),5896.780000000001) -> 5896.78 | K53: =SUM(B53:J53) -> 93086.06
A54: % | B54: =B53/$K$53 -> 0 | C54: =C53/$K$53 -> 0.090429867 | D54: =D53/$K$53 -> 0.20417794 | E54: =E53/$K$53 -> 0.052370892 | F54: =F53/$K$53 -> 0.10757046 | G54: =G53/$K$53 -> 0.2131607 | I54: =I53/$K$53 -> 0.06247552 | J54: =J53/$K$53 -> 0.063347616 | K54: =SUM(B54:J54) -> 0.793533
A55: Target % | C55: 0.1 | D55: 0.15 | E55: 0.05 | F55: 0.1 | G55: 0.4 | I55: 0.075 | J55: 0.075 | K55: =SUM(B55:J55) -> 0.95
A56: Target amt | C56: =$K$56*C55 -> 10000 | D56: =$K$56*D55 -> 15000 | E56: =$K$56*E55 -> 5000 | F56: =$K$56*F55 -> 10000 | G56: =$K$56*G55 -> 40000 | I56: =$K$56*I55 -> 7500 | J56: =$K$56*J55 -> 7500 | K56: 100000
A57: Difference | C57: =C56-C53 -> 1582.24 | D57: =D56-D53 -> -4006.12 | E57: =E56-E53 -> 125 | F57: =F56-F53 -> -13.31 | G57: =G56-G53 -> 20157.71 | I57: =I56-I53 -> 1684.4 | J57: =J56-J53 -> 1603.22 | K57: =SUM(B57:F57) -> -2312.19
A59: Qty to buy | B59: -54.137818 | D59: -1.3886507 | E59: 11.436486 | F59: 11.907144 | G59: -7.710219 | I59: -7.710219 | J59: -7.710219
A60: Amt to spend | B60: =B59*L15 -> -762.80185 | D60: =D59*N15 -> -239.20896 | E60: =E59*O15 -> 1364.8303 | F60: =F59*P15 -> 1849.6558 | G60: =G59*Q15 -> -1472.4205 | I60: =I59*S15 -> 0 | J60: =J59*T15 -> 0 | K60: =SUM(B60:F60) -> 2212.4753
A62: New Qty | B62: =B52+ROUND(B59,0) -> -54 | D62: =D52+ROUND(D59,0) -> 48 | E62: =E52+ROUND(E59,0) -> 61 | F62: =F52+ROUND(F59,0) -> 123 | G62: =G52+ROUND(G59,0) -> 51 | I62: =I52+ROUND(I59,0) -> 62 | J62: =J52+ROUND(J59,0) -> 45
A63: New Amount | B63: =B62*L12 -> -690.39 | D63: =D62*N12 -> 8614.56 | E63: =E62*O12 -> 7427.055 | F63: =F62*P12 -> 20220.517 | G63: =G62*Q12 -> 8670 | I63: =I62*S12 -> 0 | J63: =J62*T12 -> 0 | K63: =SUM(B63:G63) -> 44241.742
A64: Actual % | B64: =B63/$K$63 -> -0.015604946 | D64: =D63/$K$63 -> 0.19471566 | E64: =E63/$K$63 -> 0.16787438 | F64: =F63/$K$63 -> 0.45704613 | G64: =G63/$K$63 -> 0.19596878 | I64: =I63/$K$63 -> 0 | J64: =J63/$K$63 -> 0 | K64: =SUM(B64:G64) -> 1
A70: VGLT is an alternative to TLT with better expense ratio. can buy those instead. No need to sell TLT, can have both for the time being as the difference is not huge.
A71: FNV is an alternative to GLD, this is streamer vs pure gold, can have them 50/50 as a split
A72: VNQ is Vanguard Real estate ETF (REIT), Consider STAG as better alternative with higher dividends and growth perspecive

Sheet Dividend portfolio
B1: Qty | O1: Price
A2: Date | B2: RIO | C2: CTO | D2: OBDC | E2: EPD | F2: HTGC | G2: ABR | H2: ARCC | I2: PDX | J2: IBM | K2: CVS | L2: VZ | M2: ABBV | N2: IIPR | O2: RIO | P2: CTO | Q2: OBDC | R2: EPD | S2: HTGC | T2: ABR | U2: ARCC | V2: PDX | W2: IBM | X2: CVS | Y2: VZ | Z2: ABBV | AA2: IIPR | AC2: Total
A3: 44491 | B3: 17 | C3: 63 | E3: 46 | F3: 64 | G3: 56 | I3: 85 | J3: 9 | L3: 21 | M3: 10 | O3: 66.145 | P3: 17.86 | R3: 24.275 | S3: 17.385 | T3: 19.775 | V3: 13.12 | W3: 129.7 | Y3: 53.185 | Z3: 108.76 | AC3: =SUMPRODUCT(O3:AA3,B3:N3) -> 10073.32
A4: 44498 | B4: 18 | C4: 60 | E4: 47 | F4: 63 | G4: 55 | I4: 85 | J4: 9 | L4: 21 | M4: 10 | O4: 63.4 | P4: 18.11 | R4: 22.945 | S4: 17.655 | T4: 20.195 | V4: 13.105 | W4: 125.72 | Y4: 52.845 | Z4: 114.37 | AC4: =SUMPRODUCT(O4:AA4,B4:N4) -> 10028.055
A5: 44503 | B5: 17 | C5: 60 | E5: 51 | F5: 62 | G5: 54 | I5: 83 | J5: 8 | L5: 21 | M5: 9 | O5: 61.68 | P5: 18.09 | R5: 22.195 | S5: 17.825 | T5: =(19.575*21+33*19.575)/54 -> 19.575 | V5: 13.285 | W5: 126.615 | Y5: 52.855 | Z5: 117.085 | AC5: =SUMPRODUCT(O5:AA5,B5:N5) -> 9707.4
A6: 44512 | B6: 7 | C6: 15 | E6: 16 | F6: 25 | G6: 26 | I6: 9 | J6: 5 | L6: 8 | M6: 3 | O6: 62.495 | P6: 18.61 | R6: 23.125 | S6: 17.185 | T6: 19.315 | V6: 14.145 | W6: 119.14 | Y6: 52.42 | Z6: 116.825 | AC6: =SUMPRODUCT(O6:AA6,B6:N6) -> 3511.27
A7: 44868 | N7: 46 | AA7: 114.7487 | AC7: =SUMPRODUCT(O7:AA7,B7:N7) -> 5278.4402
A8: 44869 | B8: 26 | C8: 55 | E8: 50 | F8: 120 | G8: 195 | I8: 65 | J8: 8 | L8: 70 | M8: 4 | N8: 1 | O8: 57.79154 | P8: 20.4 | R8: 24.85 | S8: 14.765 | T8: 14.405 | V8: 15.645 | W8: 136.385 | Y8: 36.985 | Z8: 143.93 | AA8: 111.075 | AC8: =SUMPRODUCT(O8:AA8,B8:N8) -> 13831.605
A9: 44911 | E9: -214 | R9: 23.552336 | AC9: =SUMPRODUCT(O9:AA9,B9:N9) -> -5040.2
A10: 44978 | C10: 57 | F10: 21 | I10: 55 | J10: 6 | L10: 9 | M10: 3 | N10: 25 | P10: 18.66 | S10: 15.635 | V10: 15.035 | W10: 131.91 | Y10: 39.22 | Z10: 151.86 | AA10: 83.61 | AC10: =SUMPRODUCT(O10:AA10,B10:N10) -> 5909.15
A11: 44929 | C11: 24 | F11: 9 | J11: 2 | L11: 5 | P11: 17.28 | S11: 15.265 | W11: 128 | Y11: 38.275 | AC11: =SUMPRODUCT(O11:AA11,B11:N11) -> 999.48
A12: 45009 | G12: 45 | T12: 11.135 | AC12: =SUMPRODUCT(O12:AA12,B12:N12) -> 501.075
A13: 45320 | B13: 6 | C13: 60 | G13: 12 | I13: -45 | J13: -8 | L13: 10 | M13: 5 | O13: 70.825 | P13: 16.88 | S13: 17.61 | T13: 14.265 | V13: 19.65 | W13: 186.32 | Y13: 41.86 | Z13: 164.59 | AA13: 96.16 | AC13: =SUMPRODUCT(O13:AA13,B13:N13) -> 475.67
A14: 45371 | B14: 14 | C14: 7 | F14: -39 | I14: -17 | J14: -1 | L14: 8 | M14: -3 | O14: 63.31 | P14: 16.69 | S14: 18.215 | V14: 20.765 | W14: 192.495 | Y14: 39.865 | Z14: 176.58 | AC14: =SUMPRODUCT(O14:AA14,B14:N14) -> -463.535
A15: 45712 | F15: -37 | I15: -374 | J15: -7 | M15: -1 | S15: 21.44 | V15: 25.3 | W15: 262.5 | Z15: 203.94 | AC15: =SUMPRODUCT(O15:AA15,B15:N15) -> -12296.92
A16: 45884 | G16: -600 | T16: 11 | AC16: =SUMPRODUCT(O16:AA16,B16:N16) -> -6600
A17: 45887 | H17: 300 | U17: 22.365 | AC17: =SUMPRODUCT(O17:AA17,B17:N17) -> 6709.5
A18: 45888 | C18: -484 | D18: 564 | G18: -52 | P18: 16.56863 | Q18: 14.165 | T18: 11.43 | AC18: =SUMPRODUCT(O18:AA18,B18:N18) -> -624.51692
A19: 45894 | J19: -32.4964 | K19: 100 | W19: 240.54753 | X19: 71.04 | AC19: =SUMPRODUCT(O19:AA19,B19:N19) -> -712.92875
A21: Dividends | B21: =17+5 -> 22 | C21: =66+8+9 -> 83 | E21: 4 | F21: =103+17 -> 120 | G21: =173+19+17 -> 209 | I21: 54 | J21: 1.4964 | L21: =20+3+3 -> 26 | M21: 1 | N21: =9+2+3 -> 14
A26: Qty | B26: =sum(B3:B25) -> 127 | C26: =sum(C3:C25) -> 0 | D26: =sum(D3:D25) -> 564 | E26: =sum(E3:E25) -> 0 | F26: =sum(F3:F25) -> 408 | G26: =sum(G3:G25) -> 0 | H26: =sum(H3:H25) -> 300 | I26: =sum(I3:I25) -> 0 | ... N26: =sum(N3:N25) -> 86 | P26: Invested | R26: Current value | S26: Gain | T26: IRR
B27: =IFERROR(__xludf.DUMMYFUNCTION("B26*GOOGLEFINANCE(B2, ""price"")"),9137.65) -> 9137.65 | C27: =IFERROR(__xludf.DUMMYFUNCTION("C26*GOOGLEFINANCE(C2, ""price"")"),0.0) -> 0 | D27: =IFERROR(__xludf.DUMMYFUNCTION("D26*GOOGLEFINANCE(D2, ""price"")"),7427.88) -> 7427.88 | E27: =IFERROR(__xludf.DUMMYFUNCTION("E26*GOOGLEFINANCE(E2, ""price"")"),0.0) -> 0 | F27: =IFERROR(__xludf.DUMMYFUNCTION("F26*GOOGLEFINANCE(F2, ""price"")"),7344.0) -> 7344 | G27: =IFERROR(__xludf.DUMMYFUNCTION("G26*GOOGLEFINANCE(G2, ""price"")"),0.0) -> 0 | H27: =IFERROR(__xludf.DUMMYFUNCTION("H26*GOOGLEFINANCE(H2, ""price"")"),6186.0) -> 6186 | I27: =IFERROR(__xludf.DUMMYFUNCTION("I26*GOOGLEFINANCE(I2, ""price"")"),0.0) -> 0 | J27: =IFERROR(__xludf.DUMMYFUNCTION("J26*GOOGLEFINANCE(J2, ""price"")"),-4.1111114512659697E-13) -> 0 | K27: =IFERROR(__xludf.DUMMYFUNCTION("K26*GOOGLEFINANCE(K2, ""price"")"),8036.0) -> 8036 | L27: =IFERROR(__xludf.DUMMYFUNCTION("L26*GOOGLEFINANCE(L2, ""price"")"),8180.89) -> 8180.89 | M27: =IFERROR(__xludf.DUMMYFUNCTION("M26*GOOGLEFINANCE(M2, ""price"")"),9335.699999999999) -> 9335.7 | N27: =IFERROR(__xludf.DUMMYFUNCTION("N26*GOOGLEFINANCE(N2, ""price"")"),4252.7) -> 4252.7 | P27: =sum(AC3:AC25)+722 -> 42008.865 | R27: =SUM(B27:N27) -> 59900.82 | S27: =R27-P27 -> 17891.955 | T27: =((R27/P27)^(1/YEARFRAC(A3, today()))) - 1 -> 0.090266115
A28: Current | B28: =B27/$R$27 -> 0.15254633 | C28: =C27/$R$27 -> 0 | D28: =D27/$R$27 -> 0.12400298 | E28: =E27/$R$27 -> 0 | F28: =F27/$R$27 -> 0.12260266 | G28: =G27/$R$27 -> 0 | H28: =H27/$R$27 -> 0.10327071 | I28: =I27/$R$27 -> 0 | ... N28: =N27/$R$27 -> 0.070995689
A29: Target | B29: =100%/(count(B26:N26)-1) -> 0.083333333 | C29: =B29 -> 0.083333333 | D29: =C29 -> 0.083333333 | E29: =C29 -> 0.083333333 | F29: =E29 -> 0.083333333 | G29: 0 | H29: 0.1 | I29: 0 | J29: 0.1 | K29: 0.1 | L29: =J29 -> 0.1 | M29: =L29 -> 0.1 | N29: =M29 -> 0.1
B31: =$O$31*B29 -> 4490.8333 | C31: =$O$31*C29 -> 4490.8333 | D31: =$O$31*D29 -> 4490.8333 | E31: =$O$31*E29 -> 4490.8333 | F31: =$O$31*F29 -> 4490.8333 | G31: =$O$31*G29 -> 0 | H31: =$O$31*H29 -> 5389 | I31: =$O$31*I29 -> 0 | J31: =$O$31*J29 -> 5389 | L31: =$O$31*L29 -> 5389 | M31: =$O$31*M29 -> 5389 | N31: =$O$31*N29 -> 5389 | O31: 53890
B32: =B31-B27 -> -4646.8167 | C32: =C31-C27 -> 4490.8333 | D32: =D31-D27 -> -2937.0467 | E32: =E31-E27 -> 4490.8333 | F32: =F31-F27 -> -2853.1667 | G32: =G31-G27 -> 0 | H32: =H31-H27 -> -797 | I32: =I31-I27 -> 0 | J32: =J31-J27 -> 5389 | L32: =L31-L27 -> -2791.89 | M32: =M31-M27 -> -3946.7 | N32: =N31-N27 -> 1136.3

Sheet Long Term
A1: GOOGL | B1: Qty | C1: Price | D1: Amount | E1: Comment | G1: Options P&L
A2: 44804 | B2: 22 | C2: 109.37 | D2: =B2*C2*-1 -> -2406.14 | H2: ASAN | I2: CROX | J2: GOOGL | K2: AAPL | L2: WING | M2: RCAT | N2: NVDA | O2: LHDX | P2: All others
A3: 44806 | B3: 100 | C3: 108 | D3: =B3*C3*-1 -> -10800 | G3: 2022 | H3: 3528 | I3: 228 | J3: 943 | O3: 667 | P3: -282 | Q3: =SUM(H3:P3) -> 5084
A4: 45341 | B4: -100 | C4: 140 | D4: =B4*C4*-1 -> 14000 | G4: 2023 | H4: 3805 | I4: 4275 | J4: 1019 | K4: 2040 | P4: -3940 | Q4: =SUM(H4:P4) -> 7199 | R4: =Q4/Q3-1 -> 0.41601101
A5: 45492 | B5: 100 | C5: 180 | D5: =B5*C5*-1 -> -18000 | E5: Put assigned | G5: 2024 | H5: =sumif('Options 2024'!B3:B108,"ASAN",'Options 2024'!Q3:Q108) -> 2591.2 | I5: =sumif('Options 2024'!B3:B108,"CROX",'Options 2024'!Q3:Q108) -> 3802.79 | J5: =sumif('Options 2024'!B3:B108,"GOOGL",'Options 2024'!Q3:Q108) -> 2617.79 | K5: =sumif('Options 2024'!B3:B108,"AAPL",'Options 2024'!Q3:Q108) -> 2708.72 | P5: =sum('Options 2024'!Q3:Q120)-sum(H5:K5) -> 228.19 | Q5: =SUM(H5:P5) -> 11948.69 | R5: =Q5/Q4-1 -> 0.6597708
A6: 45646 | B6: -100 | C6: 187.5 | D6: =B6*C6*-1 -> 18750 | G6: 2025 | H6: =sumif('Options 2025'!B3:B169,H2,'Options 2025'!Q3:Q168) -> 1088.45 | I6: =sumif('Options 2025'!B3:B169,I2,'Options 2025'!Q3:Q168) -> 2257.24 | J6: =sumif('Options 2025'!B3:B169,J2,'Options 2025'!Q3:Q168) -> 1150.44 | K6: =sumif('Options 2025'!B3:B169,K2,'Options 2025'!Q3:Q168) -> 1049.6 | L6: =sumif('Options 2025'!B3:B169,L2,'Options 2025'!Q3:Q168) -> 3300.7 | M6: =sumif('Options 2025'!$B3:$B169,M2,'Options 2025'!$Q3:$Q168) -> 2062.78 | N6: =sumif('Options 2025'!B3:B169,N2,'Options 2025'!Q3:Q168) -> 2006.85 | P6: =sum('Options 2025'!Q3:Q181)-sum(H6:N6) -> 11039.07 | Q6: =SUM(H6:P6) -> 23955.13 | R6: =Q6/Q5-1 -> 1.0048332
A7: 45678 | B7: 100 | C7: 180 | D7: =B7*C7*-1 -> -18000 | E7: Put assigned | G7: Total | H7: =SUM(H3:H6) -> 11012.65 | I7: =SUM(I3:I6) -> 10563.03 | J7: =SUM(J3:J6) -> 5730.23 | K7: =SUM(K3:K6) -> 5798.32 | L7: =SUM(L3:L6) -> 3300.7 | M7: =SUM(M3:M6) -> 2062.78 | N7: =SUM(N3:N6) -> 2006.85 | O7: =SUM(O3:O6) -> 667 | ... Q7: =SUM(Q3:Q6) -> 48186.82
B8: =SUM(B2:B7) -> 122 | D8: =SUM(D2:D7) -> -16456.14
G9: Stock P&L | H9: =IFERROR(__xludf.DUMMYFUNCTION("D30+B30*GOOGLEFINANCE(H2, ""price"")"),-11158.0) -> -11158 | I9: =IFERROR(__xludf.DUMMYFUNCTION("D63+GOOGLEFINANCE(I2, ""price"")*B63"),-3070.290000000001) -> -3070.29 | J9: =IFERROR(__xludf.DUMMYFUNCTION("D8+GOOGLEFINANCE(J2, ""price"")*B8"),22605.82) -> 22605.82 | K9: =IFERROR(__xludf.DUMMYFUNCTION("D121+GOOGLEFINANCE(K2,""Price"")*B121"),7385.000000000004) -> 7385 | L9: =IFERROR(__xludf.DUMMYFUNCTION("D66+GOOGLEFINANCE(L2,""Price"")*B66"),4473.0) -> 4473 | M9: =IFERROR(__xludf.DUMMYFUNCTION("D80+GOOGLEFINANCE(M2,""Price"")*B80"),-840.0) -> -840 | N9: =IFERROR(__xludf.DUMMYFUNCTION("D74+GOOGLEFINANCE(N2,""Price"")*B74"),5698.0) -> 5698 | O9: =D169 -> -10112.52 | Q9: =SUM(H9:P9) -> 14981.01
A10: ASAN | B10: Qty | C10: Price | D10: Amount | E10: Comment
A11: 44592 | B11: 45 | C11: 52.08 | D11: =B11*C11*-1 -> -2343.6 | E11: Put assignment | G11: Grand total | H11: =H7+H9 -> -145.35 | I11: =I7+I9 -> 7492.74 | J11: =J7+J9 -> 28336.05 | K11: =K7+K9 -> 13183.32 | L11: =L7+L9 -> 7773.7 | M11: =M7+M9 -> 1222.78 | N11: =N7+N9 -> 7704.85 | O11: =O7+O9 -> -9445.52 | P11: =P7+P9 -> 7045.26 | Q11: =sum(H11:P11) -> 63167.83
B12: 55 | C12: 48.48 | D12: =B12*C12*-1 -> -2666.4 | E12: Put assignment
A13: 44638 | B13: 100 | C13: 50 | D13: =B13*C13*-1 -> -5000 | E13: Put assignment
A14: 44665 | B14: 100 | C14: 35 | D14: =B14*C14*-1 -> -3500 | E14: Put assignment
A15: 44701 | B15: 100 | C15: 25 | D15: =B15*C15*-1 -> -2500 | E15: Call assigned to compensate above
A16: 44911 | B16: 1000 | C16: 15 | D16: =B16*C16*-1 -> -15000 | E16: Put assignment
A17: 44975 | B17: -400 | C17: 15 | D17: =B17*C17*-1 -> 6000 | E17: Call Assigned
A18: 45002 | B18: -600 | C18: 16 | D18: =B18*C18*-1 -> 9600 | E18: Call Assigned
A19: 45037 | B19: 300 | C19: 20 | D19: =B19*C19*-1 -> -6000 | E19: Put assigned
A20: 45094 | B20: -300 | C20: 20 | D20: =B20*C20*-1 -> 6000 | E20: Call assigned
A21: 45247 | B21: -400 | C21: 17.5 | D21: =B21*C21*-1 -> 7000 | E21: Put assigned
A22: 45366 | B22: 200 | C22: 17.5 | D22: =C22*B22*-1 -> -3500 | E22: Put assigned
A23: 45366 | B23: 200 | C23: 17 | D23: =C23*B23*-1 -> -3400 | E23: Put assigned
A24: 45401 | B24: 400 | C24: 15 | D24: =C24*B24*-1 -> -6000 | E24: Put assigned
A25: 45429 | B25: -400 | C25: 15.5 | D25: =C25*B25*-1 -> 6200 | E25: Call assigned
A26: 45521 | B26: 400 | C26: 14 | D26: =C26*B26*-1 -> -5600 | E26: Put assigned
A27: 45611 | B27: -400 | C27: 12.5 | D27: =C27*B27*-1 -> 5000 | E27: Call assigned
A28: 45646 | B28: -400 | C28: 16 | D28: =C28*B28*-1 -> 6400 | E28: Call assigned
A29: 45729 | B29: 400 | C29: 17.5 | D29: =C29*B29*-1 -> -7000 | E29: Put assigned
B30: =SUM(B11:B29) -> 400 | D30: =SUM(D11:D29) -> -16310
A32: IBKR | B32: Qty | C32: Price | D32: Amount | E32: Comment
A33: 45982 | B33: 300 | C33: 62 | D33: =-B33*C33 -> -18600 | E33: Put assigned
A35: Total | B35: =sum(B33:B34) -> 300 | D35: =sum(D33:D34) -> -18600
A37: NLR | B37: Qty | C37: Price | D37: Amount | E37: Comment
A38: 45982 | B38: 100 | C38: 150 | D38: =-B38*C38 -> -15000 | E38: Put assigned
A40: Total | B40: =sum(B38:B39) -> 100 | D40: =sum(D38:D39) -> -15000
A42: GLW | B42: Qty | C42: Price | D42: Amount | E42: Comment
A43: 45982 | B43: 200 | C43: 80 | D43: =-B43*C43 -> -16000 | E43: Put assigned
A45: Total | B45: =sum(B43:B44) -> 200 | D45: =sum(D43:D44) -> -16000
A48: CROX | B48: Qty | C48: Price | D48: Amount | E48: Comment
A49: 44474 | B49: 19 | C49: 138.08 | D49: =B49*C49*-1 -> -2623.52
A50: 44491 | B50: 19 | C50: 153.83 | D50: =B50*C50*-1 -> -2922.77 | E50: Put assignment
A51: 44615 | B51: 62 | C51: 81 | D51: =B51*C51*-1 -> -5022 | E51: Call assigned to compensate above
A52: 44701 | B52: 100 | C52: 60 | D52: =B52*C52*-1 -> -6000
A53: 44792 | B53: -100 | C53: 60 | D53: =B53*C53*-1 -> 6000 | E53: Put assigned as planned
A54: 44975 | B54: -100 | C54: 130 | D54: =B54*C54*-1 -> 13000 | E54: Put assigned as planned
A55: 45002 | B55: 100 | C55: 120 | D55: =B55*C55*-1 -> -12000 | E55: Call assigned
A56: 45156 | B56: 100 | C56: 95 | D56: =B56*C56*-1 -> -9500 | E56: Put assigned
A57: 45338 | B57: -200 | C57: 110 | D57: =B57*C57*-1 -> 22000 | E57: Call assigned
A58: 45399 | B58: 100 | C58: 135 | D58: =-B58*C58 -> -13500 | E58: Put assigned
A59: 45429 | B59: -100 | C59: 140 | D59: =-B59*C59 -> 14000 | E59: Call assigned
A60: 45492 | B60: 100 | C60: 150 | D60: =-B60*C60 -> -15000 | E60: Put assigned
A61: 45611 | B61: 100 | C61: 105 | D61: =-B61*C61 -> -10500 | E61: Put assigned
A62: 45646 | B62: -100 | C62: 105 | D62: =-B62*C62 -> 10500 | E62: Call assigned
A63: Total | B63: =SUM(B49:B62) -> 100 | D63: =SUM(D49:D62) -> -11568.29
A65: WING | B65: Qty | C65: Price | D65: Amount | E65: Comment
A66: 45737 | B66: 100 | C66: 220 | D66: =-B66*C66 -> -22000 | E66: Put assigned
A68: Total | B68: =sum(B66:B67) -> 100 | D68: =sum(D66:D67) -> -22000
A71: NVDA | B71: Qty | C71: Price | D71: Amount | E71: Comment
A72: 45737 | B72: 100 | C72: 120 | D72: =-B72*C72 -> -12000 | E72: Put assigned
A74: Total | B74: =sum(B72:B73) -> 100 | D74: =sum(D72:D73) -> -12000
A76: RCAT | B76: Qty | C76: Price | D76: Amount | E76: Comment
A77: 45764 | B77: 400 | C77: 7.5 | D77: =-B77*C77 -> -3000 | E77: Put assigned
A78: 45856 | B78: -400 | C78: 8 | D78: =-B78*C78 -> 3200 | E78: Call assigned
A79: 45982 | B79: 500 | C79: 9.5 | D79: =-B79*C79 -> -4750
A80: Total | B80: =sum(B77:B79) -> 500 | D80: =sum(D77:D79) -> -4550
A82: NEM | B82: Qty | C82: Price | D82: Amount | E82: Comment
A83: 45856 | B83: 100 | C83: 59 | D83: =-B83*C83 -> -5900 | E83: Put assigned
A84: 45920 | B84: -100 | C84: 73 | D84: =-B84*C84 -> 7300 | E84: Call assigned
D85: =sum(D83:D84) -> 1400
A87: FTNT | B87: Qty | C87: Price | D87: Amount | E87: Comment
A88: 45856 | B88: 100 | C88: 97.5 | D88: =-B88*C88 -> -9750 | E88: Put assigned
A92: GLD | B92: Qty | C92: Price | D92: Amount | E92: Comment
A93: 45516 | B93: 12 | C93: 228 | D93: =B93*C93 -> 2736
A97: CI | B97: Qty | C97: Price | D97: Amount | E97: Comment
A98: 44431 | B98: 10 | C98: 207.65 | D98: =-B98*C98 -> -2076.5
A99: 44684 | B99: -10 | C99: 247.805 | D99: =-B99*C99-1.01 -> 2477.04
A100: 45022 | B100: 11 | C100: 264.92 | D100: =-B100*C100 -> -2914.12
A101: 45418 | B101: -11 | C101: 341.25 | D101: 3765.11
B102: =sum(B98:B101) -> 0 | D102: =SUM(D98:D101) -> 1251.53
A103: ZAP | B103: Qty | C103: Price | D103: Amount | E103: Comment
A104: 45804 | B104: 190 | C104: 26.2 | D104: =B104*C104 -> 4978
A107: EPAM | B107: Qty | C107: Price | D107: Amount | E107: Comment
B108: 7 | C108: 283.84 | D108: =B108*C108 -> 1986.88
A110: AAPL | B110: Qty | C110: Price | D110: Amount | E110: Comment
A111: 45156 | B111: 100 | C111: 180 | D111: =B111*C111*-1 -> -18000 | E111: Put assigned
A112: 45240 | B112: -100 | C112: 190 | D112: =B112*C112*-1 -> 19000 | E112: Call assigned
A113: 45310 | B113: 100 | C113: 190 | D113: =B113*C113*-1 -> -19000 | E113: Put assigned
A114: 45401 | B114: 100 | C114: 167.5 | D114: =B114*C114*-1 -> -16750 | E114: Put assigned
A115: 45429 | B115: -100 | C115: 175 | D115: =B115*C115*-1 -> 17500 | E115: Call assigned
A116: 45465 | B116: -100 | C116: 202.5 | D116: =B116*C116*-1 -> 20250 | E116: Call assigned
A117: 45492 | B117: 100 | C117: 227.5 | D117: =B117*C117*-1 -> -22750 | E117: Put assigned
A118: 45583 | B118: -100 | C118: 230 | D118: =B118*C118*-1 -> 23000 | E118: Call assigned
A119: 45729 | B119: 100 | C119: 237.5 | D119: =B119*C119*-1 -> -23750 | E119: Put assigned
B121: =SUM(B111:B120) -> 100 | D121: =SUM(D111:D120) -> -20500
A123: META | B123: Qty | C123: Price | D123: Amount | E123: Comment
A124: 45418 | B124: 9 | C124: 454.65 | D124: =-B124*C124-1 -> -4092.85
A125: 45425 | B125: 14 | C125: 468 | D125: =-B125*C125-1 -> -6553
A126: 45916 | B126: -3 | C126: 776 | D126: =-B126*C126-1 -> 2327
B127: =sum(B124:B125) -> 23 | D127: =sum(D124:D126) -> -8318.85
...

Sheet Options 2022
A1: Trans date | B1: Tiker | C1: Type | D1: Action | E1: Expiration | F1: Strike | G1: Qty | H1: Amount | I1: Comission | J1: Total Profit | K1: Total loss | L1: Total P&L | M1: Comment | N1: IV | O1: Hist. volatility | P1: VIX | Q1: Max Win probab | R1: Max Lose probab | S1: Profit probability | T1: Max Loss | U1: Return / Risk | V1: Liquidity
A2: 44508 | B2: LHDX | C2: Call | D2: Sell | E2: Nov19'21 | F2: 7.5 | H2: 23 | I2: 0.17 | J2: =H2-I2 -> 22.83 | K2: 0 | L2: =sum(J2:K2) -> 22.83 | M2: expired OTM
A3: 44511 | B3: LHDX | C3: Call | D3: Sell | E3: Nov19'21 | F3: 7.5 | H3: 70 | I3: 1.02 | J3: =H3-I3 -> 68.98 | K3: 0 | L3: =sum(J3:K3) -> 68.98 | M3: expired OTM
A5: 44529 | B5: DBC | C5: Put | D5: Sell | E5: Dec17'21 | F5: 21 | H5: 105 | I5: 0.27 | J5: =H5-I5 -> 104.73 | K5: 0 | L5: =sum(J5:K5) -> 104.73 | M5: Assigned! But sold at 21. See next line
A6: 44517 | B6: LHDX | C6: Call | D6: Sell | E6: Dec17'21 | F6: 10 | H6: 30 | I6: 1.02 | J6: =H6-I6 -> 28.98 | K6: =-(J6-L6) -> -13.62 | L6: 15.36 | M6: Mixed with Butterfly and cancelled out too early
A7: 44524 | B7: LHDX | C7: Call | D7: Sell | E7: Dec17'21 | F7: 7.5 | H7: 30 | I7: 1.02 | J7: =H7-I7 -> 28.98 | K7: 0 | L7: =sum(J7:K7) -> 28.98 | M7: expirred OTM
A8: 44531 | B8: LHDX | C8: Iron butterfly | D8: Sell | E8: Dec17'21 | F8: 5/7.5 | H8: 120 | I8: 2.49 | J8: =H8-I8 -> 117.51 | K8: =(8.02-7.5)*100 -> 52 | L8: =sum(J8:K8) -> 169.51 | M8: Assigned but sold later with profit of 52
A10: 44553 | B10: LHDX | C10: Call | D10: Sell | E10: Jan21'22 | F10: 10 | H10: 50 | I10: 0.16 | J10: =H10-I10 -> 49.84 | K10: 0 | L10: =sum(J10:K10) -> 49.84 | M10: expired OTM | N10: 1.14 | P10: 0.214 | Q10: 0.76 | R10: <1%
A11: 21/12.2021 | B11: LHDX | C11: Call | D11: Sell | E11: Jan21'22 | F11: 7.5 | H11: 74 | I11: 0.17 | J11: =H11-I11 -> 73.83 | K11: 0 | L11: =sum(J11:K11) -> 73.83 | M11: expired OTM | N11: 1.23 | P11: 0.216 | Q11: 0.59 | R11: <1%
A12: 44543 | B12: LHDX | C12: Bull put | E12: Jan21'22 | F12: 2.5/5 | H12: =(0.654-0.111)*2*100 -> 108.6 | I12: =2.1+1.03 -> 3.13 | J12: =H12-I12+(5.215-5)*200 -> 148.47 | K12: 0 | L12: =sum(J12:K12) -> 148.47 | M12: Put assigned. But sold on 01/03 for 5.215 | N12: 1.073 | P12: 0.215 | Q12: 0.53 | R12: 0.023
A13: 21/12.2021 | B13: DBC | C13: Call | D13: Sell | E13: Jan21'22 | F13: 21 | H13: 20 | I13: 0.27 | J13: =H13-I13 -> 19.73 | K13: 0 | L13: =sum(J13:K13) -> 19.73 | M13: Assigned, compensated prevous put. | N13: 0.208 | P13: 0.216 | Q13: 0.77 | R13: <1%
A14: 44553 | B14: PRGO | C14: Call | D14: Sell | E14: Jan21'22 | F14: 42.5 | H14: 30 | I14: 1.02 | J14: =H14-I14 -> 28.98 | K14: 0 | L14: =sum(J14:K14) -> 28.98 | M14: expired OTM
A16: 44594 | B16: VTI | C16: Call | D16: Sell | E16: Feb18'22 | F16: 235 | H16: 110 | I16: 1.89 | J16: =H16-I16 -> 108.11 | K16: 0 | L16: =sum(J16:K16) -> 108.11 | M16: expired OTM | N16: 0.185 | P16: 0.2265 | Q16: 0.73 | R16: <1%
A17: 44595 | B17: ASAN | C17: Put | D17: Sell | E17: Feb18'22 | F17: 40 | H17: 135 | I17: 0.3 | J17: =H17-I17 -> 134.7 | K17: 0 | L17: =sum(J17:K17) -> 134.7 | M17: expired OTM | N17: 0.99 | P17: 0.244 | Q17: 0.75 | R17: <1% | S17: 0.8
A19: 44603 | B19: ASAN | C19: Put | D19: Sell | E19: Mar18'22 | F19: 50 | H19: 321 | I19: 0.2 | J19: =H19-I19 -> 320.8 | M19: Assigned. Paper loss as not sold yet. | N19: 1.068 | P19: 0.2855 | Q19: 0.75 | R19: <1% | S19: 0.81
A20: 44614 | B20: ASAN | C20: Put | D20: Sell | E20: Mar18'22 | F20: 40 | H20: 104 | I20: 0.2 | J20: =H20-I20 -> 103.8 | K20: 0 | L20: =sum(J20:K20) -> 103.8 | M20: expired OTM | N20: 1.11 | P20: 0.2905 | Q20: 0.9 | R20: <1% | S20: 0.91
A21: 44614 | B21: VTI | C21: Call | D21: Sell | E21: Mar18'22 | F21: 230 | H21: 86 | I21: 0.2 | J21: =H21-I21 -> 85.8 | L21: =sum(J21:K21) -> 85.8 | M21: expired OTM | N21: 0.27 | P21: 0.2905 | Q21: 0.82 | R21: <1% | S21: 0.83
A22: 44615 | B22: CROX | C22: Call | D22: Sell | E22: Mar18'22 | F22: 90 | H22: 240 | I22: 0.3 | J22: =H22-I22 -> 239.7 | L22: =sum(J22:K22) -> 239.7 | M22: expired OTM | N22: 0.67 | P22: 0.29 | Q22: 0.73 | R22: <1% | S22: 0.77
A23: 44616 | B23: ASAN | C23: Call | D23: Sell | E23: Mar18'22 | F23: 60 | H23: 336 | I23: 0.2 | J23: =H23-I23 -> 335.8 | L23: =sum(J23:K23) -> 335.8 | M23: expired OTM | N23: 133.2 | P23: 0.31 | Q23: 0.69 | R23: <1% | S23: 0.74
A24: 44620 | B24: LHDX | C24: Call | D24: Sell | E24: Mar18'22 | F24: 5 | H24: 90 | I24: 0.1 | J24: =H24-I24 -> 89.9 | L24: =sum(J24:K24) -> 89.9 | M24: expired OTM | N24: 1.29 | P24: 0.2945 | Q24: 0.54 | R24: <1% | S24: 0.63
A25: 44629 | B25: DBC | C25: Call | D25: Sell | E25: Mar18'22 | F25: 26 | H25: 74 | I25: 0.2 | J25: =H25-I25 -> 73.8 | L25: =sum(J25:K25) -> 73.8 | M25: Sold call as want to re-balance. This is instead of selling DBC directly.
A27: 44634 | B27: CROX | C27: Call | D27: Buy | E27: Jun17'22 | F27: 95 | I27: 0.2 | K27: =-266-I27 -> -266.2 | L27: =sum(J27:K27) -> -266.2 | N27: 0.73 | P27: 0.3255 | S27: 0.17
A28: 44642 | B28: CROX | C28: Call | D28: Sell | E28: Apr14'22 | F28: 85 | H28: 396 | I28: 0.25 | J28: =H28-I28 -> 395.75 | K28: =-7-0.25 -> -7.25 | L28: =sum(J28:K28) -> 388.5 | M28: Closed for $7, 4 days before expiry | N28: 0.59 | P28: 0.2505 | Q28: 0.55 | R28: <1% | S28: 0.67
A29: 44642 | B29: VTI | C29: Call | D29: Sell | E29: Apr14'22 | F29: 235 | H29: 100 | I29: 1.05 | J29: =H29-I29 -> 98.95 | K29: =-5-1.9 -> -6.9 | L29: =sum(J29:K29) -> 92.05 | M29: Closed for $5, 4 days before expiry | N29: 0.19 | P29: 0.2505 | Q29: 0.76 | R29: <1% | S29: 0.79
A30: 44642 | B30: ASAN | C30: Put | D30: Sell | E30: Apr14'22 | F30: 35 | H30: 95 | I30: 1.05 | J30: =H30-I30 -> 93.95 | K30: =(33.36-35)*100 -> -164 | M30: Assigned. Paper loss as not sold yet. | N30: 0.88 | P30: 0.2505 | Q30: 0.82 | R30: <1% | S30: 0.85
A31: 44643 | B31: ASAN | C31: Call | D31: Sell | E31: Apr14'22 | F31: 50 | H31: 156 | I31: 0.2 | J31: =H31-I31 -> 155.8 | K31: =-5-1.9 -> -6.9 | L31: =sum(J31:K31) -> 148.9 | M31: Closed for $5, 4 days before expiry | N31: 0.9 | P31: 0.254 | Q31: 0.73 | R31: <1% | S31: 0.78
A32: 44643 | B32: DBC | C32: Call | D32: Sell | E32: Apr14'22 | F32: 28 | H32: 79 | I32: 0.2 | J32: =H32-I32 -> 78.8 | K32: =-5-0.3 -> -5.3 | L32: =sum(J32:K32) -> 73.5 | M32: Closed for $5, 4 days before expiry | N32: 0.38 | P32: 0.254 | Q32: 0.6 | R32: <1% | S32: 0.7
A34: 44663 | B34: CROX | C34: Put | D34: Sell | E34: May20'22 | F34: 60 | H34: 175 | I34: 1.05 | J34: =H34-I34 -> 173.95 | L34: =sum(J34:K34) -> 173.95 | M34: Assigned but sold in august for 60. | N34: 0.65 | P34: 0.243 | Q34: 0.8 | R34: <1% | S34: 0.83
A35: 44600 | B35: PRGO | C35: Call | D35: Sell | E35: May20'22 | F35: 42.5 | H35: 85 | I35: 0.19 | J35: =H35-I35 -> 84.81 | L35: =sum(J35:K35) -> 84.81 | M35: expired OTM
A36: 44664 | B36: DBC | C36: Call | D36: Sell | E36: May20'22 | F36: 28 | H36: 100 | I36: 1.05 | J36: =H36-I36 -> 98.95 | L36: =sum(J36:K36) -> 98.95 | M36: expired OTM | N36: 0.3 | P36: 0.231 | Q36: 0.52 | R36: <1% | S36: 0.66
A37: 44684 | B37: CROX | C37: Call | D37: Sell | E37: May20'22 | F37: 85 | H37: 129 | I37: 0.25 | J37: =H37-I37 -> 128.75 | L37: =sum(J37:K37) -> 128.75 | M37: expired OTM | N37: 0.81 | P37: 0.294 | Q37: 0.81 | R37: <1% | S37: 0.83
A38: 44684 | B38: ASAN | C38: Put | D38: Sell | E38: May20'22 | F38: 25 | H38: 146 | I38: 0.25 | J38: =H38-I38 -> 145.75 | M38: Assigned. Paper loss as not sold yet. | N38: 1.14 | P38: 0.294 | Q38: 0.65 | R38: <1% | S38: 0.74
A39: 44685 | B39: VTI | C39: Call | D39: Sell | E39: May20'22 | F39: 220 | H39: 100 | I39: 1.05 | J39: =H39-I39 -> 98.95 | L39: =sum(J39:K39) -> 98.95 | M39: expired OTM | N39: 0.26 | P39: 0.28 | Q39: 0.79 | R39: <1% | S39: 0.81
A41: 44705 | B41: PRGO | C41: Call | D41: Sell | E41: Jun17'22 | F41: 37.5 | H41: 151 | I41: 0.25 | J41: =H41-I41 -> 150.75 | K41: 0 | L41: =sum(J41:K41) -> 150.75 | M41: Assigned as planned | N41: 0.31 | P41: 0.28 | Q41: 0.26 | S41: 0.56
A42: 44707 | B42: VTI | C42: Call | D42: Sell | E42: Jun17'22 | F42: 215 | H42: 94 | I42: 1.05 | J42: =H42-I42 -> 92.95 | K42: 0 | L42: =sum(J42:K42) -> 92.95 | M42: expired OTM | N42: 0.26 | P42: 0.28 | Q42: 0.81 | S42: 0.82
A43: 44707 | B43: ASAN | C43: Call | D43: Sell | E43: Jun17'22 | F43: 25 | H43: 171 | I43: 0.21 | J43: =H43-I43 -> 170.79 | K43: 0 | L43: =sum(J43:K43) -> 170.79 | M43: expired OTM | N43: 1.39 | P43: 0.28 | Q43: 0.67 | S43: 0.73
A44: 44707 | B44: CROX | C44: Call | D44: Sell | E44: Jun17'22 | F44: 60 | H44: 141 | I44: 0.25 | J44: =H44-I44 -> 140.75 | K44: 0 | L44: =sum(J44:K44) -> 140.75 | M44: expired OTM | N44: 0.7 | P44: 0.28 | Q44: 0.73 | S44: 0.77
A45: 44707 | B45: DBC | C45: Call | D45: Sell | E45: Jun17'22 | F45: 29 | H45: 50 | I45: 0.55 | J45: =H45-I45 -> 49.45 | K45: 0 | L45: =sum(J45:K45) -> 49.45 | M45: expired OTM | N45: 0.26 | P45: 0.28 | Q45: 0.58 | S45: 0.68
A47: 44755 | B47: CROX | C47: Call | D47: Sell | E47: Aug19'22 | F47: 60 | H47: 296 | I47: 1.91 | J47: =H47-I47 -> 294.09 | L47: =sum(J47:K47) -> 294.09 | M47: assigned and sold as planned to compensate for earlier assignment | N47: 0.78 | P47: 0.27 | Q47: 0.66 | S47: 0.73
A48: 44762 | B48: CROX | C48: Call | D48: Sell | E48: Aug19'22 | F48: 70 | H48: 171 | I48: 1.91 | J48: =H48-I48 -> 169.09 | K48: =-310-1.05 -> -311.05 | L48: =sum(J48:K48) -> -141.96 | M48: closed in advance on drop, as was going up | N48: 0.77 | P48: 0.27 | Q48: 0.75 | S48: 0.79
A49: 44763 | B49: ASAN | C49: Call | D49: Sell | E49: Aug19'22 | F49: 25 | H49: 49 | I49: 0.25 | J49: =H49-I49 -> 48.75 | L49: =sum(J49:K49) -> 48.75 | M49: expired OTM | N49: 0.97 | P49: 0.26 | Q49: 0.9 | S49: 0.91
A50: 44762 | B50: CROX | C50: Call | D50: Sell | E50: Aug19'22 | F50: 80 | H50: 47 | I50: 1.05 | J50: =H50-I50 -> 45.95 | L50: =sum(J50:K50) -> 45.95 | M50: expired OTM | N50: 0.62 | P50: 0.24 | Q50: 0.87 | S50: 0.88
A52: 44781 | B52: ASAN | C52: Call | D52: Sell | E52: Sep16'22 | F52: 35 | H52: 140 | I52: 0.3 | J52: =H52-I52 -> 139.7 | K52: =-39-0.2 -> -39.2 | L52: =sum(J52:K52) -> 100.5 | M52: closed on 19/08 in advance | N52: 1.06 | O52: 0.93 | P52: 0.23 | Q52: 0.85 | S52: 0.86
A53: 44785 | B53: CROX | C53: Bear call | D53: Buy | E53: Dec16'22 | F53: 100/110 | G53: 10 | H53: =144+1359 -> 1503 | I53: =1.31+12.68 -> 13.99 | J53: =H53-I53 -> 1489.01 | M53: see below, closed with profit of 390 | N53: 0.53 | O53: 0.7 | P53: 0.21 | Q53: 0.76 | S53: 0.77
A54: 44792 | B54: CROX | G54: -5 | H54: =J53/2 -> 744.505 | I54: 7.02 | J54: =H54-I54 -> 737.485 | K54: =-1.07*100*5 -> -535 | L54: =sum(J54:K54) -> 202.485 | M54: sold half on 19/08 to book some profit
A55: 44795 | B55: CROX | G55: -5 | H55: =H54 -> 744.505 | I55: 7.02 | J55: =H55-I55 -> 737.485 | K55: -550 | L55: =sum(J55:K55) -> 187.485 | M55: closed and booked some profit
A57: 44795 | B57: CROX | C57: Put | D57: Sell | E57: Sep16'22 | F57: 70 | G57: 1 | H57: 331 | I57: 0.26 | J57: =H57-I57 -> 330.74 | K57: 0 | L57: =sum(J57:K57) -> 330.74 | M57: Expired OTM | N57: 0.58 | O57: 0.67 | P57: 0.26 | Q57: 0.59 | S57: 0.7
A58: 44795 | B58: DBC | C58: Call | D58: Sell | E58: Sep16'22 | F58: 26 | G58: 1 | H58: 80 | I58: 0.3 | J58: =H58-I58 -> 79.7 | L58: =sum(J58:K58) -> 79.7 | M58: Expired OTM | N58: 0.27 | O58: 0.27 | P58: 0.26 | Q58: 0.47 | S58: 0.63
A59: 44795 | B59: ASAN | C59: Bull put | D59: Buy | E59: Nov18'22 | F59: 17.5/12.5 | G59: 10 | H59: 1690 | I59: 1.45 | J59: =H59-I59 -> 1688.55 | K59: -1000.46 | L59: =sum(J59:K59) -> 688.09 | M59: closed on sept 8th to book profit | N59: 1.11 | O59: 0.89 | P59: 0.26 | Q59: 0.6 | S59: 0.68
A61: 44802 | B61: GOOGL | C61: Put | D61: Sell | E61: Sep2'22 | F61: 108 | G61: 1 | H61: 95 | I61: 1.05 | J61: =H61-I61 -> 93.95 | M61: Assigned. Paper loss as not sold yet. | N61: 0.338 | O61: 0.336 | P61: 0.2585 | Q61: 0.68 | S61: 0.76
A62: 44811 | B62: GOOGL | C62: Call | D62: Sell | E62: Sep23'22 | F62: 110 | G62: 1 | H62: 304 | I62: 0.76 | J62: =H62-I62 -> 303.24 | L62: =sum(J62:K62) -> 303.24 | M62: Expired OTM | N62: 0.33 | O62: 0.296 | P62: 0.25 | Q62: 0.5 | S62: 0.65
A63: 44824 | B63: CROX | C63: Bear Call | D63: Sell | E63: Nov18'22 | F63: 90/95 | G63: 10 | H63: 1080 | I63: 3.78 | J63: =H63-I63 -> 1076.22 | K63: -648.32 | L63: =sum(J63:K63) -> 427.9 | M63: Closed after 3 days | N63: 0.62 | O63: 0.54 | P63: 0.28 | Q63: 0.71 | S63: 0.72
A65: 44824 | B65: VTI | C65: Bull Put | D65: Sell | E65: Oct21'22 | F65: 180/175 | G65: 10 | H65: 707 | I65: 5.1 | J65: =H65-I65 -> 701.9 | L65: =sum(J65:K65) -> 701.9 | M65: Expired OTM | N65: 26.4 | O65: 0.19 | P65: 0.28 | Q65: 0.83 | S65: 0.84 | T65: =5*1000-J65 -> 4298.1
A66: 44827 | B66: ASAN | C66: Bull Put | D66: Sell | E66: Oct21'22 | F66: 15/12.5 | G66: 5 | H66: 105 | I66: 7.01 | J66: =H66-I66 -> 97.99 | L66: =sum(J66:K66) -> 97.99 | M66: Expired OTM | N66: 0.9 | O66: 1 | P66: 0.3 | Q66: 0.9 | S66: 0.91 | T66: 1250 | U66: =J66/T66 -> 0.078392
A67: 44831 | B67: VTI | C67: Butterfly | D67: Buy | E67: Oct21'22 | F67: 170/180/190 | G67: 3 | H67: 1506 | I67: =6.9+8.5 -> 15.4 | J67: =H67-I67 -> 1490.6 | K67: -809 | L67: =sum(J67:K67) -> 681.6 | M67: Corrective butterfly in 24 days to try and fix bleeding Bull put above. Sold 2 days before expiration. | N67: 0.32 | O67: 0.196 | P67: 0.337 | Q67: <1% | S67: 0.36 | T67: 809
A68: 44831 | B68: CROX | C68: Call | D68: Sell | E68: Oct21'22 | F68: 80 | G68: 1 | H68: 131 | I68: 0.25 | J68: =H68-I68 -> 130.75 | L68: =sum(J68:K68) -> 130.75 | M68: Expired OTM | N68: 0.74 | O68: 0.55 | P68: 0.337 | Q68: 0.79 | S68: 0.82
A69: 44831 | B69: DBC | C69: Call | D69: Sell | E69: Oct21'22 | F69: 25 | G69: 1 | H69: 34 | I69: 0.25 | J69: =H69-I69 -> 33.75 | L69: =sum(J69:K69) -> 33.75 | M69: Expired OTM | N69: 0.32 | O69: 0.26 | P69: 0.337 | Q69: 0.62 | S69: 0.7
A70: 44839 | B70: GOOGL | C70: Bear Call | D70: Sell | E70: Oct28'22 | F70: 110/111 | G70: 20 | H70: 400 | I70: 28.7 | J70: =H70-I70 -> 371.3 | L70: =sum(J70:K70) -> 371.3 | M70: Expired OTM | N70: 0.44 | O70: 0.3 | P70: 0.29 | Q70: 0.83 | S70: 0.83 | T70: =1*G70*100-J70 -> 1628.7 | U70: =J70/T70 -> 0.22797323
A72: 44838 | B72: CROX | C72: Bear Call | D72: Sell | E72: Nov18'22 | F72: 90/95 | G72: 10 | H72: 970 | I72: 10.37 | J72: =H72-I72+84.93+3768 -> 4812.56 | K72: =-1736.33-4613.33 -> -6349.66 | L72: =sum(J72:K72) -> -1537.1 | M72: Intended to take profit earlier but didn't - learning! | N72: 0.73 | O72: 0.61 | P72: 0.29 | Q72: 0.72 | S72: 0.73 | T72: =5000-J72 -> 187.44 | U72: =J72/T72 -> 25.675203
A73: 44876 | B73: CROX | C73: Butterfly | D73: Buy | E73: Nov18'22 | F73: 85/95/105 | G73: 3 | I73: 6.71 | J73: =H73-I73 -> -6.71 | K73: =-3*4.487*100 -> -1346.1 | L73: =sum(J73:K73) -> -1352.81 | M73: Significant loss due to mistake in correction. Butterfly screwed the call.
A74: 44866 | B74: ASAN | C74: Bull put | D74: Sell | E74: Nov18'22 | F74: 17.5/15 | G74: 10 | H74: 360 | I74: 1.2 | J74: =H74-I74 -> 358.8 | L74: =sum(J74:K74) -> 358.8 | M74: Expired OTM | N74: 0.97 | O74: 0.94 | P74: 0.2574 | Q74: 0.78 | S74: 0.81 | T74: =2500-J74 -> 2141.2 | U74: =J74/T74 -> 0.16756959
A75: 44869 | B75: ASAN | C75: Butterfly | D75: Buy | E75: Nov18'22 | F75: 12.5/17.5/22.5 | G75: 3 | I75: 6.69 | J75: 808.2 | K75: -838 | L75: =sum(J75:K75) -> -29.8 | M75: Might have weighed a bit to get into positive zone on good dynamic but decided not to riisk | N75: 1.029 | O75: 0.929 | Q75: <1% | S75: 0.47 | T75: 886
A77: 44883 | B77: GOOGL | C77: Bear Call | D77: Sell | E77: Dec16'22 | F77: 105/107.5 | G77: 10 | H77: 350 | I77: 23.61 | J77: =H77-I77 -> 326.39 | K77: -57.29 | L77: =sum(J77:K77) -> 269.1 | M77: Closed earlier to fix the profit | N77: 0.33 | O77: 0.459 | P77: 0.2335 | Q77: 0.8 | S77: 0.81 | T77: =2500-J77 -> 2173.61 | U77: =J77/T77 -> 0.15016033
A78: 44869 | B78: VTI | C78: Iron condor | D78: Sell | E78: Dec16'22 | F78: 170/175 195/200 | G78: 10 | H78: 2140 | I78: 20.36 | J78: =H78-I78 -> 2119.64 | L78: =sum(J78:K78) -> 2119.64 | N78: 0.253 | O78: 0.264 | Q78: 0.45 | S78: 0.53 | T78: 2991
A79: 44883 | B79: VTI | K79: -449.38 | L79: =sum(J79:K79) -> -449.38 | M79: Bought back 175 put to realize early profit of PUT leg - bad idea to break the pair, useless move and costly
A80: 44894 | B80: VTI | C80: Bull put | D80: Sell | E80: Dec16'22 | F80: 185/180 | G80: 10 | H80: 234 | I80: 10.14 | J80: =H80-I80 -> 223.86 | L80: =sum(J80:K80) -> 223.86 | M80: "Moved" low condor limit up as to far and can benefit | N80: 0.217 | O80: 0.24 | P80: 0.22 | Q80: 0.92 | S80: 0.92 | T80: 4800 | U80: =J80/T80 -> 0.0466375
A81: 44887 | B81: VTI | C81: Butterfly | D81: Buy | E81: Dec16'22 | K81: -1081.98 | L81: =sum(J81:K81) -> -1081.98 | M81: Corrective butterfly to shift from 195/200 to 200/205
A82: 44896 | B82: VTI | C82: Butterfly | D82: Buy | E82: Dec16'22 | J82: 143.09 | K82: -1213.92 | L82: =sum(J82:K82) -> -1070.83 | M82: Corrective butterfly to shift from 200/205 to 205/210, sold 210 call on 12/12 to get at least a bit more profit
A83: 44895 | B83: VTI | C83: Call | D83: Buy | E83: Jan20'23 | F83: 195 | G83: 3 | H83: =235*G83 -> 705 | I83: =4.61+0.49 -> 5.1 | J83: =H83-I83 -> 699.9 | K83: -3417 | L83: =sum(J83:K83) -> -2717.1 | M83: Corrective call to neutralize delta
A84: 44883 | B84: DBC | C84: Call | D84: Sell | E84: Dec16'22 | F84: 26 | G84: 1 | H84: 34 | I84: 0.24 | J84: =H84-I84 -> 33.76 | L84: =sum(J84:K84) -> 33.76 | M84: Expired OTM
A85: 44883 | B85: CROX | C85: Bear Call | D85: Sell | E85: Dec16'22 | F85: 115/120 | G85: 10 | H85: 840 | I85: 5.1 | J85: =H85-I85 -> 834.9 | L85: =sum(J85:K85) -> 834.9 | M85: Expired OTM | N85: 0.628 | O85: 0.752 | P85: 0.2335 | Q85: 0.76 | S85: 0.78 | T85: =5000-J85 -> 4165.1 | U85: =J85/T85 -> 0.20045137
A86: 44887 | B86: ASAN | C86: Bull Put | D86: Sell | E86: Dec16'22 | F86: 15/12.5 | G86: 10 | H86: 584 | I86: 9.43 | J86: =H86-I86+600 -> 1174.57 | L86: =sum(J86:K86) -> 1174.57 | M86: Assigned, but sold 400 of 1000 @$15 in Feb 2023 and 600 @16 on March 17 2023 | N86: 1.12 | O86: 0.98 | P86: 0.2142 | Q86: 0.69 | S86: 0.74 | T86: 1949 | U86: =J86/T86 -> 0.60265264
A87: 44888 | B87: ASAN | C87: Call | D87: Sell | E87: Dec16'22 | F87: 25 | G87: 4 | H87: 196 | I87: 0.43 | J87: =H87-I87 -> 195.57 | L87: =sum(J87:K87) -> 195.57 | M87: Expired OTM | N87: 1.13 | O87: 0.98 | P87: 0.212 | Q87: 0.84 | S87: 0.85

Sheet Options 2023
C1: How Market is doing? | D1: Is option expensive or cheap, should I Sell/Buy? | F1: Volatility ahead? | G1: Liquide? | Q1: =sum(Q3:Q77) -> 7003.14 | X1: @
A2: Trans date | B2: Tiker | C2: VIX | D2: IV | E2: Hist. volatility | F2: Corporate events? | G2: Bid/Ask spread | H2: Type | I2: Action | J2: Expiration | K2: Strike | L2: Qty | M2: Amount | N2: Comission | O2: Total Profit | P2: Total loss | Q2: Total P&L | R2: Comment | S2: Profit probability | T2: Max Win probab | U2: Max Loss | V2: Max Lose probab | W2: Return / Risk
A3: 44930 | B3: ASAN | C3: 0.22 | D3: 0.82 | E3: 0.83 | F3: No | G3: 0.1 | H3: Call | I3: Sell | J3: Feb17'23 | K3: 15 | L3: 4 | M3: 404 | N3: 0.43 | O3: =M3-N3 -> 403.57 | P3: -210.75 | Q3: =sum(O3:P3) -> 192.82 | R3: Closed in one day | S3: 0.71 | T3: 0.63 | U3: infinity | V3: <1% | W3: n/a
A4: 44923 | B4: SPY | C4: 0.215 | D4: 0.206 | E4: 0.198 | F4: No | G4: 0.03 | H4: Bull Put | I4: Sell | J4: Feb17'23 | K4: 353/350 | L4: 10 | M4: 530 | N4: 23.67 | O4: =M4-N4 -> 506.33 | P4: =-127+107-1134+954-23.61 -> -223.61 | Q4: =sum(O4:P4) -> 282.72 | R4: Closed on 10-Jan | S4: 0.83 | T4: 0.82 | U4: 2487 | V4: 0.15 | W4: =Q4/U4 -> 0.11367913
A5: 44923 | B5: GOOGL | C5: 0.2186 | D5: 0.341 | E5: 0.3343 | F5: No | G5: 0.01 | H5: Bull Put | I5: Sell | J5: Jan20'23 | K5: 79.5/77.5 | L5: 10 | M5: 300 | N5: 10.79 | O5: =M5-N5 -> 289.21 | P5: -35.77 | Q5: =sum(O5:P5) -> 253.44 | R5: Closed on 11-Jan | S5: 0.83 | T5: 0.82 | U5: 1719 | V5: 0.11 | W5: =Q5/U5 -> 0.14743455
A6: 44931 | B6: ASAN | C6: 0.22 | D6: 0.874 | E6: 0.848 | F6: No | G6: 0.1 | H6: Bull Put | I6: Sell | J6: Feb17'23 | K6: 10/7.5 | L6: 10 | M6: 440 | N6: 13.8 | O6: =M6-N6 -> 426.2 | P6: -142.71 | Q6: =sum(O6:P6) -> 283.49 | R6: Closed on 13-Jan | S6: 0.77 | T6: 0.73 | U6: 2148 | V6: 0.058 | W6: =Q6/U6 -> 0.13197858
A7: 44938 | B7: GOOGL | C7: 0.2 | D7: 0.376 | E7: 0.341 | F7: Yes 7/02 | G7: 0.05 | H7: Bull Put | I7: Sell | J7: Feb17'23 | K7: 80/75 | L7: 10 | M7: 500 | N7: 23.61 | O7: =M7-N7 -> 476.39 | P7: -128.79 | Q7: =sum(O7:P7) -> 347.6 | R7: Closed on 23-Jan | S7: 0.88 | T7: 0.87 | U7: 4518 | V7: 0.045 | W7: =Q7/U7 -> 0.076936698
A9: 44938 | B9: SPY | C9: 0.2 | D9: 0.18 | E9: 0.2 | F9: No | G9: 0.03 | H9: Bull Put | I9: Sell | J9: Feb17'23 | K9: 376/373 | L9: 10 | M9: 420 | N9: 8.85 | O9: =M9-N9 -> 411.15 | P9: -148.8 | Q9: =sum(O9:P9) -> 262.35 | R9: Closed on 31-Jan | S9: 0.85 | T9: 0.85 | U9: 2578 | V9: 0.12 | W9: =Q9/U9 -> 0.10176493
A10: 44931 | B10: CROX | C10: 0.224 | D10: 0.683 | E10: 0.513 | F10: No | G10: 0.6 | H10: Call | I10: Sell | J10: Feb17'23 | K10: 130 | L10: 1 | M10: 340 | N10: 0.19 | O10: =M10-N10 -> 339.81 | Q10: =sum(O10:P10) -> 339.81 | R10: Assigned but OK to fix profit | S10: 0.79 | T10: 0.76 | U10: infinity | V10: <1% | W10: n/a
A11: 44936 | B11: ASAN | C11: 0.21 | D11: 0.84 | E11: 0.85 | F11: No | G11: 0.1 | H11: Call | I11: Sell | J11: Feb17'23 | K11: 15 | L11: 4 | M11: 280 | N11: 0.67 | O11: =M11-N11 -> 279.33 | Q11: =sum(O11:P11) -> 279.33 | R11: Assigned as planned | S11: 0.73 | T11: 0.66 | U11: infinity | V11: <1% | W11: n/a
A12: 44949 | B12: ASAN | C12: 0.1991 | D12: 0.765 | E12: 0.759 | F12: No | G12: 0.1 | H12: Call | I12: Sell | J12: Feb17'23 | K12: 16 | L12: 6 | M12: 306 | N12: 9.25 | O12: =M12-N12 -> 296.75 | Q12: =sum(O12:P12) -> 296.75 | R12: Expired OTM | S12: 0.75 | T12: 0.7 | U12: infinity | V12: <1% | W12: n/a
A13: 44971 | B13: SPY | C13: 0.19 | D13: 0.17 | E13: 0.18 | F13: No | G13: 0.01 | H13: Bear call | I13: Sell | J13: Mar17'23 | K13: 431/433 | L13: 10 | M13: 370 | N13: 23.85 | O13: =M13-N13 -> 346.15 | P13: -129.01 | Q13: =sum(O13:P13) -> 217.14 | R13: Closed on 17/02 to take profit | S13: 0.81 | T13: 0.8 | U13: 1629 | V13: 0.17 | W13: =Q13/U13 -> 0.1332965
A15: 44971 | B15: GOOGL | C15: 0.19 | D15: 0.33 | E15: 0.43 | F15: No | G15: 0.1 | H15: Bull Put | I15: Sell | J15: Mar17'23 | K15: 85/83 | L15: 10 | M15: 260 | N15: 13.91 | O15: =M15-N15 -> 246.09 | P15: -34.51 | Q15: =sum(O15:P15) -> 211.58 | R15: Closed on 8/3/2023 | S15: 0.85 | T15: 0.84 | U15: 1739 | V15: 0.11 | W15: =Q15/U15 -> 0.12166763
A16: 44978 | B16: SPY | C16: 0.229 | D16: 0.203 | E16: 0.17671 | F16: No | G16: 0.02 | H16: Bear call | I16: Sell | J16: Mar17'23 | K16: 418/420 | L16: 10 | M16: 360 | N16: 9.04 | O16: =M16-N16 -> 350.96 | P16: -108.17 | Q16: =sum(O16:P16) -> 242.79 | R16: Closed on 2/3/2023
A17: 44992 | B17: SPY | C17: 0.2 | D17: 0.18 | E17: 0.171 | F17: No | G17: 0.01 | H17: Bear call | I17: Sell | J17: Apr21'23 | K17: 420/422 | L17: 10 | M17: 380 | N17: 10.02 | O17: =M17-N17 -> 369.98 | P17: -143.51 | Q17: =sum(O17:P17) -> 226.47 | R17: Closed on 16/3/2023 | S17: 0.79 | T17: 0.79 | U17: 1628 | V17: 0.19 | W17: =Q17/U17 -> 0.13910934
A18: 44978 | B18: CROX | C18: 0.229 | D18: 0.541 | E18: 0.535 | F18: No | G18: 0.4 | H18: Put | I18: Sell | J18: Mar17'23 | K18: 120 | L18: 1 | M18: 591 | N18: 0.27 | O18: =M18-N18 -> 590.73 | Q18: =sum(O18:P18) -> 590.73 | R18: Assigned, bough as planned | S18: 0.67 | T18: 0.53 | U18: 11408 | V18: <1% | W18: 0.05
A19: 44978 | B19: ASAN | C19: 0.229 | D19: 1.131 | E19: 0.8378 | F19: Yes (8/03) | G19: 0.1 | H19: Call | I19: Sell | J19: Mar17'23 | K19: 16 | L19: 6 | M19: 666 | N19: 9.32 | O19: =M19-N19 -> 656.68 | Q19: =sum(O19:P19) -> 656.68 | R19: Assigned, sold to fix profit from previous assignment
A20: 44980 | B20: AAPL | C20: 0.22 | D20: 0.277 | E20: 0.28 | F20: No | G20: 0.05 | H20: Put | I20: Sell | J20: Apr21'23 | K20: 135 | L20: 1 | M20: 215 | N20: 1.05 | O20: =M20-N20 -> 213.95 | P20: -44.85 | Q20: =sum(O20:P20) -> 169.1 | R20: Closed on 23/03/2023 | S20: 0.85 | T20: 0.82 | U20: 13287 | V20: <1% | W20: =Q20/U20 -> 0.012726725
A22: 45001 | B22: C | C22: 0.234 | D22: 0.4 | E22: 0.353 | F22: Yes 13/04 | G22: 0.03 | H22: Put | I22: Sell | J22: Apr21'23 | K22: 45 | L22: 1 | M22: 203 | N22: 0.63 | O22: =M22-N22 -> 202.37 | Q22: =COUNT(Q15:Q21) -> 6 | R22: Ready to buy @45 | S22: 0.68 | T22: 0.54 | U22: 4295 | V22: <1% | W22: =Q22/U22 -> 0.0013969732
A23: 45009 | B23: ASAN | C23: 0.243 | D23: 0.721 | E23: 0.854 | F23: No | G23: 0.1 | H23: Put | I23: Sell | J23: Apr21'23 | K23: 20 | L23: 3 | M23: 453 | N23: 0.29 | O23: =M23-N23 -> 452.71 | Q23: =sum(O23:P23) -> 452.71 | R23: Ready to buy @20. Assigned but OK | S23: 0.67 | T23: 0.53 | U23: 5578 | V23: <1% | W23: =Q23/U23 -> 0.081159914
A24: 45009 | B24: AAPL | C24: 0.223 | D24: 0.292 | E24: 0.242 | F24: Yes | G24: 0.1 | H24: Put | I24: Sell | J24: May19'23 | K24: 145 | L24: 1 | M24: 274 | N24: 1.05 | O24: =M24-N24 -> 272.95 | P24: -53.05 | Q24: =sum(O24:P24) -> 219.9 | R24: Ready to buy @145 | S24: 0.86 | T24: 0.82 | U24: 14234 | V24: <1% | W24: =Q24/U24 -> 0.015448925
A26: 45006 | B26: CROX | H26: Call | I26: Sell | J26: May19'23 | K26: 130 | L26: 1 | M26: 640 | N26: 0.2 | O26: =M26-N26 -> 639.8 | P26: =-156.32-38.25 -> -194.57 | Q26: =sum(O26:P26) -> 445.23 | R26: Ready to sell @125, rolled over to next month at 130 due to high growth. Closed 4/05/2023
A27: 45050 | B27: CROX | C27: 0.2 | D27: 0.556 | E27: 0.548 | F27: No | G27: 0.3 | H27: Put | I27: Sell | J27: May19'23 | K27: 100 | L27: 1 | M27: 164 | N27: 0.25 | O27: =M27-N27 -> 163.75 | P27: -34.25 | Q27: =sum(O27:P27) -> 129.5 | R27: Closed on 8/5/2023 | S27: 0.84 | T27: 0.8 | U27: 9840 | V27: <1% | W27: =Q27/U27 -> 0.013160569
A28: 45048 | B28: AAPL | C28: 0.1806 | D28: 0.259 | E28: 0.187 | F28: Yes | G28: 0.1 | H28: Put | I28: Sell | J28: Jun16'23 | K28: 155 | L28: 1 | M28: 214 | N28: 1.04 | O28: =M28-N28 -> 212.96 | P28: =-78.04 -> -78.04 | Q28: =sum(O28:P28) -> 134.92 | R28: Ready to buy @155 | S28: 0.89 | T28: 0.86 | U28: 15318 | V28: <1% | W28: =Q28/U28 -> 0.0088079384
A29: 44993 | B29: GOOGL | C29: 0.2 | D29: 0.3 | E29: 0.4 | F29: No | G29: 0.1 | H29: Iron condor | I29: Sell | J29: May19'23 | K29: 80/85 105/110 | L29: 5 | M29: 495 | N29: =6.37+0.75*3+0.25+3.25+1.25+1.05+0.62+0.63+0.7+0.71+0.31+0.32+0.04+0.03+0.07 -> 17.85 | O29: =M29-N29+5*5+-908-227-206+882-103*3+441*3 -> 1057.15 | P29: =-256.91-6997.25+4902.7 -> -2351.46 | Q29: =sum(O29:P29) -> -1294.31 | R29: Rolled over to May, bull put expired, rolled to 106/110 | S29: 0.73 | T29: 0.68 | U29: 2007 | V29: 0.14 | W29: =Q29/U29 -> -0.64489786
A30: 45008 | B30: SPY | C30: 0.243 | D30: 0.198 | E30: 0.1867 | F30: No | G30: 0.02 | H30: Bear call | I30: Sell | J30: May19'23 | K30: 411/413 | L30: 10 | M30: 610 | N30: =11.76+1.75*2+1.8*2+9.54+9.51++0.84*2+1.54*2 -> 42.67 | O30: =M30-N30-1870*2+4770*2+1440-6008+180-751+182-753+1017 -> 1674.33 | P30: =-1450-5.97-5.95-4.43-4.41-1.54-1.54-1624 -> -3097.84 | Q30: =sum(O30:P30) -> -1423.51 | R30: Mistake with closing too early as was showing profit when it was not.
A31: 45043 | B31: SPY | C31: 0.187 | D31: 0.134 | E31: 0.1354 | F31: No | G31: 0.01 | H31: Bull put | I31: Sell | J31: May19'23 | K31: 397/395 | L31: 10 | M31: 310 | N31: 20.76 | O31: =M31-N31 -> 289.24 | Q31: =sum(O31:P31) -> 289.24 | S31: 0.92 | T31: 0.92 | U31: 1819 | V31: 0.057 | W31: =Q31/U31 -> 0.15901045
A33: 45055 | B33: SPY | C33: 0.17 | D33: 0.153 | E33: 0.114 | F33: No | G33: 0.01 | H33: Bear call | I33: Sell | J33: Jun16'23 | K33: 427/429 | L33: 10 | M33: 470 | N33: =21.66+23.83 -> 45.49 | O33: =M33-N33+850+899+665.93+561.4 -> 3400.84 | P33: =-1153.83-1034-1147.65-1101.26-1531.26 -> -5968 | Q33: =sum(O33:P33) -> -2567.16 | R33: Moving to higher levels | S33: 0.76 | T33: 0.75 | U33: 1527 | V33: 0.22 | W33: =Q33/U33 -> -1.6811788
A34: 45055 | B34: SPY | C34: 0.17 | D34: 0.153 | E34: 0.114 | F34: No | G34: 0.01 | H34: Bull put | I34: Sell | J34: Jun16'23 | K34: 391/389 | L34: 10 | M34: 280 | N34: =23.86+21.86 -> 45.72 | O34: =M34-N34+270+172+226.19+227.63+196.19 -> 1326.29 | P34: -58.01 | Q34: =sum(O34:P34) -> 1268.28 | R34: Moving to higher levels 418/416, 421/419, 424/422 | S34: 0.86 | T34: 0.86 | U34: 1739 | V34: 0.12 | W34: =Q34/U34 -> 0.7293157
A35: 45057 | B35: CROX | C35: 0.17 | D35: 0.468 | E35: 0.542 | F35: No | G35: 0.2 | H35: Bull put | I35: Sell | J35: Jun16'23 | K35: 105 | L35: 1 | M35: 269 | N35: 0.25 | O35: =M35-N35 -> 268.75 | Q35: =sum(O35:P35) -> 268.75 | S35: 0.82 | T35: 0.77 | U35: 10234 | V35: <1% | W35: =Q35/U35 -> 0.026260504
A36: 45063 | B36: ASAN | C36: 0.17 | D36: 0.788 | E36: 0.516 | F36: Yes | G36: 0.15 | H36: Call | I36: Sell | J36: Jun16'23 | K36: 20 | L36: 3 | M36: 420 | N36: 0.14 | O36: =M36-N36 -> 419.86 | Q36: =sum(O36:P36) -> 419.86 | R36: Assigned but OK | S36: 0.68 | T36: 0.57
A37: 45071 | B37: GOOGL | C37: 0.19 | D37: 0.287 | E37: 0.315 | F37: No | G37: 0.1 | H37: Call | I37: Sell | J37: Jun16'23 | K37: 130 | L37: 1 | M37: 127 | N37: 1.04 | O37: =M37-N37 -> 125.96 | Q37: =sum(O37:P37) -> 125.96 | S37: 0.79 | T37: 0.75
A39: 45097 | B39: CROX | C39: 0.14 | D39: 0.47 | E39: 0.44 | F39: No | G39: 0.2 | H39: Put | I39: Sell | J39: Jul21'23 | K39: 105 | L39: 1 | M39: 496 | N39: 0.26 | O39: =M39-N39 -> 495.74 | P39: -9.05 | Q39: =sum(O39:P39) -> 486.69 | S39: 0.68 | T39: 0.55 | U39: 9998 | V39: <1% | W39: 0.05
A40: 45097 | B40: GOOGL | C40: 0.14 | D40: 0.24 | E40: 0.29 | F40: No | G40: 0.05 | H40: Put | I40: Sell | J40: Jul21'23 | K40: 120 | L40: 1 | M40: 196 | N40: 0.63 | O40: =M40-N40 -> 195.37 | P40: -23.46 | Q40: =sum(O40:P40) -> 171.91 | S40: 0.75 | T40: 0.67 | U40: 11803 | V40: <1% | W40: 0.02
A41: 45097 | B41: ASAN | C41: 0.15 | D41: 0.59 | E41: 0.68 | F41: No | G41: 0.1 | H41: Call | I41: Sell | J41: Jul21'23 | K41: 25 | L41: 1 | M41: 131 | N41: 1.9 | O41: =M41-N41 -> 129.1 | P41: -18.05 | Q41: =sum(O41:P41) -> 111.05 | S41: 0.68 | T41: 0.57 | V41: <1%
A43: 45121 | B43: GOOGL | C43: 0.14 | D43: 0.3 | E43: 0.26 | F43: Yes | G43: 0.1 | H43: Call | I43: Sell | J43: Aug18'23 | K43: 130 | L43: 1 | M43: 297 | N43: 0.63 | O43: =M43-N43 -> 296.37 | Q43: =sum(O43:P43) -> 296.37 | R43: Expired OTM | S43: 0.72 | T43: 0.63 | V43: <1%
A44: 45121 | B44: CROX | C44: 0.14 | D44: 0.6 | E44: 0.41 | F44: No | G44: 0.3 | H44: Call | I44: Sell | J44: Aug18'23 | K44: 135 | L44: 1 | M44: 541 | N44: 0.26 | O44: =M44-N44 -> 540.74 | P44: -15.05 | Q44: =sum(O44:P44) -> 525.69 | R44: Closed on 27/07 | S44: 0.73 | T44: 0.66 | V44: <1%
A45: 45124 | B45: AAPL | C45: 0.137 | D45: 0.216 | E45: 0.172 | F45: No | G45: 0.05 | H45: Put | I45: Sell | J45: Aug18'23 | K45: 180 | L45: 1 | M45: 111 | N45: 1.04 | O45: =M45-N45 -> 109.96 | Q45: =sum(O45:P45) -> 109.96 | R45: Assigned | S45: 0.91 | T45: 0.89 | U45: 17811 | V45: <1% | W45: 0.01
A46: 45124 | B46: SPY | C46: 0.137 | D46: 0.11 | E46: 0.1 | F46: No | G46: 0.01 | H46: Bear call | I46: Sell | J46: Aug18'23 | K46: 466/468 | L46: 10 | M46: 340 | N46: 23.82 | O46: =M46-N46 -> 316.18 | P46: -134.03 | Q46: =sum(O46:P46) -> 182.15 | R46: Closed on 3/08 | S46: 0.8 | T46: 0.79 | U46: 1651 | V46: 0.17 | W46: =O46/U46 -> 0.19150818
A47: 45134 | B47: CROX | C47: 0.1575 | D47: 0.465 | E47: 0.65 | F47: Yes | G47: 0.3 | H47: Put | I47: Sell | J47: Aug18'23 | K47: 95 | L47: 1 | M47: 169 | N47: 0.25 | O47: =M47-N47 -> 168.75 | Q47: =sum(O47:P47) -> 168.75 | R47: Assigned | S47: 0.92 | U47: 9412 | W47: 0.01
A48: 45146 | B48: SPY | C48: 0.16 | D48: 0.13 | E48: 0.1 | F48: No | G48: 0.01 | H48: Bear call | I48: Sell | J48: Aug18'23 | K48: 459/461 | L48: 10 | M48: 230 | N48: 21.43 | O48: =M48-N48 -> 208.57 | Q48: =sum(O48:P48) -> 208.57 | R48: Expired OTM | S48: 0.85 | T48: 0.85 | U48: 1807 | V48: 0.11 | W48: =O48/U48 -> 0.11542335
A49: 45138 | B49: ASAN | C49: 0.15 | D49: 0.7 | E49: 0.555 | F49: Yes | G49: 0.1 | H49: Call | I49: Sell | J49: Sep15'23 | K49: 25 | L49: 1 | M49: 211 | N49: 0.2 | O49: =M49-N49 -> 210.8 | P49: -85.9 | Q49: =sum(O49:P49) -> 124.9 | R49: Closed on 09/08/2023 | S49: 0.67 | T49: 0.54
A50: 45148 | B50: XP | C50: 0.165 | D50: 80.7 | E50: 0.43 | G50: 0.05 | H50: Call | I50: Sell | J50: Aug18'23 | K50: 28.5 | L50: 5 | M50: 150 | N50: 0.24 | O50: =M50-N50 -> 149.76 | Q50: =sum(O50:P50) -> 149.76 | R50: Wall of calls at 28 | S50: 0.82 | T50: 0.79
A52: 45159 | B52: CROX | C52: 0.183 | D52: 0.42 | E52: 0.45 | F52: No | G52: 0.2 | H52: Call | I52: Sell | J52: Sep 15'23 | K52: 95 | L52: 1 | M52: 550 | N52: 0.31 | O52: =M52-N52 -> 549.69 | Q52: =sum(O52:P52) -> 549.69 | S52: 0.62 | T52: 0.43
A53: 45159 | B53: GOOGL | C53: 0.183 | D53: 0.28 | E53: 0.32 | F53: No | G53: 0.02 | H53: Call | I53: Sell | J53: Sep 15'23 | K53: 132.5 | L53: 1 | M53: 187 | N53: 0.63 | O53: =M53-N53 -> 186.37 | Q53: =sum(O53:P53) -> 186.37 | R53: Assigned | S53: 0.74 | T53: 0.67
A54: 45159 | B54: AAPL | C54: 0.183 | D54: 0.21 | E54: 0.2 | F54: No | G54: 0.05 | H54: Call | I54: Sell | J54: Sep 15'23 | K54: 182.5 | L54: 1 | M54: 126 | N54: 1.04 | O54: =M54-N54 -> 124.96 | Q54: =sum(O54:P54) -> 124.96 | S54: 0.78 | T54: 0.73
A55: 45159 | B55: ASAN | C55: 0.183 | D55: 0.68 | E55: 0.53 | F55: No | G55: 0.05 | H55: Call | I55: Sell | J55: Sep 15'23 | K55: 22 | L55: 4 | M55: 436 | N55: 0.39 | O55: =M55-N55 -> 435.61 | P55: -30.2 | Q55: =sum(O55:P55) -> 405.41 | S55: 0.71 | T55: 0.62
A56: 45159 | B56: NKLA | C56: 0.183 | D56: 0.21 | E56: 0.2 | F56: No | G56: 0.05 | H56: Put | I56: Sell | J56: Sep 15'23 | K56: 1.5 | L56: 5 | M56: 140 | N56: 3.46 | O56: =M56-N56 -> 136.54 | P56: -203.5 | Q56: =sum(O56:P56) -> -66.96 | S56: 0.7 | T56: 0.54 | U56: 622 | W56: =O56/U56 -> 0.21951768
A57: 45166 | B57: SPY | C57: 0.167 | D57: 0.132 | E57: 0.112 | F57: No | G57: 0.02 | H57: Calendar Call | I57: Buy | J57: Sep 08/Sep 22 | K57: 441 | L57: 2 | M57: 486 | N57: 1.34 | O57: =M57-N57 -> 484.66 | P57: -416 | Q57: =sum(O57:P57) -> 68.66 | S57: 0.41 | U57: 414
A58: 45166 | B58: SPY | C58: 0.167 | D58: 0.132 | E58: 0.112 | F58: No | G58: 0.02 | H58: Bear call | I58: Sell | J58: Sep 15'23 | K58: 455/457 | L58: 10 | M58: 240 | N58: 23.83 | O58: =M58-N58 -> 216.17 | P58: -30.03 | Q58: =sum(O58:P58) -> 186.14 | S58: 0.86 | T58: 0.85 | U58: 1755 | V58: 0.11 | W58: =O58/U58 -> 0.12317379
A59: 45170 | B59: SPY | C59: 0.15 | D59: 0.11 | E59: 0.11 | F59: No | G59: 0.02 | H59: Calendar Call | I59: Buy | J59: Sep 08/Sep 22 | K59: 451 | L59: 2 | M59: 338 | N59: 4.77 | O59: =M59-N59 -> 333.23 | P59: -429 | Q59: =sum(O59:P59) -> -95.77 | S59: 0.38 | U59: 426 | W59: 0.58
A60: 45176 | B60: SPY | C60: 0.16 | D60: 0.118 | E60: 0.115 | F60: No | G60: 0.02 | H60: Calendar Call | I60: Buy | J60: Sep 15/Sep 29 | K60: 444 | L60: 2 | M60: 266 | N60: 1.42 | O60: =M60-N60 -> 264.58 | P60: -433 | Q60: =sum(O60:P60) -> -168.42 | S60: 0.62 | U60: 442 | W60: 1.2
A62: 45205 | B62: CROX | C62: 0.18 | D62: 0.54 | E62: 0.36 | F62: ? | G62: 0.2 | H62: Call | I62: Sell | J62: Nov 17'23 | K62: 95 | L62: 1 | M62: 279 | N62: 0.24 | O62: =M62-N62 -> 278.76 | Q62: =sum(O62:P62) -> 278.76 | S62: 0.76 | T62: 0.72 | V62: <1%
A63: 45205 | B63: GOOGL | C63: 0.18 | D63: 0.3 | E63: 0.22 | F63: ? | G63: 0.1 | H63: Put | I63: Sell | J63: Nov 17'23 | K63: 130 | L63: 1 | M63: 275 | N63: 1.03 | O63: =M63-N63 -> 273.97 | Q63: =sum(O63:P63) -> 273.97 | S63: 0.79 | T63: 0.72 | U63: 12648 | V63: <1%
A64: 45205 | B64: SPY | C64: 0.18 | D64: 0.15 | E64: 0.12 | F64: No | G64: 0.01 | H64: Bull put | I64: Sell | J64: Oct 20'23 | K64: 415/413 | L64: 10 | M64: 250 | N64: 14.85 | O64: =M64-N64 -> 235.15 | P64: 0 | Q64: =sum(O64:P64) -> 235.15 | S64: 0.87 | T64: 0.86 | U64: 1756 | V64: 0.1 | W64: =O64/U64 -> 0.1339123
A65: 45205 | B65: ASAN | C65: 0.18 | D65: 0.55 | E65: 0.57 | F65: ? | G65: 0.15 | H65: Call | I65: Sell | J65: Nov 17'23 | K65: 17.5 | L65: 4 | M65: 384 | N65: 0.43 | O65: =M65-N65 -> 383.57 | Q65: =sum(O65:P65) -> 383.57 | R65: Assigned | S65: 0.68 | T65: 0.57
A66: 45205 | B66: AAPL | C66: 0.18 | D66: 0.25 | E66: 0.24 | F66: ? | G66: 0.1 | H66: Call | I66: Sell | J66: Nov 17'23 | K66: 185 | L66: 1 | M66: 286 | N66: 0.62 | O66: =M66-N66 -> 285.38 | P66: -38.84 | Q66: =sum(O66:P66) -> 246.54 | S66: 0.74 | T66: 0.68
A67: 10/112023 | B67: SPY | C67: 0.14 | D67: 0.117 | E67: 0.136 | F67: No | G67: 0.01 | H67: Bear call | I67: Sell | J67: Nov 24'23 | K67: 448/450 | L67: 10 | M67: 220 | N67: 23.6 | O67: =M67-N67 -> 196.4 | P67: =1286.35-1363.63-2065.85 -> -2143.13 | Q67: =sum(O67:P67) -> -1946.73 | R67: Rolled for 1 week to 24th | S67: 0.84 | T67: 0.83 | U67: 1778 | V67: 0.11 | W67: 0.12
A69: 45240 | B69: AAPL | C69: 0.14 | D69: 0.174 | E69: 0.205 | F69: ? | G69: 0.01 | H69: Call | I69: Sell | J69: Dec 15'23 | K69: 190 | L69: 1 | M69: 259 | N69: 1.03 | O69: =M69-N69 -> 257.97 | Q69: =sum(O69:P69) -> 257.97 | R69: Assigned | S69: 0.7 | T69: 0.61
A70: 45259 | B70: CROX | C70: 0.12 | D70: 0.39 | E70: 0.63 | F70: ? | H70: Call | I70: Sell | J70: Dec 15'23 | K70: 110 | L70: 2 | M70: 272 | N70: 0.71 | O70: =M70-N70 -> 271.29 | Q70: =sum(O70:P70) -> 271.29 | S70: 0.79 | T70: 0.75
A71: 45259 | B71: GOOGL | C71: 0.12 | D71: 0.2 | E71: 0.31 | F71: ? | H71: Put | I71: Sell | J71: Dec 15'23 | K71: 135 | L71: 1 | M71: 214 | N71: 1.03 | O71: =M71-N71 -> 212.97 | Q71: =sum(O71:P71) -> 212.97 | R71: Assigned | S71: 0.66 | T71: 0.52
A72: 45259 | B72: SPY | C72: 0.12 | D72: 0.113 | E72: 0.117 | F72: No | G72: 0.02 | H72: Bear Call | I72: Sell | J72: Dec 15'23 | K72: 465/467 | L72: 10 | M72: 310 | N72: 17.82 | O72: =M72-N72 -> 292.18 | P72: =4.9*200-0.89-6.91*200-0.88+483-684-0.45-0.44+481-0.45-682-0.44+200*4.88-0.69-200*6.84-0.68+300*4.89-0.92-300*6.84-0.9+470-666-0.7-0.69 -> -1985.13 | Q72: =sum(O72:P72) -> -1692.95 | S72: 0.83 | T72: 0.83 | U72: 1675 | V72: 0.13 | W72: 0.19
A74: 45268 | B74: ASAN | C74: 0.125 | D74: 0.48 | E74: 0.73 | F74: No | G74: 0.1 | H74: Put | I74: Sell | J74: Jan 19'24 | K74: 17.5 | L74: 4 | M74: 200 | N74: =1.23 -> 1.23 | O74: =M74-N74 -> 198.77 | Q74: =sum(O74:P74) -> 198.77 | R74: Expired | S74: 0.78
A75: 45278 | B75: CROX | H75: Put | I75: Sell | J75: Jan 19'24 | K75: 97 | L75: 1 | M75: 220 | N75: 0.04 | O75: =M75-N75 -> 219.96 | Q75: =sum(O75:P75) -> 219.96 | R75: Expired
A76: 45278 | B76: AAPL | H76: Bear Put | I76: bought | J76: Jan 19'24 | K76: 190/195 | L76: 1 | M76: =136-282+924.94 -> 778.94 | N76: 2.09 | O76: =M76-N76 -> 776.85 | Q76: =sum(O76:P76) -> 776.85 | R76: Assigned but made profit
A77: 45278 | B77: GOOGL | H77: Call | I77: Sell | J77: Jan 19'24 | K77: 140 | L77: 1 | M77: 234 | N77: 1.03 | O77: =M77-N77 -> 232.97 | Q77: =sum(O77:P77) -> 232.97 | R77: Assigned but OK
A79: Corporate calendar
A80: 45323 | B80: AAPL
A81: 45323 | B81: GOOGL
A82: 45337 | B82: CROX

Sheet Options 2024
C1: How Market is doing? | D1: Is option expensive or cheap, should I Sell/Buy? | F1: Volatility ahead? | G1: Liquide? | Q1: =sum(Q3:Q78) -> 11948.69 | Y1: @
A2: Trans date | B2: Tiker | C2: VIX | D2: IV | E2: Hist. volatility | F2: Corporate events? | G2: Bid/Ask spread | H2: Type | I2: Action | J2: Expiration | K2: Strike | L2: Qty | M2: Amount | N2: Comission | O2: Total Profit | P2: Total loss | Q2: Total P&L | R2: Comment | S2: Profit % | T2: Profit probability | U2: Max Win probab | V2: Max Loss | W2: Max Lose probab | X2: Return / Risk | Y2: Assigned
A3: 45313 | B3: GOOGL | C3: 0.13 | D3: 0.31 | E3: 0.25 | F3: Yes | G3: 0.05 | H3: Put | I3: Sell | J3: 16.02.2024 | K3: 140 | L3: 1 | M3: 208 | N3: 0.63 | O3: =M3-N3 -> 207.37 | Q3: =sum(O3:P3) -> 207.37 | R3: Expired OOM | S3: =O3/(L3*100)/K3 -> 0.014812143 | T3: 0.78 | U3: 0.72 | V3: 13736 | W3: <1% | X3: 0.02 | Z3: =K3*L3*100 -> 14000
A4: 45313 | B4: AAPL | C4: 0.13 | D4: 0.23 | E4: 0.2 | F4: Yes | G4: 0.01 | H4: Call | I4: Sell | J4: 16.02.2024 | K4: 200 | L4: 1 | M4: 225 | N4: 1.04 | O4: =M4-N4 -> 223.96 | Q4: =sum(O4:P4) -> 223.96 | R4: Expired OOM | S4: =O4/(L4*100)/K4 -> 0.011198 | T4: 0.75 | U4: 0.68 | Z4: =K4*L4*100 -> 20000
A5: 45314 | B5: CROX | C5: 0.13 | D5: 0.46 | E5: 0.52 | F5: Yes | G5: 0.5 | H5: Call | I5: Sell | J5: 16.02.2024 | K5: 110 | L5: 2 | M5: 362 | N5: 0.7 | O5: =M5-N5 -> 361.3 | Q5: =sum(O5:P5) -> 361.3 | R5: Assigned | S5: =O5/(L5*100)/K5 -> 0.016422727 | T5: 0.78 | U5: 0.74 | Y5: 1 | Z5: =K5*L5*100 -> 22000
A6: 45322 | B6: ASAN | C6: 0.14 | D6: 0.54 | E6: 0.42 | F6: No | G6: 0.1 | H6: Put | I6: Sell | J6: 16.02.2024 | K6: 17.5 | L6: 4 | M6: 224 | N6: 6.2 | O6: =M6-N6 -> 217.8 | Q6: =sum(O6:P6) -> 217.8 | R6: Expired OOM | S6: =O6/(L6*100)/K6 -> 0.031114286 | T6: 0.69 | U6: 0.58 | V6: 6763 | W6: <1% | X6: 0.03 | Z6: =K6*L6*100 -> 7000
Z7: =sum(Z3:Z6) -> 63000 | AA7: =sum(Q3:Q6)/Z7 -> 0.016038571
A8: 45342 | B8: AAPL | C8: 0.1553 | D8: 0.21 | E8: 0.22 | F8: No | G8: 0.05 | H8: Put | I8: Sell | J8: 15.03.2024 | K8: 170 | L8: 1 | M8: 87 | N8: 1.04 | O8: =M8-N8 -> 85.96 | Q8: =sum(O8:P8) -> 85.96 | R8: Expired | S8: =O8/(L8*100)/K8 -> 0.0050564706 | T8: 0.89 | U8: 0.87 | V8: 16853 | W8: <1% | X8: 0.01 | Z8: =K8*L8*100 -> 17000
A9: 45342 | B9: ASAN | C9: 0.1553 | D9: 0.845 | E9: 0.486 | F9: No | G9: 0.05 | H9: Put | I9: Sell | J9: 15.03.2024 | K9: 17.5 | L9: 2 | M9: 212 | N9: 0.7 | O9: =M9-N9 -> 211.3 | Q9: =sum(O9:P9) -> 211.3 | R9: Assigned | S9: =O9/(L9*100)/K9 -> 0.060371429 | T9: 0.72 | U9: 0.61 | V9: 3278 | W9: <1% | X9: 0.06 | Y9: 1 | Z9: =K9*L9*100 -> 3500
A10: 45342 | B10: GOOGL | C10: 0.1553 | D10: 0.248 | E10: 0.274 | F10: No | G10: 0.02 | H10: Put | I10: Sell | J10: 15.03.2024 | K10: 138 | L10: 1 | M10: 219 | N10: 1.04 | O10: =M10-N10 -> 217.96 | Q10: =sum(O10:P10) -> 217.96 | R10: Expired | S10: =O10/(L10*100)/K10 -> 0.015794203 | T10: 0.74 | U10: 0.65 | V10: 13534 | W10: <1% | X10: 0.02 | Z10: =K10*L10*100 -> 13800
A11: 45342 | B11: AAPL | C11: 0.1553 | D11: =D8 -> 0.21 | E11: =E8 -> 0.22 | F11: No | G11: 0.05 | H11: Call | I11: Sell | J11: 15.03.2024 | K11: 190 | L11: 1 | M11: 105 | N11: 0.53 | O11: =M11-N11 -> 104.47 | Q11: =sum(O11:P11) -> 104.47 | R11: Expired | S11: =O11/(L11*100)/K11 -> 0.0054984211 | T11: 0.83 | U11: 0.8 | Z11: =K11*L11*100 -> 19000
A12: 45342 | B12: CROX | C12: 0.1553 | D12: 0.385 | E12: 0.606 | F12: No | G12: 0.1 | H12: Put | I12: Sell | J12: 15.03.2024 | K12: 110 | L12: 2 | M12: =452+258.2 -> 710.2 | N12: 0.7 | O12: =M12-N12 -> 709.5 | P12: -49.44 | Q12: =sum(O12:P12) -> 660.06 | R12: Expired | S12: =O12/(L12*100)/K12 -> 0.03225 | T12: 0.76 | U12: 0.69 | V12: 21462 | W12: <1% | X12: 0.02 | Z12: =K12*L12*100 -> 22000
A13: 45343 | B13: ASAN | C13: 0.1581 | D13: 0.855 | E13: 0.51 | F13: No | G13: 0.1 | H13: Put | I13: Sell | J13: 15.03.2024 | K13: 17 | L13: 2 | M13: 232 | N13: 0.7 | O13: =M13-N13 -> 231.3 | Q13: =sum(O13:P13) -> 231.3 | R13: Assigned | S13: =O13/(L13*100)/K13 -> 0.068029412 | T13: 0.69 | U13: 0.57 | V13: 3158 | W13: <1% | X13: 0.07 | Y13: 1 | Z13: =K13*L13*100 -> 3400
Z14: =sum(Z8:Z13) -> 78700 | AA14: =sum(Q8:Q13)/Z14 -> 0.019200127
A15: 45370 | B15: GOOGL | C15: 0.14 | D15: 0.24 | E15: 0.28 | F15: No | G15: 0.05 | H15: Put | I15: Sell | J15: 19.04.2024 | K15: 140 | L15: 1 | M15: 136 | N15: 1.04 | O15: =M15-N15 -> 134.96 | P15: -27.05 | Q15: =sum(O15:P15) -> 107.91 | R15: Closed ahead | S15: =O15/(L15*100)/K15 -> 0.00964
A16: 45370 | B16: CROX | C16: 0.14 | D16: 0.35 | E16: 0.44 | F16: No | G16: 0.2 | H16: Put | I16: Sell | J16: 19.04.2024 | K16: 120 | L16: 1 | M16: 131 | N16: 0.25 | O16: =M16-N16 -> 130.75 | P16: -22.05 | Q16: =sum(O16:P16) -> 108.7 | R16: Closed ahead | S16: =O16/(L16*100)/K16 -> 0.010895833
A17: 45370 | B17: ASAN | C17: 0.14 | D17: 0.46 | E17: 0.52 | F17: No | G17: 0.1 | H17: Put | I17: Sell | J17: 19.04.2024 | K17: 15 | L17: 4 | M17: 184 | N17: 6.2 | O17: =M17-N17 -> 177.8 | Q17: =sum(O17:P17) -> 177.8 | R17: Put assigned | S17: =O17/(L17*100)/K17 -> 0.029633333 | Y17: 1 | Z17: =K17*L17*100 -> 6000
A18: 45372 | B18: AAPL | C18: 0.13 | D18: 0.22 | E18: 0.22 | F18: No | G18: 0.03 | H18: Put | I18: Sell | J18: 19.04.2024 | K18: 167.5 | L18: 1 | M18: 246 | N18: 0.63 | O18: =M18-N18 -> 245.37 | Q18: =sum(O18:P18) -> 245.37 | R18: Put assigned | S18: =O18/(L18*100)/K18 -> 0.014648955 | Y18: 1 | Z18: =K18*L18*100 -> 16750
A19: 45385 | B19: CROX | C19: 0.14 | D19: 0.35 | E19: 0.3 | F19: No | G19: 0.05 | H19: Put | I19: Sell | J19: 19.04.2024 | K19: 135 | L19: 1 | M19: 244 | O19: =M19-N19 -> 244 | Q19: =sum(O19:P19) -> 244 | R19: Put assigned | S19: =O19/(L19*100)/K19 -> 0.018074074 | Y19: 1 | Z19: =K19*L19*100 -> 13500
A20: 45385 | B20: GOOGL | C20: 0.14 | D20: 0.25 | E20: 0.27 | F20: No | G20: 0.03 | H20: Put | I20: Sell | J20: 19.04.2024 | K20: 150 | L20: 1 | M20: 143 | N20: 1.05 | O20: =M20-N20 -> 141.95 | Q20: =sum(O20:P20) -> 141.95 | R20: Expired OOM | S20: =O20/(L20*100)/K20 -> 0.0094633333 | Z20: =K20*L20*100 -> 15000
A21: 45407 | B21: GOOGL | C21: 0.166 | D21: 1.21 | E21: 0.3 | F21: Yes | G21: 0.04 | H21: Call | I21: Sell | J21: 19.04.2024 | K21: 150 | L21: 1 | M21: 219 | N21: 1.05 | O21: =M21-N21 -> 217.95 | Q21: =sum(O21:P21) -> 217.95 | R21: Expired OOM | S21: =O21/(L21*100)/K21 -> 0.01453 | T21: 0.76 | U21: 0.7 | Z21: =K21*L21*100 -> 15000
Z22: =sum(Z16:Z21) -> 66250 | AA22: =sum(Q15:Q21)/Z22 -> 0.018772528
A23: 45407 | B23: AAPL | C23: 0.166 | D23: 0.289 | E23: 0.197 | F23: Yes | G23: 0.03 | H23: Call | I23: Sell | J23: 17.05.2024 | K23: 175 | L23: 1 | M23: 280 | N23: 1.04 | O23: =M23-N23 -> 278.96 | Q23: =sum(O23:P23) -> 278.96 | R23: Call assigned | S23: =O23/(L23*100)/K23 -> 0.015940571 | T23: 0.73 | U23: 0.65 | Y23: 1 | Z23: =K23*L23*100 -> 17500
A24: 45408 | B24: CROX | C24: 0.15 | D24: 0.61 | E24: 0.36 | F24: Yes | G24: 0.15 | H24: Call | I24: Sell | J24: 17.05.2024 | K24: 140 | L24: 1 | M24: 250 | N24: 0.05 | O24: =M24-N24 -> 249.95 | Q24: =sum(O24:P24) -> 249.95 | R24: Call assigned | S24: =O24/(L24*100)/K24 -> 0.017853571 | T24: 0.8 | U24: 0.77 | Y24: 1 | Z24: =K24*L24*100 -> 14000
A25: 45411 | B25: ASAN | C25: 0.15 | D25: 0.48 | E25: 0.39 | F25: No | G25: 0.05 | H25: Call | I25: Sell | J25: 17.05.2024 | K25: 15.5 | L25: 4 | M25: 216 | N25: 1.4 | O25: =M25-N25 -> 214.6 | Q25: =sum(O25:P25) -> 214.6 | R25: Call assigned | S25: =O25/(L25*100)/K25 -> 0.034612903 | T25: 0.66 | U25: 0.55 | Y25: 1 | Z25: =K25*L25*100 -> 6200
A26: 45411 | B26: GOOGL | C26: 0.15 | D26: 0.28 | E26: 0.45 | F26: No | G26: 0.04 | H26: Put | I26: Sell | J26: 17.05.2024 | K26: 160 | L26: 1 | M26: 164 | N26: 1.04 | O26: =M26-N26 -> 162.96 | Q26: =sum(O26:P26) -> 162.96 | R26: Expired OOM | S26: =O26/(L26*100)/K26 -> 0.010185 | T26: 0.8 | U26: 0.75 | Z26: =K26*L26*100 -> 16000
Z27: =sum(Z23:Z26) -> 53700 | AA27: =sum(Q23:Q26)/Z27 -> 0.016880261
A28: 45436 | B28: CROX | C28: 0.12 | D28: 0.3 | E28: 0.41 | F28: No | G28: 0.2 | H28: Put | I28: Sell | J28: 21.06.2024 | K28: 140 | L28: 1 | M28: 150 | N28: 0.05 | O28: =M28-N28 -> 149.95 | Q28: =sum(O28:P28) -> 149.95 | S28: =O28/(L28*100)/K28 -> 0.010710714 | T28: 0.82 | U28: 0.79 | V28: 13799 | X28: 0.01 | Z28: =K28*L28*100 -> 14000
A29: 45436 | B29: ASAN | C29: 0.12 | D29: 0.79 | E29: 0.42 | F29: Yes | G29: 0.1 | H29: Put | I29: Sell | J29: 21.06.2024 | K29: 14.5 | L29: 4 | M29: 492 | N29: 1.39 | O29: =M29-N29 -> 490.61 | P29: =-472-1.41 -> -473.41 | Q29: =sum(O29:P29) -> 17.2 | R29: closed to avoid losses | S29: =O29/(L29*100)/K29 -> 0.084587931 | T29: 0.66 | U29: 0.5 | V29: 5277 | X29: 0.09
A30: 45436 | B30: GOOGL | C30: 0.12 | D30: 0.21 | E30: 0.43 | F30: No | G30: 0.05 | H30: Put | I30: Sell | J30: 21.06.2024 | K30: 170 | L30: 1 | M30: 193 | N30: 1.05 | O30: =M30-N30 -> 191.95 | Q30: =sum(O30:P30) -> 191.95 | S30: =O30/(L30*100)/K30 -> 0.011291176 | T30: 0.76 | U30: 0.7 | V30: 16756 | X30: 0.01 | Z30: =K30*L30*100 -> 17000
A31: 45447 | B31: AAPL | C31: 0.136 | D31: 0.23 | E31: 0.29 | F31: No | G31: 0.03 | H31: Call | I31: Sell | J31: 21.06.2024 | K31: 202.5 | L31: 1 | M31: 140 | N31: 1.05 | O31: =M31-N31 -> 138.95 | Q31: =sum(O31:P31) -> 138.95 | R31: Call assigned | S31: =O31/(L31*100)/K31 -> 0.0068617284 | T31: 0.8 | U31: 0.76 | Y31: 1 | Z31: =K31*L31*100 -> 20250
A32: 45447 | B32: ASAN | C32: 0.136 | D32: 0.45 | E32: 0.65 | F32: No | G32: 0.05 | H32: Call | I32: Sell | J32: 21.06.2024 | K32: 14.5 | L32: 4 | M32: 136 | N32: 1.4 | O32: =M32-N32 -> 134.6 | Q32: =sum(O32:P32) -> 134.6 | S32: =O32/(L32*100)/K32 -> 0.023206897 | T32: 0.85 | Z32: =K32*L32*100 -> 5800
Z33: =sum(Z28:Z32) -> 57050 | AA33: =sum(Q28:Q32)/Z33 -> 0.011089395
A34: 45460 | B34: CROX | C34: 0.13 | D34: 0.33 | E34: 0.4 | F34: No | G34: 0.2 | H34: Put | I34: Sell | J34: 19.07.2024 | K34: 150 | L34: 1 | M34: 211 | N34: 0.01 | O34: =M34-N34 -> 210.99 | Q34: =sum(O34:P34) -> 210.99 | R34: Assigned | S34: =O34/(L34*100)/K34 -> 0.014066 | T34: 0.82 | U34: 0.78 | V34: 14724 | X34: 0.01 | Y34: 1 | Z34: =K34*L34*100 -> 15000
A35: 45467 | B35: AAPL | C35: 0.13 | D35: 0.2 | E35: 0.23 | F35: No | H35: Put | I35: Sell | J35: 19.07.2024 | K35: 202.5 | L35: 1 | M35: 170 | N35: 1.04 | O35: =M35-N35 -> 168.96 | P35: -46.8 | Q35: =sum(O35:P35) -> 122.16 | R35: Closed in advance to book profit | S35: =O35/(L35*100)/K35 -> 0.0083437037 | T35: 0.79 | U35: 0.75 | V35: 20001 | X35: 0.01
A36: 45467 | B36: GOOGL | C36: 0.13 | D36: 0.21 | E36: 0.2 | F36: No | G36: 0.05 | H36: Put | I36: Sell | J36: 19.07.2024 | K36: 172.5 | L36: 1 | M36: 144 | N36: 0.8 | O36: =M36-N36 -> 143.2 | P36: -28.46 | Q36: =sum(O36:P36) -> 114.74 | R36: Closed in advance to book profit | S36: =O36/(L36*100)/K36 -> 0.0083014493 | T36: 0.81 | U36: 0.76 | V36: 17042 | X36: 0.01
A37: 45467 | B37: ASAN | C37: 0.13 | D37: 0.47 | E37: 0.66 | F37: No | G37: 0.1 | H37: Put | I37: Sell | J37: 19.07.2024 | K37: 12.5 | L37: 4 | M37: 216 | N37: 1.4 | O37: =M37-N37 -> 214.6 | Q37: =sum(O37:P37) -> 214.6 | S37: =O37/(L37*100)/K37 -> 0.04292 | T37: 0.66 | U37: 0.53 | V37: 4781 | X37: 0.04 | Z37: =K37*L37*100 -> 5000
A38: 45474 | B38: AAPL | C38: 0.12 | D38: 0.2 | E38: 0.23 | F38: No | G38: 0.03 | H38: Put | I38: Sell | J38: 19.07.2024 | K38: 210 | L38: 1 | M38: 157 | N38: 1.04 | O38: =M38-N38 -> 155.96 | P38: -10.5 | Q38: =sum(O38:P38) -> 145.46 | R38: Closed in advance to book profit | S38: =O38/(L38*100)/K38 -> 0.0074266667 | T38: 0.79 | U38: 0.74 | V38: 20786
A39: 45475 | B39: GOOGL | C39: 0.12 | D39: 0.19 | E39: 0.19 | F39: No | G39: 0.04 | H39: Put | I39: Sell | J39: 19.07.2024 | K39: 180 | L39: 1 | M39: 118 | N39: 0.8 | O39: =M39-N39 -> 117.2 | Q39: =sum(O39:P39) -> 117.2 | R39: Assigned | S39: =O39/(L39*100)/K39 -> 0.0065111111 | T39: 0.81 | U39: 0.77 | V39: 17846 | X39: 0.01 | Y39: 1 | Z39: =K39*L39*100 -> 18000
A40: 45485 | B40: AAPL | C40: 0.12 | D40: 0.2 | E40: 0.24 | F40: No | G40: 0.03 | H40: Put | I40: Sell | J40: 19.07.2024 | K40: 227.5 | L40: 1 | M40: 139 | N40: 1.05 | O40: =M40-N40 -> 137.95 | Q40: =sum(O40:P40) -> 137.95 | R40: Assigned | S40: =O40/(L40*100)/K40 -> 0.0060637363 | T40: 0.82 | U40: 0.78 | V40: 22636 | X40: 0 | Y40: 1 | Z40: =K40*L40*100 -> 22750
Z41: =sum(Z35:Z40) -> 45750 | AA41: =sum(Q34:Q40)/Z41 -> 0.023237158
A42: 45495 | B42: AAPL | C42: 0.15 | D42: 0.27 | E42: 0.27 | F42: Yes | G42: 0.03 | H42: Call | I42: Sell | J42: 16.08.2024 | K42: 240 | L42: 1 | M42: 154 | N42: 1.04 | O42: =M42-N42 -> 152.96 | P42: -10.05 | Q42: =sum(O42:P42) -> 142.91 | R42: Closed in advance to book profit | S42: =O42/(L42*100)/K42 -> 0.0063733333 | T42: 0.83 | U42: 0.81
A43: 45495 | B43: GOOGL | C43: 0.15 | D43: 0.37 | E43: 0.2 | F43: Yes | G43: 0.05 | H43: Call | I43: Sell | J43: 16.08.2024 | K43: 200 | L43: 1 | M43: 174 | N43: 1.04 | O43: =M43-N43 -> 172.96 | P43: -11.05 | Q43: =sum(O43:P43) -> 161.91 | R43: Closed in advance to book profit | S43: =O43/(L43*100)/K43 -> 0.008648 | T43: 0.84 | U43: 0.82
A44: 45495 | B44: CROX | C44: 0.15 | D44: 0.59 | E44: 0.37 | F44: Yes | G44: 0.2 | H44: Put | I44: Sell | J44: 16.08.2024 | K44: 125 | L44: 1 | M44: 471 | N44: 0.26 | O44: =M44-N44 -> 470.74 | Q44: =sum(O44:P44) -> 470.74 | R44: Expired OOM | S44: =O44/(L44*100)/K44 -> 0.0376592 | T44: 0.73 | U44: 0.65 | V44: 11996 | Z44: =K44*L44*100 -> 12500
A45: 45497 | B45: ASAN | C45: 0.17 | D45: 0.5 | E45: 0.46 | F45: No | G45: 0.1 | H45: Put | I45: Sell | J45: 16.08.2024 | K45: 14 | L45: 4 | M45: 216 | N45: 1.4 | O45: =M45-N45 -> 214.6 | Q45: =sum(O45:P45) -> 214.6 | R45: Assigned | S45: =O45/(L45*100)/K45 -> 0.038321429 | T45: 0.67 | U45: 0.55 | V45: 5361 | X45: 0.04 | Y45: 1 | Z45: =K45*L45*100 -> 5600
A46: 45502 | B46: GOOGL | C46: 0.16 | D46: 0.27 | E46: 0.25 | F46: No | G46: 0.03 | H46: Call | I46: Sell | J46: 16.08.2024 | K46: 180 | L46: 1 | M46: 95 | N46: 1.04 | O46: =M46-N46 -> 93.96 | Q46: =sum(O46:P46) -> 93.96 | R46: Expired OOM | S46: =O46/(L46*100)/K46 -> 0.00522 | T46: 0.84 | U46: 0.82 | Z46: =K46*L46*100 -> 18000
Z47: =sum(Z42:Z46) -> 36100 | AA47: =sum(Q42:Q46)/Z47 -> 0.030031025
A48: 45523 | B48: GOOGL | C48: 0.16 | D48: 0.23 | E48: 0.37 | F48: No | G48: 0.03 | H48: Call | I48: Sell | J48: 20.09.2024 | K48: 175 | L48: 1 | M48: 154 | N48: 1.05 | O48: =M48-N48 -> 152.95 | P48: -13.11 | Q48: =sum(O48:P48) -> 139.84 | R48: Closed in advance to book profit | S48: =O48/(L48*100)/K48 -> 0.00874 | T48: 0.76 | U48: 0.71
A49: 45523 | B49: ASAN | C49: 0.16 | D49: 0.78 | E49: 0.56 | F49: Yes | G49: 0.1 | H49: Call | I49: Sell | J49: 20.09.2024 | K49: 14.5 | L49: 4 | M49: 324 | N49: 0.39 | O49: =M49-N49 -> 323.61 | P49: -41.61 | Q49: =sum(O49:P49) -> 282 | R49: Closed in advance to book profit | S49: =O49/(L49*100)/K49 -> 0.055794828 | T49: 0.7 | U49: 0.61
A50: 45523 | B50: CROX | C50: 0.16 | D50: 0.32 | E50: 0.54 | F50: No | G50: 0.15 | H50: Call | I50: Sell | J50: 20.09.2024 | K50: 150 | L50: 1 | M50: 174 | N50: 0.25 | O50: =M50-N50 -> 173.75 | Q50: =sum(O50:P50) -> 173.75 | R50: Expired OOM | S50: =O50/(L50*100)/K50 -> 0.011583333 | T50: 0.85 | U50: 0.84 | Z50: =K50*L50*100 -> 15000
A51: 45524 | B51: AAPL | C51: 0.16 | D51: 0.2 | E51: 0.42 | F51: No | G51: 0.03 | H51: Call | I51: Sell | J51: 20.09.2024 | K51: 235 | L51: 1 | M51: 257 | N51: 0.81 | O51: =M51-N51 -> 256.19 | Q51: =sum(O51:P51) -> 256.19 | R51: Expired OOM | S51: =O51/(L51*100)/K51 -> 0.010901702 | T51: 0.75 | U51: 0.69 | Z51: =K51*L51*100 -> 23500
A52: 45545 | B52: AAPL | C52: 0.19 | D52: 0.27 | E52: 0.41 | F52: No | G52: 0.05 | H52: Call | I52: Sell | J52: 20.09.2024 | K52: 230 | L52: 1 | M52: 96 | N52: 1.05 | O52: =M52-N52 -> 94.95 | Q52: =sum(O52:P52) -> 94.95 | R52: Expired OOM | S52: =O52/(L52*100)/K52 -> 0.0041282609 | T52: 0.83 | U52: 0.8 | Z52: =K52*L52*100 -> 23000
A53: 45545 | B53: ASAN | C53: 0.19 | D53: 0.52 | E53: 0.68 | F53: No | G53: 0.05 | H53: Put | I53: Sell | J53: 20.09.2024 | K53: 11 | L53: 4 | M53: 116 | N53: 0.37 | O53: =M53-N53 -> 115.63 | Q53: =sum(O53:P53) -> 115.63 | R53: Expired OOM | S53: =O53/(L53*100)/K53 -> 0.026279545 | T53: 0.7 | U53: 0.61 | V53: 4294 | X53: 0.02 | Z53: =K53*L53*100 -> 4400
Z54: =sum(Z48:Z53) -> 65900 | AA54: =sum(Q48:Q53)/Z54 -> 0.016120789
A55: 45558 | B55: GOOGL | C55: 0.159 | D55: 0.267 | E55: 0.257 | F55: No | G55: 0.1 | H55: Call | I55: Sell | J55: 18.10.2024 | K55: 165 | L55: 1 | M55: 304 | N55: 0.8 | O55: =M55-N55 -> 303.2 | Q55: =sum(O55:P55) -> 303.2 | R55: Expired OOM | S55: =O55/(L55*100)/K55 -> 0.018375758 | T55: 0.69 | U55: 0.57 | Z55: =K55*L55*100 -> 16500
A56: 45558 | B56: CROX | C56: 0.159 | D56: 0.372 | E56: 0.396 | F56: No | G56: 0.15 | H56: Call | I56: Sell | J56: 18.10.2024 | K56: 150 | L56: 1 | M56: 279 | N56: 0.26 | O56: =M56-N56 -> 278.74 | Q56: =sum(O56:P56) -> 278.74 | R56: Expired OOM | S56: =O56/(L56*100)/K56 -> 0.018582667 | T56: 0.74 | U56: 0.68 | Z56: =K56*L56*100 -> 15000
A57: 45558 | B57: AAPL | C57: 0.159 | D57: 0.207 | E57: 0.226 | F57: No | G57: 0.05 | H57: Call | I57: Sell | J57: 18.10.2024 | K57: 230 | L57: 1 | M57: 361 | N57: 0.87 | O57: =M57-N57 -> 360.13 | Q57: =sum(O57:P57) -> 360.13 | R57: Assigned | S57: =O57/(L57*100)/K57 -> 0.015657826 | T57: 0.69 | U57: 0.59 | Y57: 1 | Z57: =K57*L57*100 -> 23000
A58: 45559 | B58: ABR | C58: 0.1547 | D58: 0.31 | E58: 0.27 | F58: No | G58: 0.1 | H58: Call | I58: Sell | J58: 18.10.2024 | K58: 16 | L58: 6 | M58: 174 | N58: 0.56 | O58: =M58-N58 -> 173.44 | Q58: =sum(O58:P58) -> 173.44 | R58: Expired OOM | S58: =O58/(L58*100)/K58 -> 0.018066667 | T58: 0.69 | U58: 0.62 | Z58: =K58*L58*100 -> 9600
A59: 45561 | B59: MTDR | C59: 0.15 | D59: 0.38 | E59: 0.34 | F59: No | G59: 0.1 | H59: Put | I59: Sell | J59: 18.10.2024 | K59: 47.5 | L59: 1 | M59: 161 | N59: 0.26 | O59: =M59-N59 -> 160.74 | Q59: =sum(O59:P59) -> 160.74 | R59: Expired OOM | S59: =O59/(L59*100)/K59 -> 0.03384 | T59: 0.67 | U59: 0.53 | V59: 4576 | X59: 0.03 | Z59: =K59*L59*100 -> 4750
A60: 45567 | B60: NVDA | C60: 0.188 | D60: 0.46 | E60: 0.52 | F60: No | G60: 0.02 | H60: Put | I60: Sell | J60: 18.10.2024 | K60: 113 | L60: 1 | M60: 223 | N60: 1.05 | O60: =M60-N60 -> 221.95 | Q60: =sum(O60:P60) -> 221.95 | R60: Expired OOM | S60: =O60/(L60*100)/K60 -> 0.019641593 | T60: 0.77 | U60: 0.71 | V60: 11052 | X60: 0.02 | Z60: =K60*L60*100 -> 11300
Z61: =sum(Z55:Z60) -> 80150 | AA61: =sum(Q55:Q60)/Z61 -> 0.018692452
A62: 45593 | B62: AAPL | C62: 0.1953 | D62: 0.26 | E62: 0.23 | F62: Yes | G62: 0.03 | H62: Put | I62: Sell | J62: 15.11.2024 | K62: 220 | L62: 1 | M62: 182 | N62: 0.64 | O62: =M62-N62 -> 181.36 | Q62: =sum(O62:P62) -> 181.36 | R62: Expired OOM | S62: =O62/(L62*100)/K62 -> 0.0082436364 | T62: 0.85 | V62: 21770 | X62: 0.01 | Z62: =K62*L62*100 -> 22000
A63: 45593 | B63: GOOGL | C63: 0.1953 | D63: 0.37 | E63: 0.23 | F63: Yes | G63: 0.05 | H63: Call | I63: Sell | J63: 15.11.2024 | K63: 175 | L63: 1 | M63: 325 | N63: 1.05 | O63: =M63-N63 -> 323.95 | Q63: =sum(O63:P63) -> 323.95 | R63: Expired OOM | S63: =O63/(L63*100)/K63 -> 0.018511429 | T63: 0.74 | Z63: =K63*L63*100 -> 17500
A64: 45593 | B64: ASAN | C64: 0.1953 | D64: 0.53 | E64: 0.38 | F64: No | G64: 0.05 | H64: Call | I64: Sell | J64: 15.11.2024 | K64: 12.5 | L64: 4 | M64: 148 | N64: 2.83 | O64: =M64-N64 -> 145.17 | Q64: =sum(O64:P64) -> 145.17 | R64: Call assigned | S64: =O64/(L64*100)/K64 -> 0.029034 | T64: 0.7 | Y64: 1 | Z64: =K64*L64*100 -> 5000
A65: 45593 | B65: CROX | C65: 0.1953 | D65: 0.55 | E65: 0.38 | F65: Yes | G65: 0.2 | H65: Call | I65: Sell | J65: 15.11.2024 | K65: 150 | L65: 1 | M65: 410 | N65: 0.07 | O65: =M65-N65 -> 409.93 | P65: -5 | Q65: =sum(O65:P65) -> 404.93 | R65: Closed in advance to book profit | S65: =O65/(L65*100)/K65 -> 0.027328667 | T65: 0.76
A66: 45593 | B66: MTDR | C66: 0.1953 | D66: 0.408 | E66: 0.402 | F66: No | G66: 0.05 | H66: Put | I66: Sell | J66: 15.11.2024 | K66: 50 | L66: 1 | M66: 160 | N66: 0.06 | O66: =M66-N66 -> 159.94 | Q66: =sum(O66:P66) -> 159.94 | R66: Expired OOM | S66: =O66/(L66*100)/K66 -> 0.031988 | T66: 0.68 | V66: 4828 | X66: 0.03 | Z66: =K66*L66*100 -> 5000
A67: 45593 | B67: C | C67: 0.1953 | D67: 0.299 | E67: 0.248 | F67: No | G67: 0.02 | H67: Put | I67: Sell | J67: 15.11.2024 | K67: 62 | L67: 1 | M67: 124 | N67: 1.05 | O67: =M67-N67 -> 122.95 | Q67: =sum(O67:P67) -> 122.95 | R67: Expired OOM | S67: =O67/(L67*100)/K67 -> 0.019830645 | T67: 0.73 | V67: 6061 | X67: 0.02 | Z67: =K67*L67*100 -> 6200
A68: 45594 | B68: CROX | C68: 0.1939 | D68: 0.48 | E68: 0.84 | F68: No | G68: 0.15 | H68: Put | I68: Sell | J68: 15.11.2024 | K68: 105 | L68: 1 | M68: 165 | N68: 1.06 | O68: =M68-N68 -> 163.94 | Q68: =sum(O68:P68) -> 163.94 | R68: Put assigned | S68: =O68/(L68*100)/K68 -> 0.015613333 | T68: 0.8 | V68: 10322 | X68: 0.02 | Y68: 1 | Z68: =K68*L68*100 -> 10500
Z69: =sum(Z62:Z68) -> 66200 | AA69: =sum(Q62:Q68)/Z69 -> 0.022692447
A70: 45614 | B70: AAPL | C70: 0.154 | D70: 0.192 | E70: 0.204 | F70: No | G70: 0.02 | H70: Put | I70: Sell | J70: 20.12.2024 | K70: 220 | L70: 1 | M70: 191 | N70: 1.06 | O70: =M70-N70 -> 189.94 | Q70: =sum(O70:P70) -> 189.94 | R70: Expired OOM | S70: =O70/(L70*100)/K70 -> 0.0086336364 | T70: 0.83 | U70: 0.79 | V70: 21746 | X70: 0.01 | Z70: =K70*L70*100 -> 22000
A71: 45614 | B71: GOOGL | C71: 0.154 | D71: 0.228 | E71: 0.293 | F71: No | G71: 0.04 | H71: Call | I71: Sell | J71: 20.12.2024 | K71: 187.5 | L71: 1 | M71: 116 | N71: 1.06 | O71: =M71-N71 -> 114.94 | Q71: =sum(O71:P71) -> 114.94 | R71: Call assigned | S71: =O71/(L71*100)/K71 -> 0.0061301333 | Y71: 1 | Z71: =K71*L71*100 -> 18750
A72: 45615 | B72: C | C72: 0.167 | D72: 0.24 | E72: 0.32 | F72: No | H72: Put | I72: Sell | J72: 20.12.2024 | K72: 67 | L72: 1 | M72: 112 | N72: 1.06 | O72: =M72-N72 -> 110.94 | Q72: =sum(O72:P72) -> 110.94 | R72: Expired OOM | S72: =O72/(L72*100)/K72 -> 0.016558209 | T72: 0.77 | U72: 0.71 | V72: 6587 | X72: 0.01 | Z72: =K72*L72*100 -> 6700
A73: 45617 | B73: CROX | C73: 0.167 | D73: 0.38 | E73: 0.67 | F73: No | G73: 0.1 | H73: Call | I73: Sell | J73: 20.12.2024 | K73: 105 | L73: 1 | M73: 326 | N73: 0.26 | O73: =M73-N73 -> 325.74 | Q73: =sum(O73:P73) -> 325.74 | R73: Call assigned | S73: =O73/(L73*100)/K73 -> 0.031022857 | T73: 0.69 | U73: 0.59 | Y73: 1 | Z73: =K73*L73*100 -> 10500
A74: 45614 | B74: ASAN | C74: 0.14 | D74: 1.02 | E74: 0.43 | F74: Yes | G74: 0.05 | H74: Call | I74: Sell | J74: 20.12.2024 | K74: 16 | L74: 4 | M74: 416 | N74: 1.4 | O74: =M74-N74 -> 414.6 | Q74: =sum(O74:P74) -> 414.6 | R74: Call assigned | S74: =O74/(L74*100)/K74 -> 0.06478125 | T74: 0.69 | U74: 0.59 | Y74: 1 | Z74: =K74*L74*100 -> 6400
Z75: =sum(Z70:Z74) -> 64350 | AA75: =sum(Q70:Q74)/Z75 -> 0.017966744
A76: 45460 | B76: VTI | C76: 0.13 | D76: 0.13 | E76: 0.11 | F76: No | G76: 0.35 | H76: Put | I76: Buy | J76: 17.01.2025 | K76: 220 | L76: 2 | M76: -334 | N76: 1.39 | O76: =M76-N76 -> -335.39 | R76: Protective put moved to higher price
A77: 45376 | B77: VTI | C77: 0.13 | D77: 0.136 | E77: 0.11 | F77: No | G77: 0.6 | H77: Put | I77: Buy | J77: 17.01.2025 | K77: 185 | L77: 2 | M77: -342 | N77: 0.71 | O77: =M77-N77 -> -342.71 | R77: Protective put
A78: 45485 | B78: ABR | H78: Put | I78: Buy | J78: 20.09.2024 | K78: 12 | L78: 5 | M78: -720 | N78: 1.77 | O78: =M78-N78 -> -721.77 | Q78: =sum(O78:P78) -> -721.77 | R78: Expired
Y79: =count(Q3:Q74) -> 62 | AA79: =sum(AA3:AA75) -> 0.2107215
Y80: =sum(Y3:Y78)/Y79 -> 0.32258065

Sheet Options 2025
Q1: =sum(Q3:Q979) -> 23955.13
A2: Trans date | B2: Tiker | C2: VIX | D2: IV (>30%) | E2: Hist. vol. | F2: Corporate events? | G2: Bid/Ask spread | H2: Type | I2: Action | J2: Expiration | K2: Strike | L2: Qty | M2: Amount | N2: Comission | O2: Total Profit | P2: Total loss | Q2: Total P&L | R2: Comment | S2: Profit % | T2: Profit probability (>70%) | U2: Max Win probab | V2: Max Loss | W2: Max Lose probab | X2: Return / Risk
A3: 45666 | B3: GOOGL | C3: 0.186 | D3: 0.32 | E3: 0.29 | F3: Y | G3: 0.1 | H3: Put | I3: Sell | J3: 45709 | K3: 180 | L3: 1 | M3: 311 | N3: 0.8 | O3: =M3-N3 -> 310.2 | Q3: =sum(O3:P3) -> 310.2 | R3: Put assigned | S3: =Q3/(K3*100*L3) -> 0.017233333 | T3: 0.81 | U3: 0.77 | V3: 17604 | W3: <1% | X3: 0.02
A4: 45666 | B4: AAPL | C4: 0.186 | D4: 0.246 | E4: 0.196 | F4: Y | G4: 0.05 | H4: Put | I4: Sell | J4: 45709 | K4: 220 | L4: 1 | M4: 249 | N4: 1.05 | O4: =M4-N4 -> 247.95 | Q4: =sum(O4:P4) -> 247.95 | R4: Expired OOM | S4: =Q4/(K4*100*L4) -> 0.011270455 | T4: 0.86 | U4: 0.82 | V4: 21647 | W4: <1% | X4: 0.01
A5: 45671 | B5: CROX | C5: 0.186 | D5: 0.55 | E5: 0.35 | F5: Y | G5: 0.1 | H5: Put | I5: Sell | J5: 45709 | K5: 95 | L5: 1 | M5: 331 | N5: 1.08 | O5: =M5-N5 -> 329.92 | Q5: =sum(O5:P5) -> 329.92 | R5: Expired OOM | S5: =Q5/(K5*100*L5) -> 0.034728421 | T5: 0.78 | U5: 0.72 | V5: 9146 | W5: <1% | X5: 0.03
A6: 45685 | B6: C | C6: 0.167 | D6: 0.216 | E6: 0.256 | F6: N | G6: 0.02 | H6: Put | I6: Sell | J6: 45709 | K6: 78 | L6: 1 | M6: 112 | N6: 1.05 | O6: =M6-N6 -> 110.95 | Q6: =sum(O6:P6) -> 110.95 | R6: Expired OOM | S6: =Q6/(K6*100*L6) -> 0.014224359 | T6: 0.74 | U6: 0.65 | V6: 7670 | W6: <1% | X6: 0.01
A7: 45694 | B7: NVDA | C7: 0.1549 | D7: 0.44 | E7: 0.67 | F7: N | G7: 0.02 | H7: Put | I7: Sell | J7: 45709 | K7: 121 | L7: 1 | M7: 196 | N7: 1.05 | O7: =M7-N7 -> 194.95 | Q7: =sum(O7:P7) -> 194.95 | R7: Expired OOM | S7: =Q7/(K7*100*L7) -> 0.01611157 | T7: 0.8 | U7: 0.74 | V7: 11891 | W7: <1% | X7: 0.02
A9: 45712 | B9: GOOGL | C9: 0.1749 | D9: 0.26 | E9: 0.36 | F9: N | G9: 0.03 | H9: Call | I9: Sell | J9: 45737 | K9: 190 | L9: 1 | M9: 177 | N9: 1.05 | O9: =M9-N9 -> 175.95 | Q9: =sum(O9:P9) -> 175.95 | R9: Expired OOM | S9: =Q9/(K9*100*L9) -> 0.0092605263 | T9: 0.8 | U9: 0.76
A10: 45712 | B10: AAPL | C10: 0.1749 | D10: 0.22 | E10: 0.3 | F10: N | G10: 0.03 | H10: Put | I10: Sell | J10: 45737 | K10: 237.5 | L10: 1 | M10: 218 | N10: 1.06 | O10: =M10-N10 -> 216.94 | Q10: =sum(O10:P10) -> 216.94 | R10: Put assigned | S10: =Q10/(K10*100*L10) -> 0.0091343158 | T10: 0.84 | U10: 0.8 | V10: 23466 | W10: <1% | X10: 0.01
A11: 45712 | B11: CROX | C11: 0.1749 | D11: 0.39 | E11: 0.77 | F11: N | G11: 0.15 | H11: Put | I11: Sell | J11: 45737 | K11: 100 | L11: 1 | M11: 214 | N11: 1.06 | O11: =M11-N11 -> 212.94 | Q11: =sum(O11:P11) -> 212.94 | R11: Expired OOM | S11: =Q11/(K11*100*L11) -> 0.021294 | T11: 0.78 | U11: 0.72 | V11: 9785 | W11: <1% | X11: 0.02
A12: 45712 | B12: CROX | C12: 0.1749 | D12: 0.39 | E12: 0.77 | F12: N | H12: Call | I12: Sell | J12: 45737 | K12: 115 | L12: 1 | M12: 121 | N12: 0.26 | O12: =M12-N12 -> 120.74 | Q12: =sum(O12:P12) -> 120.74 | R12: Expired OOM | S12: =Q12/(K12*100*L12) -> 0.01049913 | T12: 0.81 | U12: 0.78
A13: 45712 | B13: NVDA | C13: 0.1749 | D13: 0.64 | E13: 0.67 | F13: N | G13: 0.1 | H13: Put | I13: Sell | J13: 45737 | K13: 120 | L13: 1 | M13: 339 | N13: 0.81 | O13: =M13-N13 -> 338.19 | Q13: =sum(O13:P13) -> 338.19 | R13: Put assigned | S13: =Q13/(K13*100*L13) -> 0.0281825
A14: 45712 | B14: JD | C14: 0.1749 | D14: 0.4 | E14: 0.56 | F14: Y | G14: 0.03 | H14: Put | I14: Sell | J14: 45737 | K14: 36 | L14: 1 | M14: 112 | N14: 1.05 | O14: =M14-N14 -> 110.95 | Q14: =sum(O14:P14) -> 110.95 | R14: Expired OOM | S14: =Q14/(K14*100*L14) -> 0.030819444 | T14: 0.76 | U14: 0.7 | V14: 3477 | W14: <1% | X14: 0.03
A15: 45712 | B15: WING | C15: 0.1749 | D15: 0.38 | E15: 0.54 | F15: N | G15: 0.2 | H15: Put | I15: Sell | J15: 45737 | K15: 220 | L15: 1 | M15: 281 | N15: 0.02 | O15: =M15-N15 -> 280.98 | Q15: =sum(O15:P15) -> 280.98 | R15: Put assigned | S15: =Q15/(K15*100*L15) -> 0.012771818 | T15: 0.84 | U15: 0.81 | V15: 21664 | W15: <1% | X15: 0.01
A16: 45712 | B16: ASAN | C16: 0.1749 | D16: 1.04 | E16: 0.79 | F16: N | G16: 0.1 | H16: Put | I16: Sell | J16: 45737 | K16: 17.5 | L16: 4 | M16: 384 | N16: 1.36 | O16: =M16-N16 -> 382.64 | Q16: =sum(O16:P16) -> 382.64 | R16: Put assigned | S16: =Q16/(K16*100*L16) -> 0.054662857 | T16: 0.74 | U16: 0.66 | V16: 6541 | W16: <1% | X16: 0.06
A18: 45733 | B18: AAPL | C18: 0.2 | D18: 0.28 | E18: 0.295 | F18: N | G18: 0.05 | H18: Call | I18: Sell | J18: 45764 | K18: 225 | L18: 1 | M18: 306 | N18: 0.81 | O18: =M18-N18 -> 305.19 | Q18: =sum(O18:P18) -> 305.19 | R18: Expired OOM | S18: =Q18/(K18*100*L18) -> 0.013564 | T18: 0.75 | U18: 0.7 | W18: <1%
A19: 45743 | B19: WING | C19: 0.19 | D19: 0.43 | E19: 0.63 | F19: N | H19: Call | I19: Sell | J19: 45764 | K19: 240 | L19: 1 | M19: 576 | N19: 1.08 | O19: =M19-N19 -> 574.92 | Q19: =sum(O19:P19) -> 574.92 | R19: Expired OOM | S19: =Q19/(K19*100*L19) -> 0.023955 | T19: 0.73 | U19: 0.66 | W19: <1%
A20: 45743 | B20: GOOGL | C20: 0.19 | D20: 0.28 | E20: 0.3 | F20: N | H20: Call | I20: Sell | J20: 45764 | K20: 172.5 | L20: 1 | M20: 119 | N20: 1.05 | O20: =M20-N20 -> 117.95 | Q20: =sum(O20:P20) -> 117.95 | R20: Expired OOM | S20: =Q20/(K20*100*L20) -> 0.0068376812 | T20: 0.83 | U20: 0.8 | W20: <1%
A21: 45747 | B21: NEM | C21: 0.22 | D21: 0.33 | E21: 0.35 | F21: N | G21: 0.04 | H21: Put | I21: Sell | J21: 45764 | K21: 48 | L21: 1 | M21: 130 | N21: 1.05 | O21: =M21-N21 -> 128.95 | Q21: =sum(O21:P21) -> 128.95 | R21: Expired OOM | S21: =Q21/(K21*100*L21) -> 0.026864583 | T21: 0.68 | U21: 0.56 | W21: <1%
A22: 45747 | B22: NVDA | C22: 0.22 | D22: 0.49 | E22: 0.55 | F22: N | G22: 0.02 | H22: Call | I22: Sell | J22: 45764 | K22: 117 | L22: 1 | M22: 109 | N22: 1.05 | O22: =M22-N22 -> 107.95 | Q22: =sum(O22:P22) -> 107.95 | R22: Expired OOM | S22: =Q22/(K22*100*L22) -> 0.0092264957 | T22: 0.8 | U22: 0.76 | W22: <1%
A23: 45748 | B23: RCAT | C23: 0.23 | D23: 1.03 | E23: 1.07 | F23: Y | G23: 0.1 | H23: Put | I23: Sell | J23: 45764 | K23: 7.5 | L23: 4 | M23: =196+224 -> 420 | N23: =1.35+6 -> 7.35 | O23: =M23-N23 -> 412.65 | Q23: =sum(O23:P23) -> 412.65 | R23: Moved from 6 to 7.5 to capture growth, then, assigned! | S23: =Q23/(K23*100*L23) -> 0.13755 | T23: 0.65 | U23: 0.49 | W23: <1% | X23: 0.09
A25: 45747 | B25: CROX | C25: 0.22 | D25: 0.45 | E25: 0.47 | F25: N | G25: 0.2 | H25: Call | I25: Sell | J25: 45793 | K25: 120 | L25: 1 | M25: 219 | N25: =0.27+4.63 -> 4.9 | O25: =M25-N25 -> 214.1 | Q25: =sum(O25:P25) -> 214.1 | R25: Expired OOM. Moved to May from April and price from 110 to 120 | S25: =Q25/(K25*100*L25) -> 0.017841667 | T25: 0.73 | U25: 0.66 | W25: <1%
A26: 45754 | B26: CROX | C26: 0.51 | D26: 0.8 | E26: 0.66 | F26: Y | G26: 0.8 | H26: Put | I26: Sell | J26: 45793 | K26: 70 | L26: 1 | M26: 228 | N26: 1.07 | O26: =M26-N26 -> 226.93 | Q26: =sum(O26:P26) -> 226.93 | R26: Expired OOM. | S26: =Q26/(K26*100*L26) -> 0.032418571 | T26: 0.91 | U26: 0.89 | X26: 0.03
A27: 45754 | B27: GOOGL | C27: 0.51 | D27: 0.5 | E27: 0.35 | F27: Y | G27: 0.09 | H27: Put | I27: Sell | J27: 45793 | K27: 130 | L27: 1 | M27: =258+81.58 -> 339.58 | N27: 1.06 | O27: =M27-N27 -> 338.52 | Q27: =sum(O27:P27) -> 338.52 | R27: Expired OOM. Moved 120->130. | S27: =Q27/(K27*100*L27) -> 0.02604 | T27: 0.91 | U27: 0.89 | X27: 0.02
A28: 45754 | B28: NVDA | C28: 0.51 | D28: 0.67 | E28: 0.62 | F28: N | G28: 0.04 | H28: Put | I28: Sell | J28: 45793 | K28: 85 | L28: 1 | M28: =170+111 -> 281 | N28: 0.71 | O28: =M28-N28 -> 280.29 | Q28: =sum(O28:P28) -> 280.29 | R28: Expired OOM. Moved 70->85. | S28: =Q28/(K28*100*L28) -> 0.032975294 | T28: 0.95 | U28: 0.93 | X28: 0.02
A29: 45737 | B29: IIPR | F29: Y | H29: Put/Call | I29: Buy | J29: 45793 | K29: 55/70 | L29: 1 | N29: 0.62 | O29: =M29-N29 -> -0.62 | P29: -9 | Q29: =sum(O29:P29) -> -9.62 | R29: Expired OOM. Risk reversal.
A30: 45737 | B30: ABR | F30: Y | H30: Put/Call | I30: Buy | J30: 45793 | K30: 10/14 | L30: 6 | N30: 14.38 | O30: =M30-N30 -> -14.38 | P30: -48 | Q30: =sum(O30:P30) -> -62.38 | R30: Expired OOM. Risk reversal.
A32: 45735 | B32: ASAN | C32: 0.2 | D32: 0.56 | E32: 1.09 | F32: N | G32: 0.1 | H32: Call | I32: Sell | J32: 45828 | K32: 20 | L32: 4 | M32: =244+104 -> 348 | N32: 1.36 | O32: =M32-N32 -> 346.64 | P32: -136 | Q32: =sum(O32:P32) -> 210.64 | R32: Moved from April 15 to May to June with higher strike | S32: =Q32/(K32*100*L32) -> 0.02633 | T32: 0.67 | U32: 0.57 | W32: <1%
A33: 45754 | B33: AAPL | C33: 0.51 | D33: 0.7 | E33: 0.43 | F33: N | G33: 0.04 | H33: Call | I33: Sell | J33: 45828 | K33: 215 | L33: 1 | M33: =151+104.56 -> 255.56 | N33: 0.64 | O33: =M33-N33 -> 254.92 | P33: -39 | Q33: =sum(O33:P33) -> 215.92 | R33: Moved from April 200 to May 210 to June 215 | S33: =Q33/(K33*100*L33) -> 0.010042791 | T33: 0.82 | U33: 0.8
A34: 45754 | B34: RCAT | C34: 0.51 | D34: 1.16 | E34: 1.19 | F34: N | G34: 0.1 | H34: Put | I34: Sell | J34: 45828 | K34: 6 | L34: 4 | M34: =304+104.23 -> 408.23 | N34: 1.35 | O34: =M34-N34 -> 406.88 | Q34: =sum(O34:P34) -> 406.88 | R34: Moved from May 6 to June 6 | S34: =Q34/(K34*100*L34) -> 0.16953333 | T34: 0.71 | U34: 0.58 | X34: 0.15
A35: 45769 | B35: WING | C35: 0.31 | D35: 0.68 | E35: 0.58 | F35: Y | H35: Call | I35: Sell | J35: 45828 | K35: 240 | L35: 1 | M35: =411+630.3 -> 1041.3 | N35: 0.27 | O35: =M35-N35 -> 1041.03 | Q35: =sum(O35:P35) -> 1041.03 | R35: Moved from May to June | S35: =Q35/(K35*100*L35) -> 0.04337625
A36: 45796 | B36: CROX | C36: 0.18 | D36: 0.36 | E36: 0.75 | F36: N | G36: 0.1 | H36: Call | I36: Sell | J36: 45828 | K36: 125 | L36: 1 | M36: 149 | N36: 0.26 | O36: =M36-N36 -> 148.74 | Q36: =sum(O36:P36) -> 148.74 | R36: Moved to Sept | S36: =Q36/(K36*100*L36) -> 0.0118992 | T36: 0.8 | U36: 0.77
A37: 45796 | B37: GOOGL | C37: 0.18 | D37: 0.29 | E37: 0.47 | F37: N | G37: 0.03 | H37: Call | I37: Sell | J37: 45828 | K37: 180 | L37: 1 | M37: 150 | N37: 0.78 | O37: =M37-N37 -> 149.22 | Q37: =sum(O37:P37) -> 149.22 | R37: Expired OOM | S37: =Q37/(K37*100*L37) -> 0.00829 | T37: 0.84 | U37: 0.82
A38: 45796 | B38: NVDA | C38: 0.18 | D38: 0.49 | E38: 0.77 | F38: Y | G38: 0.02 | H38: Put | I38: Sell | J38: 45828 | K38: 110 | L38: 1 | M38: 107 | N38: 0.78 | O38: =M38-N38 -> 106.22 | Q38: =sum(O38:P38) -> 106.22 | R38: Expired OOM | S38: =Q38/(K38*100*L38) -> 0.0096563636 | T38: 0.93 | U38: 0.93 | V38: 10852 | X38: 0.01
A39: 45796 | B39: RCAT | C39: 0.18 | D39: 0.96 | E39: 1.33 | F39: N | G39: 0.1 | H39: Call | I39: Sell | J39: 45828 | K39: 8 | L39: 4 | M39: 136 | N39: 1.36 | O39: =M39-N39 -> 134.64 | Q39: =sum(O39:P39) -> 134.64 | R39: Expired OOM | S39: =Q39/(K39*100*L39) -> 0.042075 | T39: 0.75 | U39: 0.7
A40: 45796 | B40: SHOP | C40: 0.18 | D40: 0.46 | E40: 0.96 | F40: N | G40: 0.05 | H40: Put | I40: Sell | J40: 45828 | K40: 95 | L40: 1 | M40: 134 | N40: 0.78 | O40: =M40-N40 -> 133.22 | Q40: =sum(O40:P40) -> 133.22 | R40: Expired OOM | S40: =Q40/(K40*100*L40) -> 0.014023158 | T40: 0.88 | U40: 0.85 | V40: 9325 | X40: 0.01
A41: 45796 | B41: MU | C41: 0.18 | D41: 0.52 | E41: 0.83 | F41: N | G41: 0.04 | H41: Put | I41: Sell | J41: 45828 | K41: 87 | L41: 1 | M41: 156 | N41: 0.78 | O41: =M41-N41 -> 155.22 | Q41: =sum(O41:P41) -> 155.22 | R41: Expired OOM | S41: =Q41/(K41*100*L41) -> 0.017841379 | T41: 0.85 | U41: 0.82 | V41: 8527 | X41: 0.02
A42: 45796 | B42: VRT | C42: 0.18 | D42: 0.55 | E42: 1.11 | F42: N | G42: 0.07 | H42: Put | I42: Sell | J42: 45828 | K42: 90 | L42: 1 | M42: 138 | N42: 0.81 | O42: =M42-N42 -> 137.19 | Q42: =sum(O42:P42) -> 137.19 | R42: Expired OOM | S42: =Q42/(K42*100*L42) -> 0.015243333 | T42: 0.87 | U42: 0.85 | V42: 8838 | X42: 0.01
A43: 45799 | B43: ANF | F43: Y | H43: Call/Put | I43: Sell | J43: 45828 | K43: 89/69 | L43: 1 | M43: =322-289 -> 33 | N43: 2.12 | O43: =M43-N43 -> 30.88 | Q43: =sum(O43:P43) -> 30.88 | R43: Long call and short put as a candidate for breakout.
A45: 45811 | B45: ABR | C45: 0.178 | D45: 0.448 | E45: 0.436 | F45: N | H45: Call | I45: Sell | J45: 45856 | K45: 11 | L45: 6 | M45: 120 | N45: 4.26 | O45: =M45-N45 -> 115.74 | Q45: =sum(O45:P45) -> 115.74 | R45: Moved to Aug | S45: =Q45/(K45*100*L45) -> 0.017536364 | T45: 0.8 | U45: 0.76
A46: 45834 | B46: AAPL | C46: 0.1635 | D46: 0.239 | E46: 0.253 | F46: N | G46: 0.02 | H46: Call | I46: Sell | J46: 45856 | K46: 205 | L46: 1 | M46: 269 | N46: 0.78 | O46: =M46-N46 -> 268.22 | Q46: =sum(O46:P46) -> 268.22 | R46: Moved to Aug | S46: =Q46/(K46*100*L46) -> 0.013083902 | T46: 0.72 | U46: 0.64
A47: 45834 | B47: NEM | C47: 0.1635 | D47: 0.3 | E47: 0.294 | F47: N | G47: 0.05 | H47: Put | I47: Sell | J47: 45856 | K47: 59 | L47: 1 | M47: 165 | N47: 0.78 | O47: =M47-N47 -> 164.22 | Q47: =sum(O47:P47) -> 164.22 | R47: Assigned | S47: =Q47/(K47*100*L47) -> 0.027833898 | T47: 0.66 | U47: 0.5 | X47: 0.03
A48: 45834 | B48: GOOGL | C48: 0.1635 | D48: 0.25 | E48: 0.31 | F48: N | G48: 0.02 | H48: Call | I48: Sell | J48: 45856 | K48: 180 | L48: 1 | M48: 190 | N48: 0.78 | O48: =M48-N48 -> 189.22 | Q48: =sum(O48:P48) -> 189.22 | R48: Moved to Aug | S48: =Q48/(K48*100*L48) -> 0.010512222 | T48: 0.77 | U48: 0.72
A49: 45834 | B49: SHOP | C49: 0.1635 | D49: 0.41 | E49: 0.4 | F49: N | G49: 0.06 | H49: Put | I49: Sell | J49: 45856 | K49: 107 | L49: 1 | M49: 211 | N49: 0.78 | O49: =M49-N49 -> 210.22 | Q49: =sum(O49:P49) -> 210.22 | R49: Expired OOM | S49: =Q49/(K49*100*L49) -> 0.019646729 | T49: 0.78 | U49: 0.72 | X49: 0.02
A50: 45834 | B50: RMBS | C50: 0.1635 | D50: 0.38 | E50: 0.37 | F50: N | G50: 0.15 | H50: Put | I50: Sell | J50: 45856 | K50: 60 | L50: 1 | M50: 131 | N50: 0.01 | O50: =M50-N50 -> 130.99 | Q50: =sum(O50:P50) -> 130.99 | R50: Expired OOM | S50: =Q50/(K50*100*L50) -> 0.021831667 | T50: 0.74 | U50: 0.66 | X50: 0.02
A51: 45834 | B51: CROX | C51: 0.1635 | D51: 0.38 | E51: 0.33 | F51: N | G51: 0.02 | H51: Call | I51: Sell | J51: 45856 | K51: 105 | L51: 1 | M51: 184 | N51: 0.01 | O51: =M51-N51 -> 183.99 | Q51: =sum(O51:P51) -> 183.99 | R51: Moved to Aug | S51: =Q51/(K51*100*L51) -> 0.017522857 | T51: 0.75 | U51: 0.69 | X51: 0.02
A52: 45835 | B52: ACMR | C52: 0.1635 | D52: 0.59 | E52: 0.46 | F52: N | G52: 0.95 | H52: Put | I52: Sell | J52: 45856 | K52: 25 | L52: 3 | M52: 243 | N52: 1.02 | O52: =M52-N52 -> 241.98 | Q52: =sum(O52:P52) -> 241.98 | R52: Expired OOM | S52: =Q52/(K52*100*L52) -> 0.032264 | T52: 0.63 | U52: 0.6 | X52: 0.01
A53: 45835 | B53: NVDA | C53: 0.1635 | D53: 0.33 | E53: 0.35 | F53: N | G53: 0.02 | H53: Call | I53: Sell | J53: 45856 | K53: 167.5 | L53: 1 | M53: 171 | N53: 0.78 | O53: =M53-N53 -> 170.22 | Q53: =sum(O53:P53) -> 170.22 | R53: Moved to Aug | S53: =Q53/(K53*100*L53) -> 0.010162388 | T53: 0.8 | U53: 0.76
A54: 45840 | B54: RCAT | C54: 0.165 | D54: 0.98 | E54: 1.25 | F54: N | G54: 0.1 | H54: Call | I54: Sell | J54: 45856 | K54: 8 | L54: 4 | M54: 156 | N54: 1.37 | O54: =M54-N54 -> 154.63 | Q54: =sum(O54:P54) -> 154.63 | R54: Assigned | S54: =Q54/(K54*100*L54) -> 0.048321875 | T54: 0.7 | U54: 0.62
A56: 45841 | B56: CROX | C56: 0.165 | D56: 0.52 | E56: 0.39 | F56: Y | G56: 0.4 | H56: Call | I56: Sell | J56: 45884 | K56: 110 | L56: 1 | M56: 174 | N56: 2.12 | O56: =M56-N56 -> 171.88 | Q56: =sum(O56:P56) -> 171.88 | R56: Moved from Jul 105 | S56: =Q56/(K56*100*L56) -> 0.015625455 | T56: 0.66 | U56: 0.54
A57: 45841 | B57: AAPL | C57: 0.165 | D57: 0.22 | E57: 0.26 | F57: Y | G57: 0.1 | H57: Call | I57: Sell | J57: 45884 | K57: 210 | L57: 1 | M57: 29 | N57: 1.41 | O57: =M57-N57 -> 27.59 | Q57: =sum(O57:P57) -> 27.59 | R57: Moved from Jul 205 | S57: =Q57/(K57*100*L57) -> 0.0013138095 | T57: 0.61 | U57: 0.4
A58: 45841 | B58: GOOGL | C58: 0.165 | D58: 0.33 | E58: 0.3 | F58: Y | G58: 0.1 | H58: Call | I58: Sell | J58: 45884 | K58: 190 | L58: 1 | M58: 101 | N58: 1.41 | O58: =M58-N58 -> 99.59 | Q58: =sum(O58:P58) -> 99.59 | R58: Moved from Jul 180 | S58: =Q58/(K58*100*L58) -> 0.0052415789 | T58: 0.74 | U58: 0.67
A59: 45848 | B59: ASAN | C59: 0.16 | D59: 0.41 | E59: 0.56 | F59: N | G59: 0.1 | H59: Call | I59: Sell | J59: 45884 | K59: 15 | L59: 4 | M59: 244 | N59: 1.37 | O59: =M59-N59 -> 242.63 | Q59: =sum(O59:P59) -> 242.63 | S59: =Q59/(K59*100*L59) -> 0.040438333 | T59: 0.67 | U59: 0.56
A60: 45848 | B60: ABR | C60: 0.16 | D60: 0.46 | E60: 0.32 | F60: Y | G60: 0.13 | H60: Call | I60: Sell | J60: 45884 | K60: 11 | L60: 6 | M60: 198 | N60: 3.89 | O60: =M60-N60 -> 194.11 | Q60: =sum(O60:P60) -> 194.11 | R60: Assigned. Moved from Jul same strike. | S60: =Q60/(K60*100*L60) -> 0.029410606 | T60: 0.65 | U60: 0.5
A61: 45849 | B61: RCAT | C61: 0.16 | D61: 1.11 | E61: 1.13 | F61: N | G61: 0.15 | H61: Call | I61: Sell | J61: 45884 | K61: 8 | L61: 4 | M61: -8 | N61: 0.36 | O61: =M61-N61 -> -8.36 | Q61: =sum(O61:P61) -> -8.36 | R61: Expired | S61: =Q61/(K61*100*L61) -> -0.0026125 | T61: 0.59 | U61: 0.4
A62: 45853 | B62: NVDA | C62: 0.17 | H62: Call | I62: Sell | J62: 45884 | K62: 175 | L62: 1 | M62: 81 | N62: 1.41 | O62: =M62-N62 -> 79.59 | Q62: =sum(O62:P62) -> 79.59 | R62: Moved from Jul to 175 strike | S62: =Q62/(K62*100*L62) -> 0.004548
A63: 45859 | B63: MU | C63: 0.16 | D63: 0.4 | E63: 0.39 | F63: N | G63: 0.04 | H63: Put | I63: Sell | J63: 45884 | K63: 105 | L63: 1 | M63: 150 | N63: 0.71 | O63: =M63-N63 -> 149.29 | Q63: =sum(O63:P63) -> 149.29 | R63: Expired | S63: =Q63/(K63*100*L63) -> 0.014218095 | T63: 0.81 | U63: 0.76 | X63: 0.03
A64: 45859 | B64: ON | C64: 0.16 | D64: 0.62 | E64: 0.58 | F64: Y | G64: 0.04 | H64: Put | I64: Sell | J64: 45884 | K64: 55 | L64: 1 | M64: 139 | N64: 0.81 | O64: =M64-N64 -> 138.19 | Q64: =sum(O64:P64) -> 138.19 | R64: Moved to 50 and Sept. | S64: =Q64/(K64*100*L64) -> 0.025125455 | T64: 0.81 | U64: 0.76 | X64: 0.03
A65: 45859 | B65: FTNT | C65: 0.16 | D65: 0.54 | E65: 0.3 | F65: Y | G65: 0.11 | H65: Put | I65: Sell | J65: 45884 | K65: 97.5 | L65: 1 | M65: 225 | N65: 0.71 | O65: =M65-N65 -> 224.29 | Q65: =sum(O65:P65) -> 224.29 | R65: Assigned | S65: =Q65/(K65*100*L65) -> 0.023004103 | T65: 0.81 | U65: 0.76 | X65: 0.02
A66: 45859 | B66: ANET | C66: 0.16 | D66: 0.56 | E66: 0.35 | F66: Y | G66: 0.1 | H66: Put | I66: Sell | J66: 45884 | K66: 100 | L66: 1 | M66: 196 | N66: 0.01 | O66: =M66-N66 -> 195.99 | Q66: =sum(O66:P66) -> 195.99 | R66: Expired | S66: =Q66/(K66*100*L66) -> 0.019599 | T66: 0.83 | U66: 0.79 | X66: 0.02
A67: 45859 | B67: RCAT | C67: 0.16 | D67: 1.25 | E67: 1.23 | F67: N | G67: 0.05 | H67: Put | I67: Sell | J67: 45884 | K67: 8 | L67: 4 | M67: 164 | N67: 1.37 | O67: =M67-N67 -> 162.63 | Q67: =sum(O67:P67) -> 162.63 | R67: Expired | S67: =Q67/(K67*100*L67) -> 0.050821875 | T67: 0.79 | U67: 0.74 | X67: 0.05
A68: 45859 | B68: APH | C68: 0.16 | D68: 0.37 | E68: 0.21 | F68: Y | G68: 0.1 | H68: Put | I68: Sell | J68: 45884 | K68: 95 | L68: 1 | M68: 114 | N68: 0.26 | O68: =M68-N68 -> 113.74 | Q68: =sum(O68:P68) -> 113.74 | R68: Expired | S68: =Q68/(K68*100*L68) -> 0.011972632 | T68: 0.85 | U68: 0.82 | X68: 0.01
A70: 45868 | B70: GOOGL | C70: 0.16 | D70: 0.27 | E70: 0.27 | F70: N | G70: 0.1 | H70: Call | I70: Sell | J70: 45919 | K70: 195 | L70: 1 | M70: 31 | N70: 1.41 | O70: =M70-N70 -> 29.59 | Q70: =sum(O70:P70) -> 29.59 | R70: Moved from Aug 190 to 195 | S70: =Q70/(K70*100*L70) -> 0.0015174359 | T70: 0.63 | U70: 0.44
A71: 45868 | B71: NVDA | C71: 0.16 | D71: 0.39 | E71: 0.26 | F71: Y | G71: 0.1 | H71: Call | I71: Sell | J71: 45919 | K71: 185 | L71: 1 | M71: 64 | N71: 1.41 | O71: =M71-N71 -> 62.59 | Q71: =sum(O71:P71) -> 62.59 | R71: Moved from Aug to 175 strike | S71: =Q71/(K71*100*L71) -> 0.0033832432 | T71: 0.68 | U71: 0.56
A72: 45868 | B72: ASAN | C72: 0.16 | D72: 0.68 | E72: 0.37 | F72: Y | G72: 0.1 | H72: Call | I72: Sell | J72: 45919 | K72: 17.5 | L72: 4 | M72: 2 | N72: 6.66 | O72: =M72-N72 -> -4.66 | Q72: =sum(O72:P72) -> -4.66 | R72: Moved from Aug 15 strike | S72: =Q72/(K72*100*L72) -> -0.00066571429 | T72: 0.75 | U72: 0.68
A73: 45814 | B73: WING | C73: 0.17 | D73: 0.34 | E73: 0.44 | F73: Y | H73: Call | I73: Sell | J73: 45919 | K73: 240 | L73: 1 | M73: 541 | N73: 2.12 | O73: =M73-N73 -> 538.88 | Q73: =sum(O73:P73) -> 538.88 | R73: Moved from June w/o change of strike | S73: =Q73/(K73*100*L73) -> 0.022453333
A74: 45859 | B74: ON | C74: 0.1768 | D74: 0.46 | E74: 0.53 | F74: N | G74: 0.1 | H74: Put | I74: Sell | J74: 45919 | K74: 50 | L74: 1 | M74: 0 | N74: 0.81 | O74: =M74-N74 -> -0.81 | P74: -322.33 | Q74: =sum(O74:P74) -> -323.14 | R74: Expired. Move from Aug 55. | S74: =Q74/(K74*100*L74) -> -0.064628 | T74: 0.61 | U74: 0.4 | X74: 0.03
A75: 45841 | B75: AAPL | C75: 0.1577 | D75: 0.25 | E75: 0.25 | F75: N | G75: 0.04 | H75: Call | I75: Sell | J75: 45919 | K75: 210 | L75: 1 | M75: 254 | N75: 1.41 | O75: =M75-N75 -> 252.59 | Q75: =sum(O75:P75) -> 252.59 | R75: Moved from Aug to same strike | S75: =Q75/(K75*100*L75) -> 0.012028095 | T75: 0.57 | U75: 0.14
A76: 45706 | B76: MU | C76: 0.1533 | D76: 0.42 | E76: 0.438 | F76: N | G76: 0.06 | H76: Put | I76: Sell | J76: 45919 | K76: 112 | L76: 1 | M76: 213 | N76: 0.8 | O76: =M76-N76 -> 212.2 | Q76: =sum(O76:P76) -> 212.2 | R76: Expired OOM | S76: =Q76/(K76*100*L76) -> 0.018946429 | T76: 0.82 | U76: 0.78 | X76: 0.02
A77: 45706 | B77: NEM | C77: 0.1533 | D77: 0.305 | E77: 0.35 | F77: N | G77: 0.03 | H77: Call | I77: Sell | J77: 45919 | K77: 73 | L77: 1 | M77: 110 | N77: 1.05 | O77: =M77-N77 -> 108.95 | Q77: =sum(O77:P77) -> 108.95 | R77: Assigned | S77: =Q77/(K77*100*L77) -> 0.014924658 | T77: 0.78 | U77: 0.73
A78: 45706 | B78: CROX | C78: 0.1533 | D78: 38.2 | E78: 0.82 | F78: N | G78: 0.1 | H78: Call | I78: Sell | J78: 45919 | K78: 77.5 | L78: 1 | M78: 144 | N78: 0 | O78: =M78-N78 -> 144 | Q78: =sum(O78:P78) -> 144 | R78: Expired OOM | S78: =Q78/(K78*100*L78) -> 0.018580645 | T78: 0.79 | U78: 0.74 | X78: 0.02
A79: 45707 | B79: RCAT | C79: 0.158 | D79: 0.97 | E79: 1.13 | F79: N | G79: 0.05 | H79: Call | I79: Sell | J79: 45919 | K79: 7.5 | L79: 4 | M79: 156 | N79: 1.38 | O79: =M79-N79 -> 154.62 | Q79: =sum(O79:P79) -> 154.62 | R79: Expired OOM | S79: =Q79/(K79*100*L79) -> 0.05154 | T79: 0.77 | U79: 0.71 | X79: 0.06
A80: 45707 | B80: APH | C80: 0.158 | D80: 0.304 | E80: 0.389 | F80: N | G80: 0.15 | H80: Put | I80: Sell | J80: 45919 | K80: 105 | L80: 1 | M80: 191 | N80: 0.25 | O80: =M80-N80 -> 190.75 | Q80: =sum(O80:P80) -> 190.75 | R80: Expired OOM | S80: =Q80/(K80*100*L80) -> 0.018166667 | T80: 0.77 | U80: 0.7 | X80: 0.02
A81: 45707 | B81: CCJ | C81: 0.158 | D81: 0.427 | E81: 0.396 | F81: N | G81: 0.06 | H81: Put | I81: Sell | J81: 45919 | K81: 68 | L81: 1 | M81: 128 | N81: 1.05 | O81: =M81-N81 -> 126.95 | Q81: =sum(O81:P81) -> 126.95 | R81: Expired OOM | S81: =Q81/(K81*100*L81) -> 0.018669118 | T81: 0.81 | U81: 0.76
A82: 45707 | B82: PSTG | C82: 0.158 | D82: 0.62 | E82: 0.32 | F82: Y | G82: 0.05 | H82: Put | I82: Sell | J82: 45919 | K82: 50 | L82: 1 | M82: 131 | N82: 0 | O82: =M82-N82 -> 131 | Q82: =sum(O82:P82) -> 131 | R82: Expired OOM | S82: =Q82/(K82*100*L82) -> 0.0262 | T82: 0.82 | U82: 0.78 | X82: 0.03
A84: 45922 | B84: NVDA | C84: 0.1586 | D84: 0.34 | E84: 0.32 | F84: N | G84: 0.02 | H84: Call | I84: Sell | J84: 45947 | K84: 190 | L84: 1 | M84: 173 | N84: 1.05 | O84: =M84-N84 -> 171.95 | Q84: =sum(O84:P84) -> 171.95 | R84: Expired OOM | S84: =Q84/(K84*100*L84) -> 0.00905 | T84: 0.83 | U84: 0.8
A85: 45922 | B85: CROX | C85: 0.1586 | D85: 0.41 | E85: 0.38 | F85: N | G85: 0.2 | H85: Call | I85: Sell | J85: 45947 | K85: 85 | L85: 1 | M85: 99 | N85: 0 | O85: =M85-N85 -> 99 | Q85: =sum(O85:P85) -> 99 | R85: Expired OOM | S85: =Q85/(K85*100*L85) -> 0.011647059 | T85: 0.82 | U85: 0.79
A86: 45922 | B86: FTNT | C86: 0.1586 | D86: 0.32 | E86: 0.32 | F86: N | G86: 0.08 | H86: Call | I86: Sell | J86: 45947 | K86: 90 | L86: 1 | M86: 98 | N86: 0.8 | O86: =M86-N86 -> 97.2 | Q86: =sum(O86:P86) -> 97.2 | R86: Expired OOM | S86: =Q86/(K86*100*L86) -> 0.0108 | T86: 0.81 | U86: 0.77
A87: 45922 | B87: ASAN | C87: 0.1586 | D87: 0.46 | E87: 0.51 | F87: N | G87: 0.05 | H87: Call | I87: Sell | J87: 45947 | K87: 15.5 | L87: 4 | M87: 124 | N87: 1.39 | O87: =M87-N87 -> 122.61 | Q87: =sum(O87:P87) -> 122.61 | R87: Expired OOM | S87: =Q87/(K87*100*L87) -> 0.019775806 | T87: 0.76 | U87: 0.71
A88: 45922 | B88: TER | C88: 0.1586 | D88: 0.44 | E88: 0.38 | F88: N | G88: 0.15 | H88: Put | I88: Sell | J88: 45947 | K88: 120 | L88: 1 | M88: 201 | N88: 0 | O88: =M88-N88 -> 201 | Q88: =sum(O88:P88) -> 201 | R88: Expired OOM | S88: =Q88/(K88*100*L88) -> 0.01675 | T88: 0.82 | U88: 0.78 | X88: 0.02
A89: 45922 | B89: RCAT | C89: 0.1586 | D89: 1.2 | E89: 1 | F89: N | G89: 0.05 | H89: Put | I89: Sell | J89: 45947 | K89: 9.5 | L89: 4 | M89: 224 | N89: 0.39 | O89: =M89-N89 -> 223.61 | Q89: =sum(O89:P89) -> 223.61 | R89: Expired OOM | S89: =Q89/(K89*100*L89) -> 0.058844737 | T89: 0.76 | U89: 0.7
A90: 45922 | B90: HCC | C90: 0.1586 | D90: 0.487 | E90: 0.35 | F90: N | G90: 0.2 | H90: Put | I90: Sell | J90: 45947 | K90: 55 | L90: 2 | M90: 168 | N90: 0.69 | O90: =M90-N90 -> 167.31 | Q90: =sum(O90:P90) -> 167.31 | R90: Expired OOM | S90: =Q90/(K90*100*L90) -> 0.01521 | T90: 0.83 | U90: 0.8 | X90: 0.02
A91: 45922 | B91: CELH | C91: 0.1586 | D91: 0.5 | E91: 0.43 | F91: N | G91: 0.04 | H91: Put | I91: Sell | J91: 45947 | K91: 47 | L91: 2 | M91: 200 | N91: 0.91 | O91: =M91-N91 -> 199.09 | Q91: =sum(O91:P91) -> 199.09 | R91: Expired OOM | S91: =Q91/(K91*100*L91) -> 0.021179787 | T91: 0.8 | U91: 0.75 | X91: 0.02
A92: 45923 | B92: PAAS | C92: 0.163 | D92: 0.42 | E92: 0.36 | F92: N | G92: 0.1 | H92: Put | I92: Sell | J92: 45947 | K92: 35.5 | L92: 2 | M92: 120 | N92: 0.19 | O92: =M92-N92 -> 119.81 | Q92: =sum(O92:P92) -> 119.81 | R92: Expired OOM | S92: =Q92/(K92*100*L92) -> 0.016874648 | T92: 0.79
A93: 45923 | B93: SSRM | C93: 0.163 | D93: 0.59 | E93: 0.42 | F93: N | G93: 0.05 | H93: Put | I93: Sell | J93: 45947 | K93: 21 | L93: 5 | M93: 200 | N93: 1.35 | O93: =M93-N93 -> 198.65 | Q93: =sum(O93:P93) -> 198.65 | R93: Expired OOM | S93: =Q93/(K93*100*L93) -> 0.018919048 | T93: 0.8 | X93: 0.02
A94: 45923 | B94: NVT | C94: 0.163 | D94: 0.38 | E94: 0.26 | F94: N | G94: 0.45 | H94: Put | I94: Sell | J94: 45947 | K94: 92.5 | L94: 1 | M94: 145 | N94: 0 | O94: =M94-N94 -> 145 | Q94: =sum(O94:P94) -> 145 | R94: Expired OOM | S94: =Q94/(K94*100*L94) -> 0.015675676 | T94: 0.78
A96: 45953 | B96: PAAS | C96: 0.17 | D96: 0.57 | E96: 0.54 | F96: N | G96: 0.15 | H96: Put | I96: Sell | J96: 45982 | K96: 32 | L96: 5 | M96: 350 | N96: 3.49 | O96: =M96-N96 -> 346.51 | Q96: =sum(O96:P96) -> 346.51 | R96: Expired OOM | S96: =Q96/(K96*100*L96) -> 0.021656875 | T96: 0.81 | U96: 0.78 | X96: 0.02
A97: 45953 | B97: NEM | C97: 0.17 | D97: 0.518 | E97: 0.43 | F97: Y | G97: 0.11 | H97: Put | I97: Sell | J97: 45982 | K97: 81 | L97: 2 | M97: 360 | N97: 1.4 | O97: =M97-N97 -> 358.6 | Q97: =sum(O97:P97) -> 358.6 | R97: Expired OOM | S97: =Q97/(K97*100*L97) -> 0.022135802 | T97: 0.8 | U97: 0.75 | X97: 0.02
A98: 45953 | B98: TSEM | C98: 0.17 | D98: 0.628 | E98: 0.47 | F98: Y | G98: 0.35 | H98: Put | I98: Sell | J98: 45982 | K98: 65 | L98: 3 | M98: 522 | N98: 1.05 | O98: =M98-N98 -> 520.95 | Q98: =sum(O98:P98) -> 520.95 | R98: Expired OOM | S98: =Q98/(K98*100*L98) -> 0.026715385 | T98: 0.82 | U98: 0.78 | X98: 0.03
A99: 45953 | B99: IBKR | C99: 0.17 | D99: 0.39 | E99: 0.39 | F99: N | G99: 0.1 | H99: Put | I99: Sell | J99: 45982 | K99: 62 | L99: 3 | M99: 297 | N99: 1.05 | O99: =M99-N99 -> 295.95 | Q99: =sum(O99:P99) -> 295.95 | R99: Assigned | S99: =Q99/(K99*100*L99) -> 0.01591129 | T99: 0.81 | U99: 0.77 | X99: 0.02
A100: 45954 | B100: LOGI | C100: 0.16 | D100: 0.37 | E100: 0.23 | F100: Y | G100: 0.25 | H100: Put | I100: Sell | J100: 45982 | K100: 100 | L100: 2 | M100: 238 | N100: 0.2 | O100: =M100-N100 -> 237.8 | Q100: =sum(O100:P100) -> 237.8 | R100: Expired OOM | S100: =Q100/(K100*100*L100) -> 0.01189 | T100: 0.89 | U100: 0.86 | X100: 0.01
A101: 45957 | B101: AMKR | C101: 0.16 | D101: 0.81 | E101: 0.65 | F101: Y | G101: 0.1 | H101: Put | I101: Sell | J101: 45982 | K101: 28 | L101: 5 | M101: 345 | N101: 1.76 | O101: =M101-N101 -> 343.24 | Q101: =sum(O101:P101) -> 343.24 | R101: Expired OOM | S101: =Q101/(K101*100*L101) -> 0.024517143 | T101: 0.83 | U101: 0.8 | X101: 0.03
A102: 45965 | B102: AMKR | C102: 0.19 | D102: 0.57 | E102: 0.69 | F102: Y | G102: 0.2 | H102: Put | I102: Sell | J102: 45982 | K102: 32 | L102: 4 | M102: 184 | N102: 2.79 | O102: =M102-N102 -> 181.21 | Q102: =sum(O102:P102) -> 181.21 | R102: Expired OOM | S102: =Q102/(K102*100*L102) -> 0.014157031 | T102: 0.84 | U102: 0.81 | X102: 0.01
A103: 45958 | B103: RCAT | C103: 0.16 | D103: 1.24 | E103: 1.29 | F103: Y | G103: 0.15 | H103: Put | I103: Sell | J103: 45982 | K103: 9.5 | L103: 5 | M103: 305 | N103: 1.76 | O103: =M103-N103 -> 303.24 | Q103: =sum(O103:P103) -> 303.24 | R103: Assigned | S103: =Q103/(K103*100*L103) -> 0.06384 | T103: 0.76 | U103: 0.69 | X103: 0.07
A104: 45958 | B104: NLR | C104: 0.16 | D104: 0.5 | E104: 0.51 | F104: N | G104: 1.9 | H104: Put | I104: Sell | J104: 45982 | K104: 150 | L104: 1 | M104: 580 | N104: 0.4 | O104: =M104-N104 -> 579.6 | Q104: =sum(O104:P104) -> 579.6 | R104: Assigned | S104: =Q104/(K104*100*L104) -> 0.03864 | T104: 0.69 | U104: 0.57 | X104: 0.04
A105: 45959 | B105: SSRM | C105: 0.17 | D105: 0.73 | E105: 0.64 | F105: Y | G105: 0.15 | H105: Put | I105: Sell | J105: 45982 | K105: 20 | L105: 5 | M105: 320 | N105: 1.76 | O105: =M105-N105 -> 318.24 | Q105: =sum(O105:P105) -> 318.24 | R105: Expired OOM | S105: =Q105/(K105*100*L105) -> 0.031824 | T105: 0.77 | U105: 0.72 | X105: 0.03
A106: 45965 | B106: SSRM | C106: 0.17 | D106: 0.63 | E106: 0.78 | F106: Y | G106: 0.15 | H106: Put | I106: Sell | J106: 45982 | K106: 19 | L106: 5 | M106: 195 | N106: 1.76 | O106: =M106-N106 -> 193.24 | Q106: =sum(O106:P106) -> 193.24 | R106: Expired OOM | S106: =Q106/(K106*100*L106) -> 0.020341053 | T106: 0.71 | U106: 0.65 | X106: 0.02
A107: 45959 | B107: KGC | C107: 0.17 | D107: 0.59 | E107: 0.52 | F107: Y | G107: 0.05 | H107: Put | I107: Sell | J107: 45982 | K107: 21 | L107: 5 | M107: 235 | N107: 3.49 | O107: =M107-N107 -> 231.51 | Q107: =sum(O107:P107) -> 231.51 | R107: Expired OOM | S107: =Q107/(K107*100*L107) -> 0.022048571 | T107: 0.77 | U107: 0.73 | X107: 0.02
A108: 45965 | B108: GLW | C108: 0.19 | D108: 0.41 | E108: 0.39 | F108: N | G108: 0.09 | H108: Put | I108: Sell | J108: 45982 | K108: 80 | L108: 2 | M108: 220 | N108: 0.9 | O108: =M108-N108 -> 219.1 | Q108: =sum(O108:P108) -> 219.1 | R108: Assigned | S108: =Q108/(K108*100*L108) -> 0.01369375 | T108: 0.81 | U108: 0.77 | X108: 0.01
A109: 45953 | B109: NVDA | C109: 0.17 | D109: 0.46 | E109: 0.34 | F109: Y | G109: 0.03 | H109: Call | I109: Sell | J109: 45982 | K109: 205 | L109: 1 | M109: 242 | N109: 1.05 | O109: =M109-N109 -> 240.95 | Q109: =sum(O109:P109) -> 240.95 | R109: Expired OOM | S109: =Q109/(K109*100*L109) -> 0.011753659 | T109: 0.83 | U109: 0.81
...

Sheet Portfolio
B2: Category | C2: Position (Ticker) | D2: Allocated Value (USD) | E2: Currency | F2: Sector | G2: Geography | H2: Industry / Theme
B3: Core Thematic ETFs | C3: XLV | D3: 515643 | E3: USD | F3: Health Care | G3: USA | H3: US Healthcare (Pharma Biotech Equipment)
B4: Core Thematic ETFs | C4: NLR | D4: 128911 | E4: USD | F4: Energy / Utilities | G4: Global | H4: Nuclear Energy & Uranium
B5: Core Thematic ETFs | C5: GRID | D5: 128911 | E5: USD | F5: Industrials / Technology | G5: Global | H5: Grid & Electrification Infrastructure
B6: Core Thematic ETFs | C6: ITA | D6: 128911 | E6: USD | F6: Industrials | G6: USA | H6: US Aerospace & Defense
B7: Core Thematic ETFs | C7: EWL | D7: 128911 | E7: USD | F7: Multi-Sector | G7: Switzerland | H7: Swiss Equities (Healthcare Financials etc.)
B8: Core Thematic ETFs | C8: ESIT | D8: 85940 | E8: EUR | F8: Technology | G8: Europe | H8: European Technology (Non-Mainstream)
B9: Core Thematic ETFs | C9: DGIN | D9: 85940 | E9: USD | F9: Technology / Comms. | G9: India | H9: Digital India (Non-Mainstream EM)
B11: Portfolio Stabilizers | C11: IEO | D11: 85940 | E11: USD | F11: Energy | G11: USA | H11: Oil & Gas Exploration & Production
B13: Satellite Individual Stocks | C13: GOOGL | D13: 53756 | E13: USD | F13: Communication Services | G13: USA | H13: Internet Content & Information
B14: Satellite Individual Stocks | C14: META | D14: 36554 | E14: USD | F14: Communication Services | G14: USA | H14: Internet Content & Information
B15: Satellite Individual Stocks | C15: NVDA | D15: 37414 | E15: USD | F15: Technology | G15: USA | H15: Semiconductors
B16: Satellite Individual Stocks | C16: AAPL | D16: 47305 | E16: USD | F16: Technology | G16: USA | H16: Computer Manufacturing
... B27: Cash | C27: CHF Cash | D27: 85940 | E27: CHF | F27: Cash | G27: Switzerland | H27: Strategic Reserve
B31: Same theme | C31: AIFS | D31: 28000 | E31: EUR | F31: AI Infrastructure | H31: VVSM is alternative
C32: VVSM | D32: 28000 | E32: EUR | F32: Semiconductor
C33: RBOT | D33: 33000 | E33: USD | F33: Robotics
C34: EMQQ | D34: 33000 | E34: USD | F34: EM Internet
C35: NATO | D35: 33000 | E35: USD | F35: Future of defense | H35: DFENG
C36: BTEC | D36: 33000 | E36: USD | F36: Biotech
C37: NLR | D37: 33000 | E37: USD | F37: Nuclear | H37: NUKL
C38: GRID | D38: 28000 | E38: EUR | F38: Infrastructure
C40: DFEN | D40: 28000 | E40: EUR | F40: Defense | H40: Leveraged. No!
C41: KWEB | D41: 33000 | E41: USD | F41: China Internet
C44: QQQ
C45: IBB | D45: instead of XLV

Sheet Option strategies
B1: Description | C1: Type | D1: Profit driver | E1: Drainers | F1: Volatility | G1: Adjustments | H1: Comments
A2: Debit spreads | B2: Extension of single long options. Buy long and sell short option. | C2: Directional | D2: Price change | E2: Time decay | F2: buy at low volatility as price grows if high volatility | G2: Take part profit if arises, close if goes against. | H2: better than single option as reduces time decay, moderates delta and vega
A3: Credit speads | B3: Extension of single short options. Sell short option and buy long option. | C3: Directional | D3: Price change, time decay | E3: Volatility | F3: sell at high as prices at max | G3: if goes against, buy in the money option for next month to reduce time decay as in the money and longer
A4: Straddle/Strangle (debit) | B4: Buy in the money put and call for straddle and move them apart for strangle which reduces risk and price, yet, slower to generate profit. | C4: Non-directional, assumes that stock moves fast in any direction. | D4: Fast move of the price needed, delta drives profitability. Also, vega increase can help. | E4: Very big time decay issue as two long options. Needs to generate profit in few days and move out fast. Volatility reduction is also massive potential drainer, if starts to go down. So, ideally put it when volatility low. | F4: Works for high volatility environment with fast and strong moves. | G4: If stock grows, volatility drops and it drains profit. Can be reduced by selling a put out of the money. Yet, will increase delta and can hurt if stock starts dropping. Also reduces time decay, which is good. Yet, this adjustment limits upside in case of drop of price due to short put. Similarly, could put a short call in addition or as a standalon, to pick up more premium or mitigate move down. | H4: Strangles not really recommended as even more difficult to make a profit.
A5: Iron condor (credit) | B5: Two credit spreads one with put and one with call. Typically, idea to have delta neutral position at the start with probability below 20%. Legs are equally spaced on both sides. | C5: Non-directional, assumes that stock does not move far and stays in the current corridor. | D5: Time decay is the driver as have two short options. | E5: Volatility increase will drain it, as well as move of price close to the limits. | F5: preferably to have volatility going down. | G5: Similar to credit spreads. Addtional option is to roll a stuggling side to next month.
A6: Calendar (debit) | B6: Sell at the money put or call closer to today and buy at the money put or call with longer period. No difference to use put or call. Starts delta neutral. | C6: Non-directional, profits from limited move, similar to the condor. | D6: Time decay on a short option. Yet, the price should not go very far from initial price to make a profit. | E6: Price moving out of original price to the limits. Volatility decrease. | G6: Double calendar to expant the profit zone at the struggling end. Can do triple and quadrouple as well. | H6: Low probability of profit! Requires stock to stay in the narrow range.
A7: Diagonal (debit) | B7: Similar to calendar but back month option is out of the money (bying). It reduces the cost of bying.We also reduce slightly positive Vega as going out of the money. It also creates slight directional and delta biases. Still, it is Theta positive and Vega positive. Same as for diagonal, can use either puts or calls. No major difference. | C7: Mostly non-directional. | D7: Also, as above, time decay strategy. And, assumes the price does not go too far from original level. Otherwise, needs adjustment. | E7: Price moving out of original at the money price. Volatility decrease but a bit less with the calendar. | F7: If volatility drops, we lose profit as the positiion is Vega positive. | G7: Similar adjustments to a calendar, can adjust to double diagonal. Might also roll it but complicated. | H7: Relatively exotic straetegy and may be somewhat difficult to control. Might not be worth it.
A8: Back spreads (debit) | B8: Has more long options than short options, typical rations are 2:1, 3:2 but can be more creative. If expect upside, use Calls, Puts for expected downside. Example, sell 10 at the money calls and buy 20 out of the money calls. Depending on chosen 2nd call strike, can have upsides at both ends except for the middle. | C8: Non-directonal but assimetric. Can have unlimited upside and limited downside. depends on how it is constructed. | D8: Fast and significant move to one of the directions. | E8: Time decay as have more long options than short. If stays in the middle zone will start generating losses. | F8: Volatility strategy and needs a move in a week or two, otherwise will have issue with time decay. | H8: Volatility strategy. Should be a credit spread, so strikes need to be selected appropriately. Need to pick strike prices so that we do not have too much loss with the white line, otherwise would be difficult to get out of valley of deaf.
A9: Ration spreads (credit) | B9: Opposite to backspread and have more short options than long options. Can be done with both calls and puts. Has unlimited loss at one side. | D9: Time decay | E9: Moves of prices in undesirable direction. | F9: as this short skewed, has negative Vega and loses if volativilty increases. | H9: Not most attactive strategy due to inlimited loss profile and high requirements to margin. It is still a credit spread and we get immediate credit. Both strikes can be in the money or close.
A10: Butterfly (debit) | B10: Bull spread + Bear spread with short options at the money. Low risk and high reward but in specific conditions. Mainly makes money only in last 15 days before expiry. The strategy is relatively low probability. Works best with 30-40 days before expiry. Can be done with both puts and calls. Example: sell 20 ATM calls, buy 10 ITM call and 10 OTM calls equally distant. | C10: Non-directional. | D10: Time decay. As two ATM options, they lose value most in last 15 days. | E10: Move out of narrow corridor of profit for the price. | F10: Vega negative - volatility drops we have a profit. | G10: Not easy to adjust | H10: High reward, low risk but low probability. Exotic strategy which may not be the best. There is one specific application that can be useful. In case Iron condor goes into trouble, butterfly can be used as a hedge for the condor. Butterfly added at the iron condor strike price if the side in trouble could convert a loss into a profit. Can put it with the shorter expiry dates vs condor to respect 15 days.
A13: Option walls | B13: https://www.barchart.com/options/open-interest-change/increase | C13: TNET call and put at 130 on 15/09 with price on 28/08 at 105

Sheet StockRover
A1: Period/Screener | B1: Relative strength | C1: Small cap | D1: Capital Effic. | E1: CAN SLIM | F1: 17 factors | G1: Safe performers | H1: Momentum | I1: Fair value | J1: Strong buys | K1: GARP | L1: Revert to mean | M1: EG Screener | N1: Vintage value inv | O1: Top 50 Revenue | P1: Large cap value | Q1: Top stocks | R1: High shareholder yield | S1: Value + Dividends | T1: Dividends+Gr free cashflow | U1: Buffetology Insp
A2: Jan'22 - Jan'24 | B2: 1.33 | C2: 2.14 | D2: 1.23 | E2: 0.633 | F2: 0.71 | G2: 1.19 | H2: 1.21 | I2: 1.4 | J2: 1.57 | M2: 0.35 | N2: 0.48 | O2: 0.28 | P2: 0.45 | Q2: 1.33 | R2: 0.45 | S2: 0.36 | T2: 0.51 | U2: 0.207
A3: YTD | B3: 0.64 | C3: 0.73 | D3: 0.1 | E3: 0.4 | F3: 0.24 | G3: 0.21 | H3: 0.57 | I3: -0.13 | J3: 0.03 | M3: 0.21 | N3: 0.05 | O3: 0.14 | P3: 0.11 | Q3: 0.21 | R3: 0.07 | S3: 0.1 | T3: 0.06 | U3: 0.04
A4: 1 year | B4: 1.54 | C4: 2.39 | D4: 0.4 | E4: 0.91 | F4: 0.67 | G4: 0.64 | H4: 1.42 | I4: 0.35 | J4: 0.18 | M4: 0.59 | N4: 0.47 | O4: 0.34 | P4: 0.29 | Q4: 0.89 | R4: 0.23 | S4: 0.26 | T4: 0.3 | U4: 0.17
A5: 2 years | B5: 2.92 | C5: 4.41 | D5: 1.25 | E5: 1.61 | F5: 1.26 | G5: 1.29 | H5: 2.6 | I5: 1.06 | J5: 1.14 | M5: 1.1 | N5: 1.21 | O5: 0.82 | P5: 0.6 | Q5: 1.59 | R5: 0.46 | S5: 0.4 | T5: 0.46 | U5: 0.41
A6: 5 year | B6: 12.21 | C6: 13.31 | D6: 7.39 | E6: 3.14 | F6: 4.28 | G6: 3.6 | H6: 10.05 | I6: 32.19 | J6: 11.37 | M6: 2.49 | N6: 3.06 | O6: 2.4 | P6: 1.36 | Q6: 5.73 | R6: 1.43 | S6: 1.88 | T6: 1.46 | U6: 1.47
A7: No of tickers | B7: 147 | C7: 49 | D7: 45 | E7: 1 | F7: 50 | G7: 0 | H7: 109 | I7: 50 | J7: 85 | M7: 15
B8: Find stocks with strong relative strength defined as consistent outperformance vs. the S&P 500.
C9: Small caps with inexpensive valuation; good ROE with an upward trend; ranked according to sales and earnings combined with low valuation
D10: A screener composed of Stock Rover capital efficiency metrics.
B12: 1 | C12: 1 | D12: 1 | E12: 1 | F12: 1 | G12: 1 | H12: 1 | I12: 1 | J12: 1 | K12: 1 | L12: 1 | M12: 1 | N12: 1 | O12: 1
B13: 1 | C13: 1 | D13: 1 | E13: 1 | F13: 1 | G13: 1 | H13: 1 | I13: 1 | J13: 1 | K13: 1 | L13: 1 | M13: 1 | N13: 1 | O13: 1
A15: 15/12/2024 v1
A16: 15/12/2024 v2
A17: 21/12/2024 v2
A18: 21/12/2024 v1
A20: 23/01/2025 v2
A21: 23/01/2025 v1

Sheet Citi funds
A1: Fund | B1: ISIN | C1: Currency | D1: Value | E1: Value $ 2022 | F1: Value $ Nov'23 | G1: Value $ May'24 | H1: Value Aug'24 | I1: Value Jan'25 | J1: Value Oct'25
A2: ALLIANZ GLOBAL ARTIFICIAL INTELLIGENCE AT EUR HEDGED ACC | B2: LU1548497772 | C2: EUR | D2: 14993 | E2: 16200 | F2: =17772*1.08 -> 19193.76 | G2: 21203 | H2: 22726 | I2: 24495 | J2: =24060*1.16 -> 27909.6
A3: ALLIANZ EUROPE EQUITY GROWTH AT USD HEDGED ACC | B3: LU0857590862 | C3: USD | D3: 32951 | E3: =D3 -> 32951 | F3: 31817 | G3: 36118 | H3: 37185 | I3: 37938 | J3: 34295
A4: ALLIANZ ORIENTAL INCOME AT USD ACC | B4: LU0348784397 | C4: USD | D4: 9635 | E4: =D4 -> 9635 | F4: 9999 | G4: 10154 | H4: 10542 | I4: 9919 | J4: 13881
A5: ALLIANZ INCOME AND GROWTH AM USD DIS | B5: LU0820561818 | C5: USD | D5: 21362 | E5: =D5 -> 21362 | F5: 21820 | G5: 22415 | H5: 22744 | I5: 23302 | J5: 23371
A6: FRANKLIN TECHNOLOGY A USD ACC | B6: LU0109392836 | C6: USD | D6: 59409 | E6: =D6 -> 59409 | F6: 69997 | G6: 82856 | H6: 89152 | I6: 102869 | J6: 116776
A7: JPMORGAN GLOBAL HEALTHCARE D USD ACC | B7: LU0432979960 | C7: USD | D7: 27365 | E7: =D7 -> 27365 | F7: 26670 | G7: 28636 | H7: 31512 | I7: 28000 | J7: 26630
A8: SCHRODER ISF FRONTIER MARKETS EQUITY A USD ACC | B8: LU0562313402 | C8: USD | D8: 10992 | E8: =D8 -> 10992 | F8: 12516 | G8: 14701 | H8: 15642 | I8: 15686 | J8: 19277
A9: SCHRODER ISF GLOBAL DIVIDEND MAXIMISER A USD DIS | B9: LU0306807586 | C9: USD | D9: 13325 | E9: =D9 -> 13325 | F9: 12972 | G9: 12959 | H9: 13404 | I9: 12808 | J9: 14605
E10: =SUM(E2:E9) -> 191239 | F10: =SUM(F2:F9) -> 204984.76 | G10: =SUM(G2:G9) -> 229042 | H10: =SUM(H2:H9) -> 242907 | I10: =SUM(I2:I9) -> 255017 | J10: =SUM(J2:J9) -> 276744.6
J11: =J10/E10-1 -> 0.44711382
J12: =J10-E10 -> 85505.6
A21: Product | B21: Short name | C21: Theme | D21: Management style | E21: Selection mode | F21: Currency
A22: UBS (Lux) Strategy Fund - Fixed Income (CHF) Q-acc (UBF) ISIN: LU1240799699 | B22: Focus Global Fixed Income | C22: Global Sustainability | D22: Actively managed | E22: As simple as possible Theme-based | F22: CHF
A23: UBS (Lux) Strategy SICAV - Income (CHF) Q-acc (UBF) ISIN: LU1240800968 | B23: Focus Global Income | C23: Global Sustainability | D23: Actively managed | E23: As simple as possible Theme-based | F23: CHF
A24: UBS (CH) Equity Fund - Mid Caps Switzerland (CHF) QL ISIN: CH0560899525 | B24: Stocks - Switzerland | C24: Switzerland | D24: Actively managed | E24: Theme-based | F24: CHF
A25: UBS (Lux) Strategy Fund - Yield (CHF) Q-acc ISIN: LU0941351768 | B25: Focus - Global Yield | C25: Global Sustainability | D25: Actively managed | E25: As simple as possible Theme-based | F25: CHF
A26: UBS (Lux) Strategy Fund - Balanced (CHF) Q-acc ISIN: LU0941351099 | B26: Focus - Global Balanced | C26: Global Sustainability | D26: Actively managed | E26: As simple as possible Theme-based | F26: CHF
A27: UBS (Lux) Strategy Fund - Growth (CHF) Q-acc ISIN: LU0941351412 | B27: Focus - Global Growth | C27: Global Sustainability | D27: Actively managed | E27: As simple as possible Theme-based | F27: CHF
A28: UBS (Lux) Strategy Fund - Equity (CHF) Q-acc ISIN: LU1240799343 | B28: Focus - Global Equities | C28: Global Sustainability | D28: Actively managed | E28: As simple as possible Theme-based | F28: CHF
A29: UBS (CH) Vitainvest - Passive 25 Sustainable Q ISIN: CH1110134124 | B29: Focus - Passive Yield | C29: Global Sustainability | D29: Passively managed | E29: As simple as possible Theme-based | F29: CHF
A30: UBS (CH) Vitainvest - Passive 50 Sustainable Q ISIN: CH1110134132 | B30: Focus - Passive Balanced | C30: Global Sustainability | D30: Passively managed | E30: As simple as possible Theme-based | F30: CHF
A31: UBS (CH) Vitainvest - Passive 75 Sustainable Q ISIN: CH1110134140 | B31: Focus - Passive Growth | C31: Global Sustainability | D31: Passively managed | E31: As simple as possible Theme-based | F31: CHF
A32: UBS (CH) Vitainvest - Passive 100 Sustainable Q ISIN: CH1110134157 | B32: Focus - Passive Equities | C32: Global Sustainability | D32: Passively managed | E32: As simple as possible Theme-based | F32: CHF
... A53: UBS Core MSCI World UCITS ETF ISIN: IE000N6LBS91 | B53: Global Large Cap ETF | C53: Global | D53: Passively managed | E53: Theme-based | F53: CHF

Sheet PCA
B1: SGMS | C1: PK | D1: MTZ | E1: DFS | F1: UAA | G1: OSK | H1: EVR | I1: DVN | J1: DKS | K1: LSI | L1: CROX | M1: MPWR | N1: PXD | O1: AA | P1: CVS | Q1: CMA | R1: WTFC | S1: SGMS | T1: PK | U1: MTZ | V1: DFS | W1: UAA | X1: OSK | Y1: EVR | Z1: DVN | AA1: DKS | AB1: LSI | AC1: CROX | AD1: MPWR | AE1: PXD | AF1: AA | AG1: CVS | AH1: CMA | AI1: WTFC | AJ1: Invested | AK1: Received
A2: 44228 | B2: 20 | C2: 47 | D2: 9 | E2: 9 | F2: 44 | S2: =(14*40.42+5*40.395+1*40.4)/(14+5+1) -> 40.41275 | T2: =(21*16.575+25*16.575+1*16.575)/47 -> 16.575 | U2: 79.905 | V2: 82.33 | W2: 17.815 | AJ2: =SUMPRODUCT(B2:F2,S2:W2) -> 3831.255
B3: 14 | C3: 30 | D3: 10 | E3: 9 | F3: 30 | S3: 49.595 | T3: 21.765 | U3: 90.5 | V3: 97.63 | W3: 23.535 | AJ3: =SUMPRODUCT(B3:F3,S3:W3) -> 3837
A4: 44292 | B4: 17 | C4: 18 | D4: 4 | E4: 3 | F4: 15 | S4: 40.91 | T4: 21.65 | U4: 97.435 | V4: 98.57 | W4: 23.255 | AJ4: =SUMPRODUCT(B4:F4,S4:W4) -> 2119.445
A5: 44319 | B5: 4 | C5: 42 | D5: 6 | E5: 6 | F5: 40 | S5: 57.45 | T5: 22.885 | U5: =(5*106.625+1*106.625)/6 -> 106.625 | V5: 115.39 | W5: 24.205 | AJ5: =SUMPRODUCT(B5:F5,S5:W5) -> 3491.26
A6: 44348 | B6: -55 | C6: -137 | F6: -129 | S6: 74.205 | T6: 21.145 | U6: 117.55 | V6: 120.56 | W6: 22.94 | AK6: =SUMPRODUCT(B6:F6,S6:W6) -> -9937.4
A7: 44348 | G7: 24 | H7: 22 | I7: 111 | X7: 132.095 | Y7: 146.91 | Z7: 29.695 | AJ7: =SUMPRODUCT(B7:I7,S7:Z7) -> 9698.445
A8: 44397 | D8: 6 | E8: 2 | G8: 6 | H8: 5 | I8: 30 | U8: 98.12 | V8: 117.85 | X8: 114.495 | Y8: 127.585 | Z8: 24.96 | AJ8: =SUMPRODUCT(B8:I8,S8:Z8) -> 2898.115
A9: 44426 | D9: -35 | E9: -29 | U9: 90.66 | V9: 131.43 | X9: 114.89 | Z9: 26.94 | AK9: =SUMPRODUCT(B9:F9,S9:W9) -> -6984.57
A10: 44431 | J10: 10 | K10: 10 | AA10: 112.215 | AB10: 121.85 | AJ10: =SUMPRODUCT(B10:K10,S10:AB10) -> 2340.65
A11: 44447 | J11: 10 | K11: 10 | AA11: 140.74 | AB11: 128.415 | AJ11: =SUMPRODUCT(B11:K11,S11:AB11) -> 2691.55
A12: 44474 | G12: 19 | H12: 8 | J12: 21 | K12: 25 | X12: =(8*106.715+4*106.71+4*106.725+3*106.505)/19 -> 106.68289 | Y12: 144.265 | AA12: 123.23 | AB12: =(5*114.56+20*114.63)/25 -> 114.616 | AJ12: =SUMPRODUCT(B12:K12,S12:AB12) -> 8634.325
A13: 44474 | I13: -141 | Z13: 39.225 | AD13: 470.01 | AK13: =Z13*I13 -> -5530.725
A14: 44474 | L14: 19 | M14: 6 | Z14: 39.225 | AC14: 138.075 | AD14: 470.01 | AJ14: =SUMPRODUCT(B14:M14,S14:AD14) -> 5443.485
A15: 44491 | L15: 19 | M15: 4 | AC15: 153.825 | AD15: 522.26 | AJ15: =SUMPRODUCT(B15:M15,S15:AD15) -> 5011.715
A16: 44503 | G16: 8 | H16: 7 | J16: 8 | K16: 3 | L16: 0 | M16: 2 | X16: =(112.015*7+111.98)/8 -> 112.01063 | Y16: =(153.895*6+153.96)/7 -> 153.90429 | AA16: 131.245 | AB16: 132.795 | AD16: 538.385 | AJ16: =SUMPRODUCT(B16:M16,S16:AD16) -> 4498.53
A17: 44524 | H17: 2 | J17: 2 | K17: 1 | X17: 116.26 | Y17: 147.92 | AA17: 126.69 | AB17: 134.515 | AD17: 548.97 | AJ17: =SUMPRODUCT(B17:M17,S17:AD17) -> 683.735
A18: 44543 | G18: -2 | K18: -7 | X18: 110.44 | AB18: 143.01 | AK18: =G18*X18+K18*AB18 -> -1221.95
A19: 44543 | H19: 2 | J19: 7 | Y19: 132.74 | AA19: 104.55 | AJ19: =SUMPRODUCT(B19:M19,S19:AD19) -> 997.33
A20: 44592 | K20: -42 | AB20: 134 | AK20: =G20*X20+K20*AB20 -> -5628
A21: 44594 | N21: 13 | O21: 50 | P21: 27 | Q21: 31 | R21: 30 | AE21: 221.2 | AF21: 58.975 | AG21: 108.775 | AH21: 95.05 | AI21: 98.84773 | AJ21: =SUMPRODUCT(B21:R21,S21:AI21) -> 14673.257
A22: 44614 | L22: 30 | AC22: 80.39 | AJ22: =SUMPRODUCT(B22:R22,S22:AI22) -> 2411.7
A23: 44615 | L23: 32 | AC23: 81.175 | AJ23: =SUMPRODUCT(B23:R23,S23:AI23) -> 2597.6
A24: 44785 | M24: -12 | AD24: 528.65 | AK24: =AD24*M24 -> -6343.8
A25: 44802 | N25: -13 | O25: -50 | P25: -27 | Q25: -31 | R25: -30 | AE25: 265.15 | AF25: 56.28 | AG25: 100.77 | AH25: 81.44 | AI25: 85.42 | AK25: =SUMPRODUCT(B25:R25,S25:AI25) -> -14068.98
A26: 44958 | J26: -58 | AA26: 134.15 | AK26: =SUMPRODUCT(B26:R26,S26:AI26) -> -7780.7
A27: 44975 | L27: -100 | X27: 91.15 | Y27: 130.74 | AC27: 130 | AK27: =SUMPRODUCT(B27:R27,S27:AI27) -> -13000
A28: 45286 | H28: -46 | Y28: 171.07 | AK28: =SUMPRODUCT(B28:R28,S28:AI28) -> -7869.22
A29: 45425 | G29: -55 | X29: 121.715 | AK29: =SUMPRODUCT(B29:R29,S29:AI29) -> -6694.325
S30: Stock value | T30: Total invested - Curre Stock | U30: Outflow | V30: Months | X30: Yearly return | Y30: Abs return
A31: Qty | B31: =SUM(B2:B17) -> 0 | C31: =SUM(C2:C17) -> 0 | D31: =SUM(D2:D17) -> 0 | E31: =SUM(E2:E17) -> 0 | F31: =SUM(F2:F17) -> 0 | G31: =SUM(G2:G30) -> 0 | H31: =SUM(H2:H30) -> 0 | I31: =SUM(I2:I30) -> 0 | J31: =SUM(J2:J30) -> 0 | K31: =SUM(K2:K30) -> 0 | L31: =SUM(L2:L30) -> 0 | M31: =SUM(M2:M30) -> 0 | N31: =SUM(N2:N30) -> 0 | ... R31: =SUM(R2:R30) -> 0
A32: Amt | B32: =B31*S17 -> 0 | C32: =C31*T17 -> 0 | D32: =D31*U17 -> 0 | E32: =E31*V17 -> 0 | F32: =F31*W17 -> 0 | G32: =G31*X27 -> 0 | H32: =H31*Y27 -> 0 | I32: =I31*Z27 -> 0 | J32: =J31*AA27 -> 0 | K32: =K31*AB27 -> 0 | L32: =L31*AC27 -> 0 | M32: =M31*AD27 -> 0 | N32: =N31*AE27 -> 0 | ... R32: =R31*AI27 -> 0 | S32: =sum(B32:R32) -> 0 | T32: =SUM(AJ2:AJ27)-S32 -> 75859.397 | U32: =sum(AK2:AK27) -> -70496.125 | V32: =(MAX(A2:A30)-MIN(A2:A30))/30.4167 -> 39.353382 | X32: =(((-U32)/T32)^(1/(V32)))^12-1 -> -0.022110489 | Y32: =-(T32+U32) -> -5363.2719
A33: Current % | B33: =B32/$S$32 -> #DIV/0! | C33: =C32/$S$32 -> #DIV/0! | D33: =D32/$S$32 -> #DIV/0! | E33: =E32/$S$32 -> #DIV/0! | F33: =F32/$S$32 -> #DIV/0! | G33: =G32/$S$32 -> #DIV/0! | H33: =H32/$S$32 -> #DIV/0! | I33: =I32/$S$32 -> #DIV/0! | ... S33: =S32/$S$32 -> #DIV/0!
A34: Target % | B34: =100/countif(B32:M32,">0") -> #DIV/0! | C34: =B34 -> #DIV/0! | D34: =C34 -> #DIV/0! | E34: =D34 -> #DIV/0! | F34: =E34 -> #DIV/0! | N34: 0.2 | O34: 0.2 | P34: 0.2 | Q34: 0.2 | R34: 0.2
G35: -867
M37: OSK | N37: HES | O37: EPAM | P37: ON | Q37: CAH | R37: CI
M38: 55.1729 | N38: 24 | O38: 7 | P38: 44 | Q38: 44 | R38: 11
M39: 121.7 | N39: 128.86 | O39: 417.8 | P39: 70.28 | Q39: 69.538 | R39: 288.125
M40: =M38*M39 -> 6714.5419 | N40: =N38*N39 -> 3092.64 | O40: =O38*O39 -> 2924.6 | P40: =P38*P39 -> 3092.32 | Q40: =Q38*Q39 -> 3059.672 | R40: =R38*R39 -> 3169.375 | S40: =sum(N40:R40) -> 15338.607
A42: 45022 | M42: =SUMPRODUCT(G2:G27, X2:X27) -> 6559.43 | N42: 3370 | O42: 1649 | P42: 3320 | Q42: 3476 | R42: 3765 | S42: =sum(N42:R42) -> 15580 | T42: =S42/S40-1 -> 0.015737609
M43: =M40-M42 -> 155.11193 | N43: =N42-N40 -> 277.36 | O43: =O42-O40 -> -1275.6 | P43: =P42-P40 -> 227.68 | Q43: =Q42-Q40 -> 416.328 | R43: =R42-R40 -> 595.625 | S43: =sum(M43:R43) -> 396.50493
